Workbook
Name \Z: #REF!
Name \Z: #REF!
Name \Z: #REF!
Name \Z: #REF!
Name \Z: #REF!
Name \Z: #REF!
Name \Z: #REF!
Name \Z: #REF!
Name \Z: #REF!
Name \Z: #REF!
Name \Z: #REF!
Name \Z: #REF!
Name \Z: #REF!
Name \Z: #REF!
Name \Z: #REF!
Name \Z: #REF!
Name \Z: #REF!
Name \Z: #REF!
Name \Z: #REF!
Name \Z: #REF!
Name \Z: #REF!
Name \Z: #REF!
Name \Z: #REF!
Name \Z: #REF!
Name \Z: #REF!
Name \Z: #REF!
Name \Z: #REF!
Name \Z: #REF!
Name ________MTH06: [1]Paramter!$A$16:$A$27
Name _______MTH06: [1]Paramter!$A$16:$A$27
Name ______MTH06: [1]Paramter!$A$16:$A$27
Name _____MTH06: [2]Paramter!$A$16:$A$27
Name _____MTH06: [2]Paramter!$A$16:$A$27
Name _____MTH06: [2]Paramter!$A$16:$A$27
Name _____MTH06: [2]Paramter!$A$16:$A$27
Name _____MTH06: [2]Paramter!$A$16:$A$27
Name _____MTH06: [2]Paramter!$A$16:$A$27
Name _____MTH06: [2]Paramter!$A$16:$A$27
Name _____MTH06: [2]Paramter!$A$16:$A$27
Name _____MTH06: [2]Paramter!$A$16:$A$27
Name _____MTH06: [2]Paramter!$A$16:$A$27
Name _____MTH06: [2]Paramter!$A$16:$A$27
Name _____MTH06: [2]Paramter!$A$16:$A$27
Name _____MTH06: [2]Paramter!$A$16:$A$27
Name _____MTH06: [2]Paramter!$A$16:$A$27
Name _____MTH06: [2]Paramter!$A$16:$A$27
Name _____MTH06: [2]Paramter!$A$16:$A$27
Name _____MTH06: [2]Paramter!$A$16:$A$27
Name _____MTH06: [2]Paramter!$A$16:$A$27
Name _____MTH06: [2]Paramter!$A$16:$A$27
Name _____MTH06: [2]Paramter!$A$16:$A$27
Name _____MTH06: [2]Paramter!$A$16:$A$27
Name _____MTH06: [3]Paramter!$A$16:$A$27
Name _____MTH06: [3]Paramter!$A$16:$A$27
Name ____MTH06: [2]Paramter!$A$16:$A$27
Name ____MTH06: [2]Paramter!$A$16:$A$27
Name ____MTH06: [2]Paramter!$A$16:$A$27
Name ____MTH06: [2]Paramter!$A$16:$A$27
Name ____MTH06: [2]Paramter!$A$16:$A$27
Name ____MTH06: [2]Paramter!$A$16:$A$27

Sheet Account
A1: PRC编码 | B1: PRC名称 | C1: HK code | D1: HK Account Name | E1: 全名 | G1: 余额方向 | H1: 科目类别 | I1: 外币核算 | J1: 核算维度 | K1: 数据状态
A2: 1001 | B2: 库存现金 | E2: 库存现金 | F2: Cash On Hand | G2: 借方 | H2: 流动资产 | K2: 已审核
A3: 1002 | B3: 银行存款 | E3: 银行存款 | F3: Bank Deposit | G3: 借方 | H3: 流动资产 | I3: 所有币别 | K3: 已审核
A4: 1002.01 | B4: 【旭智资本】银行存款账户 | E4: 银行存款_【旭智资本】银行存款账户 | F4: ACPL Bank Account | G4: 借方 | H4: 流动资产 | I4: 所有币别 | K4: 已审核
A5: 1002.01.01 | B5: 汇丰银行-741-282-503-838 | E5: 银行存款_【旭智资本】银行存款账户_汇丰银行-741-282-503-838 | F5: HSBC Account 741-282-503-838 | G5: 借方 | H5: 流动资产 | I5: 所有币别 | K5: 已审核
A6: 1002.01.01.01 | B6: 【旭智资本】汇丰港元储蓄账户 3838 | E6: 银行存款_【旭智资本】银行存款账户_汇丰银行-741-282-503-838_【旭智资本】汇丰港元储蓄账户 3838 | F6: ACPL HSBC HKD Savings | G6: 借方 | H6: 流动资产 | I6: 所有币别 | K6: 已审核
A7: 1002.01.01.02 | B7: 【旭智资本】汇丰港元往来账户 3838 | E7: 银行存款_【旭智资本】银行存款账户_汇丰银行-741-282-503-838_【旭智资本】汇丰港元往来账户 3838 | F7: ACPL HSBC HKD Current | G7: 借方 | H7: 流动资产 | I7: 所有币别 | K7: 已审核
A8: 1002.01.01.03 | B8: 【旭智资本】汇丰外币储蓄账户 - 人民币 3838 | E8: 银行存款_【旭智资本】银行存款账户_汇丰银行-741-282-503-838_【旭智资本】汇丰外币储蓄账户 - 人民币 3838 | F8: ACPL HSBC RMB Savings | G8: 借方 | H8: 流动资产 | I8: 所有币别 | K8: 已审核
A9: 1002.01.01.04 | B9: 【旭智资本】汇丰外币储蓄账户 - 美元 3838 | E9: 银行存款_【旭智资本】银行存款账户_汇丰银行-741-282-503-838_【旭智资本】汇丰外币储蓄账户 - 美元 3838 | F9: ACPL HSBC USD Savings | G9: 借方 | H9: 流动资产 | I9: 所有币别 | K9: 已审核
A10: 1002.01.01.05 | B10: 【旭智资本】汇丰港元定期存款 | E10: 银行存款_【旭智资本】银行存款账户_汇丰银行-741-282-503-838_【旭智资本】汇丰港元定期存款 | F10: ACPL HSBC HKD Time Deposit | G10: 借方 | H10: 流动资产 | I10: 所有币别 | K10: 已审核
A11: 1002.02 | B11: 【旭智资本（香港）】银行存款账户 | E11: 银行存款_【旭智资本（香港）】银行存款账户 | F11: ACPLHK Bank Account | G11: 借方 | H11: 流动资产 | I11: 所有币别 | K11: 已审核
A12: 1002.02.01 | B12: 汇丰银行-741-269492-838 | E12: 银行存款_【旭智资本（香港）】银行存款账户_汇丰银行-741-269492-838 | F12: HSBC Account 741-269492-838 | G12: 借方 | H12: 流动资产 | I12: 所有币别 | K12: 已审核
A13: 1002.02.01.01 | B13: 【旭智资本（香港）】汇丰港元储蓄账户 2838 | E13: 银行存款_【旭智资本（香港）】银行存款账户_汇丰银行-741-269492-838_【旭智资本（香港）】汇丰港元储蓄账户 2838 | F13: ACPLHK HSBC HKD Savings | G13: 借方 | H13: 流动资产 | I13: 所有币别 | K13: 已审核
A14: 1002.02.01.02 | B14: 【旭智资本（香港）】汇丰港元活期账户 2838 | E14: 银行存款_【旭智资本（香港）】银行存款账户_汇丰银行-741-269492-838_【旭智资本（香港）】汇丰港元活期账户 2838 | F14: ACPLHK HSBC HKD Current | G14: 借方 | H14: 流动资产 | I14: 所有币别 | K14: 已审核
... A76: 1002.31.03.01 | B76: 【郴州景叶新能源】三湘 人民币一般户 4937 | E76: 银行存款_【郴州景叶新能源】银行存款账户_三湘银行账户_【郴州景叶新能源】三湘 人民币一般户 4937 | F76: Chenzhou Jingye SXB RMB GDA 4937 | G76: 借方 | H76: 流动资产 | I76: 所有币别 | K76: 已审核
A77: 1002.31.04 | B77: 兴业银行账户 | E77: 银行存款_【郴州景叶新能源】银行存款账户_兴业银行账户 | F77: 0 | G77: 借方 | H77: 流动资产 | I77: 所有币别 | K77: 已审核
A78: 1002.31.04.01 | B78: 【郴州景叶新能源】兴业 人民监管户 9000 | E78: 银行存款_【郴州景叶新能源】银行存款账户_兴业银行账户_【郴州景叶新能源】兴业 人民监管户 9000 | F78: Chenzhou Jingye CIB RMB RA 9000 | G78: 借方 | H78: 流动资产 | I78: 所有币别 | K78: 已审核
A79: 1002.32 | B79: 【旭智富能（成都）】银行存款账户 | E79: 银行存款_【旭智富能（成都）】银行存款账户 | F79: Albamen Foxpower(Chengdu) Bank Account | G79: 借方 | H79: 流动资产 | I79: 所有币别 | K79: 已审核
A80: 1002.33 | B80: 【旭智富联（鹤壁）】银行存款账户 | E80: 银行存款_【旭智富联（鹤壁）】银行存款账户 | F80: Albamen Foxconn (Hebi) Bank Account | G80: 借方 | H80: 流动资产 | I80: 所有币别 | K80: 已审核
A81: 1012 | B81: 其他货币资金 | E81: 其他货币资金 | F81: Other Monetary Fund | G81: 借方 | H81: 流动资产 | K81: 已审核
A82: 1101 | B82: 交易性金融资产 | E82: 交易性金融资产 | F82: Financial Assets Held For Trading | G82: 借方 | H82: 流动资产 | K82: 已审核
A83: 1101.01 | B83: 投资成本 | E83: 交易性金融资产_投资成本 | F83: Investment Cost | G83: 借方 | H83: 流动资产 | K83: 已审核
A84: 1101.01.01 | B84: 基金 | E84: 交易性金融资产_投资成本_基金 | F84: Fund Investments | G84: 借方 | H84: 流动资产 | K84: 已审核
A85: 1101.01.02 | B85: 股权 | E85: 交易性金融资产_投资成本_股权 | F85: Equity Investments | G85: 借方 | H85: 流动资产 | K85: 已审核
A86: 1101.01.02.01 | B86: 宜兴旭智投资咨询合伙企业（有限合伙） | E86: 交易性金融资产_投资成本_股权_宜兴旭智投资咨询合伙企业（有限合伙） | F86: Yixing Albamen Investment Consultancy Limited Partnership | G86: 借方 | H86: 流动资产 | K86: 已审核
A87: 1101.01.02.02 | B87: 旭智富能新能源（深圳）有限责任公司 | E87: 交易性金融资产_投资成本_股权_旭智富能新能源（深圳）有限责任公司 | F87: Albamen Foxpower Renewable Energy (Shenzhen) Company Limited | G87: 借方 | H87: 流动资产 | K87: 已审核
A88: 1101.01.03 | B88: 银行理财 | E88: 交易性金融资产_投资成本_银行理财 | F88: Treasury Products | G88: 借方 | H88: 流动资产 | K88: 已审核
A89: 1101.02 | B89: 公允价值变动 | E89: 交易性金融资产_公允价值变动 | F89: Changes In Fair Value | G89: 借方 | H89: 流动资产 | K89: 已审核
A90: 1101.02.01 | B90: 基金 | E90: 交易性金融资产_公允价值变动_基金 | F90: Fund Investments | G90: 借方 | H90: 流动资产 | K90: 已审核
A91: 1101.02.02 | B91: 股权 | E91: 交易性金融资产_公允价值变动_股权 | F91: Equity Investments | G91: 借方 | H91: 流动资产 | K91: 已审核
A92: 1101.02.02.01 | B92: 宜兴旭智投资咨询合伙企业（有限合伙） | E92: 交易性金融资产_公允价值变动_股权_宜兴旭智投资咨询合伙企业（有限合伙） | F92: Yixing Albamen Investment Consultancy Limited Partnership | G92: 借方 | H92: 流动资产 | K92: 已审核
... A94: 1101.02.03 | B94: 银行理财 | E94: 交易性金融资产_公允价值变动_银行理财 | F94: Treasury Products | G94: 借方 | H94: 流动资产 | K94: 已审核
A95: 1121 | B95: 应收票据 | E95: 应收票据 | F95: Bills Receivables | G95: 借方 | H95: 流动资产 | I95: 所有币别 | J95: 客户 | K95: 已审核
A96: 1122 | B96: 应收账款 | E96: 应收账款 | F96: Accounts Receivables | G96: 借方 | H96: 流动资产 | I96: 所有币别 | J96: 客户 | K96: 已审核
A97: 1122.01 | B97: 咨询费收入 | E97: 应收账款_咨询费收入 | F97: Entities | G97: 借方 | H97: 流动资产 | I97: 所有币别 | J97: 客户 | K97: 已审核
A98: 1122.02 | B98: 管理费收入 | E98: 应收账款_管理费收入 | F98: Individual | G98: 借方 | H98: 流动资产 | I98: 所有币别 | J98: 客户 | K98: 已审核
A99: 1122.03 | B99: 售电收入 | E99: 应收账款_售电收入 | F99: Electricity Sales Revenue | G99: 借方 | H99: 流动资产 | J99: 客户 | K99: 已审核
A100: 1122.03.01 | B100: 暂估结算电费 | E100: 应收账款_售电收入_暂估结算电费 | F100: Estimated Electricity | G100: 借方 | H100: 流动资产 | J100: 客户 | K100: 已审核
A101: 1122.03.02 | B101: 实际结算电费 | E101: 应收账款_售电收入_实际结算电费 | F101: Actuai Electricity | G101: 借方 | H101: 流动资产 | J101: 客户 | K101: 已审核
A102: 1123 | B102: 预付账款 | E102: 预付账款 | F102: Prepayments | G102: 借方 | H102: 流动资产 | I102: 所有币别 | J102: 供应商 | K102: 已审核
A103: 1123.01 | B103: 单位 | E103: 预付账款_单位 | F103: Entities | G103: 借方 | H103: 流动资产 | I103: 所有币别 | J103: 供应商 | K103: 已审核
A104: 1123.02 | B104: 个人 | E104: 预付账款_个人 | F104: Individual | G104: 借方 | H104: 流动资产 | I104: 所有币别 | J104: 供应商 | K104: 已审核
A105: 1131 | B105: 应收股利 | E105: 应收股利 | F105: Dividends Receivables | G105: 借方 | H105: 流动资产 | I105: 所有币别 | J105: 其他往来单位 | K105: 已审核
A106: 1132 | B106: 应收利息 | E106: 应收利息 | F106: Interest Receivables | G106: 借方 | H106: 流动资产 | I106: 所有币别 | J106: 其他往来单位 | K106: 已审核
A107: 1221 | B107: 其他应收款 | E107: 其他应收款 | F107: Other Receivables | G107: 借方 | H107: 流动资产 | I107: 所有币别 | J107: 客户 | K107: 已审核
A108: 1221.01 | B108: 单位 | E108: 其他应收款_单位 | F108: Entities | G108: 借方 | H108: 流动资产 | I108: 所有币别 | J108: 客户 | K108: 已审核
A109: 1221.02 | B109: 个人 | E109: 其他应收款_个人 | F109: Individual | G109: 借方 | H109: 流动资产 | I109: 所有币别 | J109: 客户 | K109: 已审核
A110: 1221.03 | B110: 多流水性质过渡科目 | E110: 其他应收款_多流水性质过渡科目 | F110: Multi-Transaction Nature Clearing Account | G110: 借方 | H110: 流动资产 | I110: 所有币别 | J110: 客户 | K110: 已审核
A111: 1221.04 | B111: 重能内部存款 | E111: 其他应收款_重能内部存款 | F111: Sany Internal Deposit | G111: 借方 | H111: 流动资产 | I111: 所有币别 | J111: 客户 | K111: 已审核
A112: 1231 | B112: 坏账准备 | E112: 坏账准备 | F112: Allowance For Doubtful Accounts | G112: 贷方 | H112: 流动资产 | K112: 已审核
A113: 1321 | B113: 代理业务资产 | E113: 代理业务资产 | F113: Agency Business Assets | G113: 借方 | H113: 流动资产 | K113: 已审核
A114: 1401 | B114: 材料采购 | E114: 材料采购 | F114: Material Procurement | G114: 借方 | H114: 流动资产 | K114: 已审核
A115: 1402 | B115: 在途物资 | E115: 在途物资 | F115: Goods In Transit | G115: 借方 | H115: 流动资产 | K115: 已审核
A116: 1403 | B116: 原材料 | E116: 原材料 | F116: Raw Materials | G116: 借方 | H116: 流动资产 | K116: 已审核
A117: 1404 | B117: 材料成本差异 | E117: 材料成本差异 | F117: Material Cost Variance | G117: 借方 | H117: 流动资产 | K117: 已审核
A118: 1405 | B118: 库存商品 | E118: 库存商品 | F118: Merchandise Inventory | G118: 借方 | H118: 流动资产 | K118: 已审核
A119: 1406 | B119: 发出商品 | E119: 发出商品 | F119: Goods Shipped | G119: 借方 | H119: 流动资产 | K119: 已审核
A120: 1407 | B120: 商品进销差价 | E120: 商品进销差价 | F120: Gross Margin On Sales | G120: 贷方 | H120: 流动资产 | K120: 已审核
A121: 1408 | B121: 委托加工物资 | E121: 委托加工物资 | F121: Consigned Processing Materials | G121: 借方 | H121: 流动资产 | K121: 已审核
A122: 1411 | B122: 周转材料 | E122: 周转材料 | F122: Revolving Materials | G122: 借方 | H122: 流动资产 | K122: 已审核
A123: 1462 | B123: 合同资产 | E123: 合同资产 | F123: Contract Assets | G123: 借方 | H123: 流动资产 | K123: 已审核
... A222: 2101.02 | B222: 公允价值变动 | E222: 交易性金融负债_公允价值变动 | F222: Changes In Fair Value | G222: 贷方 | H222: 流动负债 | K222: 已审核
A223: 2201 | B223: 应付票据 | E223: 应付票据 | F223: Notes Payable | G223: 贷方 | H223: 流动负债 | I223: 所有币别 | J223: 供应商 | K223: 已审核
A224: 2202 | B224: 应付账款 | E224: 应付账款 | F224: Accounts Payables | G224: 贷方 | H224: 流动负债 | I224: 所有币别 | J224: 供应商 | K224: 已审核
A225: 2202.01 | B225: 单位 | E225: 应付账款_单位 | F225: Entities | G225: 贷方 | H225: 流动负债 | I225: 所有币别 | J225: 供应商 | K225: 已审核
A226: 2202.02 | B226: 个人 | E226: 应付账款_个人 | F226: Individual | G226: 贷方 | H226: 流动负债 | I226: 所有币别 | J226: 供应商 | K226: 已审核
A227: 2203 | B227: 预收账款 | E227: 预收账款 | F227: Receipt In Advance | G227: 贷方 | H227: 流动负债 | I227: 所有币别 | J227: 客户 | K227: 已审核
A228: 2203.01 | B228: 单位 | E228: 预收账款_单位 | F228: Entities | G228: 贷方 | H228: 流动负债 | I228: 所有币别 | J228: 客户 | K228: 已审核
A229: 2203.02 | B229: 个人 | E229: 预收账款_个人 | F229: Individual | G229: 贷方 | H229: 流动负债 | I229: 所有币别 | J229: 客户 | K229: 已审核
A230: 2204 | B230: 合同负债 | E230: 合同负债 | F230: Contract Liabilities | G230: 贷方 | H230: 流动负债 | K230: 已审核
A231: 2211 | B231: 应付职工薪酬 | E231: 应付职工薪酬 | F231: Employee Compensation Payable | G231: 贷方 | H231: 流动负债 | K231: 已审核
A232: 2211.01 | B232: 职工工资 | E232: 应付职工薪酬_职工工资 | F232: Employee Wages | G232: 贷方 | H232: 流动负债 | K232: 已审核
A233: 2211.02 | B233: 职工奖金 | E233: 应付职工薪酬_职工奖金 | F233: Employee Bonuses | G233: 贷方 | H233: 流动负债 | K233: 已审核
A234: 2211.03 | B234: 劳务报酬 | E234: 应付职工薪酬_劳务报酬 | F234: Remuneration For Services | G234: 贷方 | H234: 流动负债 | K234: 已审核
A235: 2211.04 | B235: 职工福利 | E235: 应付职工薪酬_职工福利 | F235: Employee Welfare | G235: 贷方 | H235: 流动负债 | K235: 已审核
A236: 2211.05 | B236: 社会保险费 | E236: 应付职工薪酬_社会保险费 | F236: Social Insurance Premiums | G236: 贷方 | H236: 流动负债 | K236: 已审核
A237: 2211.06 | B237: 住房公积金 | E237: 应付职工薪酬_住房公积金 | F237: Housing Provident Fund | G237: 贷方 | H237: 流动负债 | K237: 已审核
A238: 2211.07 | B238: 工会经费 | E238: 应付职工薪酬_工会经费 | F238: Union Funding | G238: 贷方 | H238: 流动负债 | K238: 已审核
A239: 2211.08 | B239: 职工教育经费 | E239: 应付职工薪酬_职工教育经费 | F239: Employee Education Expenses | G239: 贷方 | H239: 流动负债 | K239: 已审核
A240: 2211.09 | B240: 非货币性福利 | E240: 应付职工薪酬_非货币性福利 | F240: Non-Monetary Benefits | G240: 贷方 | H240: 流动负债 | K240: 已审核
A241: 2211.10 | B241: 辞退福利 | E241: 应付职工薪酬_辞退福利 | F241: Severance Benefits | G241: 贷方 | H241: 流动负债 | K241: 已审核
... A277: 2221.99 | B277: 应交其他税费 | E277: 应交税费_应交其他税费 | F277: Other Tax Payable | G277: 贷方 | H277: 流动负债 | K277: 已审核
A278: 2231 | B278: 应付利息 | E278: 应付利息 | F278: Interest Payable | G278: 贷方 | H278: 流动负债 | I278: 所有币别 | J278: 其他往来单位 | K278: 已审核
A279: 2232 | B279: 应付股利 | E279: 应付股利 | F279: Dividends Payable | G279: 贷方 | H279: 流动负债 | I279: 所有币别 | J279: 其他往来单位 | K279: 已审核
A280: 2241 | B280: 其他应付款 | E280: 其他应付款 | F280: Other Payables | G280: 贷方 | H280: 流动负债 | I280: 所有币别 | J280: 供应商 | K280: 已审核
A281: 2241.01 | B281: 单位 | E281: 其他应付款_单位 | F281: Entities | G281: 贷方 | H281: 流动负债 | I281: 所有币别 | J281: 供应商 | K281: 已审核
A282: 2241.02 | B282: 个人 | E282: 其他应付款_个人 | F282: Individual | G282: 贷方 | H282: 流动负债 | I282: 所有币别 | J282: 供应商 | K282: 已审核
A283: 2245 | B283: 持有待售负债 | E283: 持有待售负债 | F283: Liabilities Held For Sale | G283: 贷方 | H283: 流动负债 | K283: 已审核
A284: 2314 | B284: 代理业务负债 | E284: 代理业务负债 | F284: Agency Business Liabilities | G284: 贷方 | H284: 流动负债 | K284: 已审核
A285: 2316 | B285: 一年内到期的长期借款 | E285: 一年内到期的长期借款 | F285: Long-term Loans Matured Within One Year | G285: 贷方 | H285: 流动负债 | K285: 已审核
A286: 2304 | B286: 其他金融工具负债 | E286: 其他金融工具负债 | F286: Financial liability | G286: 贷方 | H286: 非流动负债 | K286: 已审核
A287: 2304.01 | B287: B类优先股 | E287: 其他金融工具负债_B类优先股 | F287: Class B Preferred Share | G287: 贷方 | H287: 非流动负债 | J287: 其他往来单位 | K287: 已审核
A288: 2401 | B288: 递延收益 | E288: 递延收益 | F288: Deferred Income | G288: 贷方 | H288: 非流动负债 | K288: 已审核
A289: 2501 | B289: 长期借款 | E289: 长期借款 | F289: Long-Term Borrowing | G289: 贷方 | H289: 非流动负债 | K289: 已审核
A290: 2501.01 | B290: 本金 | E290: 长期借款_本金 | F290: Principal | G290: 贷方 | H290: 非流动负债 | K290: 已审核
A291: 2501.02 | B291: 利息调整 | E291: 长期借款_利息调整 | F291: Interest Adjustments | G291: 贷方 | H291: 非流动负债 | K291: 已审核
A292: 2501.03 | B292: 一年内到期的非流动负债 | E292: 长期借款_一年内到期的非流动负债 | F292: Non-current Liability Matured Within One Year | G292: 贷方 | H292: 非流动负债 | K292: 已审核
A293: 2502 | B293: 应付债券 | E293: 应付债券 | F293: Bonds Payable | G293: 贷方 | H293: 非流动负债 | K293: 已审核
A294: 2502.01 | B294: 优先股 | E294: 应付债券_优先股 | F294: Preferred Stock | G294: 贷方 | H294: 非流动负债 | K294: 已审核
A295: 2502.02 | B295: 永续债 | E295: 应付债券_永续债 | F295: Perpetual Bond | G295: 贷方 | H295: 非流动负债 | K295: 已审核
...

Sheet 汇总
B2: 输入 - 情形1 | K2: 输入 - 情形2 | S2: 输入 - 情形3
C3: 年底 | D3: 46357 | L3: 年底 | M3: 46357 | T3: 年底 | U3: 46357
C4: RF's base (-)/+ | D4: -0.44861538 | L4: RF's base (-)/+ | M4: -0.44861538 | T4: RF's base (-)/+ | U4: -0.44861538
C5: RF's base in HKD | D5: ='[90]Personnel-HK 2026'!$U$11 -> 180700 | E5: =D5*12+1000000 -> 3168400 | L5: RF's base in HKD | M5: ='[90]Personnel-HK 2026'!$U$11 -> 180700 | N5: =M5*12+1000000 -> 3168400 | T5: RF's base in HKD | U5: 180700 | V5: 3168400
C6: 2026拟招聘员工： | D6: 月薪 | E6: 开始日期 | L6: 2026拟招聘员工： | M6: 月薪 | N6: 开始日期 | T6: 2026拟招聘员工： | U6: 月薪 | V6: 开始日期
C7: 风资源工程师 | D7: 35000 | E7: 46113 | G7: RMB | I7: 张弛 | L7: 风资源工程师 | M7: 35000 | N7: 46113 | P7: RMB | T7: 风资源工程师 | U7: 35000 | V7: 46113 | X7: RMB | Y7: RMB
C8: 电力交易员 | D8: 33000 | E8: 46054 | G8: RMB | I8: 贾璇 | L8: 电力交易员 | M8: 33000 | N8: 46054 | P8: RMB | T8: 电力交易员 | U8: 33000 | V8: 46054 | X8: RMB | Y8: RMB
C9: 律师 | D9: 60000 | E9: 46143 | G9: RMB | L9: 律师 | M9: 60000 | N9: 46143 | P9: RMB | T9: 律师 | U9: 60000 | V9: 46143 | X9: RMB | Y9: RMB
C10: 区域副总 | D10: 26000 | E10: 46143 | G10: RMB | L10: 区域副总 | M10: 26000 | N10: 46143 | P10: RMB | T10: 区域副总 | U10: 26000 | V10: 46143 | X10: RMB | Y10: RMB
C11: 项目会计 | D11: 17000 | E11: 46235 | G11: RMB | L11: 项目会计 | M11: 17000 | N11: 46235 | P11: RMB | T11: 项目会计 | U11: 17000 | V11: 46235 | X11: RMB | Y11: RMB
C12: 档案管理员 | D12: 12000 | E12: 46357 | G12: RMB | L12: 档案管理员 | M12: 12000 | N12: 46357 | P12: RMB | T12: 档案管理员 | U12: 12000 | V12: 46357 | X12: RMB | Y12: RMB
C13: RO HKD | D13: 60000 | E13: 46082 | G13: 开始日 | L13: RO HKD | M13: 60000 | N13: 46082 | P13: 开始日 | T13: RO HKD | U13: 60000 | V13: 46082 | X13: 开始日 | Y13: 开始日
C14: RO HKD | D14: 60000 | E14: 46569 | G14: 终止日 | I14: =61500*6*0.89 -> 328410 | L14: RO HKD | M14: 60000 | N14: 46569 | P14: 终止日 | T14: RO HKD | U14: 60000 | V14: 46569 | X14: 终止日 | Y14: 终止日
C15: Head of Origination | D15: 100000 | E15: 46143 | L15: Head of Origination | M15: 100000 | N15: 46143 | T15: Head of Origination | U15: 100000 | V15: 46143
C16: Op Partner - ZJX | D16: 80000 | E16: 46143 | L16: Op Partner - ZJX | M16: 80000 | N16: 46143 | T16: Op Partner - ZJX | U16: 80000 | V16: 46143
C17: 玉杰replacement | D17: 40000 | E17: 46388 | I17: 650000 | L17: 玉杰replacement | M17: 40000 | N17: 46388 | T17: 玉杰replacement | U17: 40000 | V17: 46388
C20: 2026拟终止员工： | D20: 月薪 | E20: 终止日期 | L20: 2026拟终止员工： | M20: 月薪 | N20: 终止日期 | T20: 2026拟终止员工： | U20: 月薪 | V20: 终止日期
C21: DQ | E21: 46387 | L21: DQ | N21: 46387 | T21: DQ | V21: 46387
C22: AC | E22: 46022 | L22: AC | N22: 46022 | T22: AC | V22: 46022
C25: 2026承担成本比例变化 | L25: 2026承担成本比例变化 | T25: 2026承担成本比例变化
C26: MG | D26: 0 | L26: MG | M26: 0 | T26: MG | U26: 0
C28: 员工奖金 | D28: 1 | E28: "1" Means has bonus, "0" means no | L28: 员工奖金 | M28: 1 | N28: "1" Means has bonus, "0" means no | T28: 员工奖金 | U28: 1 | V28: "1" Means has bonus, "0" means no
C29: 员工奖金总额 | D29: ='[90]Bonus 2026'!$J$19*D28 -> 2317250 | L29: 员工奖金总额 | M29: ='[90]Bonus 2026'!$J$19*M28 -> 2317250 | T29: 员工奖金总额 | U29: 2317250
C30: 员工加薪 | D30: 1 | E30: "1" Means has payrise, "0" means no | L30: 员工加薪 | M30: 1 | N30: "1" Means has payrise, "0" means no | T30: 员工加薪 | U30: 1 | V30: "1" Means has payrise, "0" means no
C31: 员工加薪总额 | D31: ='[90]Bonus 2026'!$J$31*D30 -> 714000 | L31: 员工加薪总额 | M31: ='[90]Bonus 2026'!$J$31*M30 -> 714000 | T31: 员工加薪总额 | U31: 714000
D32: 2026 | E32: 2027 | F32: 2028 | M32: 2026 | N32: 2027 | O32: 2028 | U32: 2026 | V32: 2027 | W32: 2028
C33: 富能基金总实缴金额 | D33: =情形1!S23 -> 79972.505 | E33: =情形1!AE23 -> 125842.73 | F33: =情形1!AQ23 -> 141939.41 | L33: 富能基金总实缴金额 | M33: =情形2!S23 -> 49941.559 | N33: =情形2!AE23 -> 95626.981 | O33: =情形2!AQ23 -> 141600.02 | T33: 富能基金总实缴金额 | U33: 27428.483 | V33: 72955.25 | W33: 118769.2
C34: 对应GP总实缴金额 | D34: =情形1!S33 -> 2665.7502 | E34: =情形1!AE33 -> 4194.7578 | F34: =情形1!AQ33 -> 4731.3137 | L34: 对应GP总实缴金额 | M34: =情形2!S33 -> 1664.7186 | N34: =情形2!AE33 -> 3187.566 | O34: =情形2!AQ33 -> 4720.0006 | T34: 对应GP总实缴金额 | U34: 1500 | V34: 2431.8417 | W34: 3958.9732
C35: 对应旭智总实缴金额 | D35: =情形1!S27+情形1!S29+情形1!S31 -> 2225.9014 | E35: =情形1!AE27+情形1!AE29+情形1!AE31 -> 3502.6228 | F35: =情形1!AQ27+情形1!AQ29+情形1!AQ31 -> 3950.647 | L35: 对应旭智总实缴金额 | M35: =情形2!S27+情形2!S29+情形2!S31 -> 1420.9167 | N35: =情形2!AE27+情形2!AE29+情形2!AE31 -> 2661.6176 | O35: =情形2!AQ27+情形2!AQ29+情形2!AQ31 -> 3941.2005 | T35: 对应旭智总实缴金额 | U35: 1347.0918 | V35: 2030.5878 | W35: 3305.7426
D36: =D35/(4900-750) -> 0.53636178 | E36: =E35/(4900-750) -> 0.84400549 | F36: =F35/(4900-750) -> 0.95196312 | M36: =M35/(4900-750) -> 0.34238956 | N36: =N35/(4900-750) -> 0.64135365 | O36: =O35/(4900-750) -> 0.94968687 | U36: 0.32460044 | V36: 0.48929827 | W36: 0.79656449
C38: 新增装机（MW) | L38: 新增装机（MW) | T38: 新增装机（MW)
C39: 46112 | D39: 0 | L39: 46112 | M39: 0 | T39: 46112 | U39: 0
C40: 46203 | D40: 100 | L40: 46203 | M40: 0 | T40: 46203 | U40: 0
C41: 46295 | D41: 0 | L41: 46295 | M41: =SUM(Pipeline!E5:E6)/2 -> 150 | T41: 46295 | U41: 150
C42: 46387 | D42: 400 | L42: 46387 | M42: 150 | T42: 46387 | U42: 0
C43: 2026平均累计装机 | D43: =INDEX(情形1!$9:$9,MATCH(汇总!$D$3,情形1!$3:$3,0)) -> 147.60274 | L43: 2026平均累计装机 | M43: =INDEX(情形2!$9:$9,MATCH(汇总!$D$3,情形2!$3:$3,0)) -> 117.87671 | T43: 2026平均累计装机 | U43: 105.13699
C44: 2026累计装机 | D44: =SUM(D38:D42)+55 -> 555 | L44: 2026累计装机 | M44: =SUM(M38:M42)+55 -> 355 | T44: 2026累计装机 | U44: 205
C45: 项目数量 | D45: =INDEX(情形1!$10:$10,MATCH(汇总!$D$3,情形1!$3:$3,0)) -> 5.7142857 | L45: 项目数量 | M45: =INDEX(情形2!$10:$10,MATCH(汇总!$D$3,情形2!$3:$3,0)) -> 5 | T45: 项目数量 | U45: 3
C46: 区域数量 | D46: =INDEX(情形1!$11:$11,MATCH(汇总!$D$3,情形1!$3:$3,0)) -> 2.8571429 | L46: 区域数量 | M46: =INDEX(情形2!$11:$11,MATCH(汇总!$D$3,情形2!$3:$3,0)) -> 3 | T46: 区域数量 | U46: 3
C47: 46477 | D47: 0 | L47: 46477 | M47: 50 | T47: 46477 | U47: 50 | Y47: 15000000
C48: 46568 | D48: 100 | L48: 46568 | M48: 100 | T48: 46568 | U48: 100 | Y48: 42000000
C49: 46660 | D49: 100 | L49: 46660 | M49: 50 | T49: 46660 | U49: 50 | Y49: 16800000
C50: 46752 | D50: 100 | L50: 46752 | M50: 100 | T50: 46752 | U50: 100 | Y50: 25200000
C51: 2027平均累计装机 | D51: =INDEX(情形1!$9:$9,MATCH($E$51,情形1!$3:$3,0)) -> 655.54795 | E51: 46722 | L51: 2027平均累计装机 | M51: =INDEX(情形2!$9:$9,MATCH($N$51,情形2!$3:$3,0)) -> 480.75342 | N51: 46722 | T51: 2027平均累计装机 | U51: 330.75342 | V51: 46722 | Y51: 49400000
C52: 2027累计装机 | D52: =SUM(D47:D50)+D44 -> 855 | L52: 2027累计装机 | M52: =SUM(M47:M50)+M44 -> 655 | T52: 2027累计装机 | U52: 505 | Y52: 35200000
C53: 项目数量 | D53: =INDEX(情形1!$10:$10,MATCH($E$51,情形1!$3:$3,0)) -> 8.7142857 | L53: 项目数量 | M53: =INDEX(情形2!$10:$10,MATCH($N$51,情形2!$3:$3,0)) -> 9 | T53: 项目数量 | U53: 7 | Y53: -14200000
C54: 区域数量 | D54: =INDEX(情形1!$11:$11,MATCH($E$51,情形1!$3:$3,0)) -> 3.8571429 | L54: 区域数量 | M54: =INDEX(情形2!$11:$11,MATCH($N$51,情形2!$3:$3,0)) -> 4 | T54: 区域数量 | U54: 4
C55: 46843 | D55: 0 | L55: 46843 | T55: 46843
C56: 46934 | D56: 100 | L56: 46934 | M56: 150 | T56: 46934 | U56: 150
C57: 47026 | D57: 0 | L57: 47026 | T57: 47026
C58: 47118 | D58: 0 | L58: 47118 | M58: 150 | T58: 47118 | U58: 150
C59: 2028平均累计装机 | D59: =INDEX(情形1!$9:$9,MATCH($E$59,情形1!$3:$3,0)) -> 915.9726 | E59: 47088 | L59: 2028平均累计装机 | M59: =INDEX(情形2!$9:$9,MATCH($N$59,情形2!$3:$3,0)) -> 757.47945 | N59: 47088 | T59: 2028平均累计装机 | U59: 607.06849 | V59: 47088
C60: 2028累计装机 | D60: =SUM(D55:D58)+D52 -> 955 | L60: 2028累计装机 | M60: =SUM(M55:M58)+M52 -> 955 | T60: 2028累计装机 | U60: 805
C61: 项目数量 | D61: =INDEX(情形1!$10:$10,MATCH($E$59,情形1!$3:$3,0)) -> 9.7142857 | L61: 项目数量 | M61: =INDEX(情形2!$10:$10,MATCH($N$59,情形2!$3:$3,0)) -> 13 | T61: 项目数量 | U61: 11
C62: 区域数量 | D62: =INDEX(情形1!$11:$11,MATCH($E$59,情形1!$3:$3,0)) -> 4 | L62: 区域数量 | M62: =INDEX(情形2!$11:$11,MATCH($N$59,情形2!$3:$3,0)) -> 4 | T62: 区域数量 | U62: 4
C64: 平均单瓦股权价格（元/W) | D64: 2 | E64: =6.5*0.3 -> 1.95 | L64: 平均单瓦股权价格（元/W) | M64: 2 | N64: =6.5*0.3 -> 1.95 | T64: 平均单瓦股权价格（元/W) | U64: 2 | V64: 1.95
C65: 基金激励管理费支付 | D65: 0.3 | E65: 0 | F65: （1为支付，0为不支付） | L65: 基金激励管理费支付 | M65: 0.3 | N65: 0 | O65: （1为支付，0为不支付） | T65: 基金激励管理费支付 | U65: 0.3 | V65: 0 | W65: （1为支付，0为不支付）
C66: MAA基础管理费支付 | D66: 0.1 | L66: MAA基础管理费支付 | M66: 0.1 | T66: MAA基础管理费支付 | U66: 0.1
C67: MAA激励管理费一支付 | D67: 0.01 | E67: 0 | F67: （1为支付，0为不支付） | L67: MAA激励管理费一支付 | M67: 0.01 | N67: 0 | O67: （1为支付，0为不支付） | T67: MAA激励管理费一支付 | U67: 0.01 | V67: 0 | W67: （1为支付，0为不支付）
C68: MAA激励管理费二支付 | D68: 0.04 | E68: 0 | F68: （1为支付，0为不支付） | L68: MAA激励管理费二支付 | M68: 0.04 | N68: 0 | O68: （1为支付，0为不支付） | T68: MAA激励管理费二支付 | U68: 0.04 | V68: 0 | W68: （1为支付，0为不支付）
C69: 运维费率 | D69: 0.035 | F69: =1800000/55000000 -> 0.032727273 | L69: 运维费率 | M69: 0.035 | T69: 运维费率 | U69: 0.035
C70: 董监高保险 | E70: 0 | F70: （1为旭智承担，0为项目公司承担） | L70: 董监高保险 | N70: 0 | O70: （1为旭智承担，0为项目公司承担） | T70: 董监高保险 | V70: 0 | W70: （1为旭智承担，0为项目公司承担）
D72: 新增装机 | E72: 基金累计实缴 | F72: 旭智主体累计实缴 | M72: 新增装机 | N72: 基金累计实缴 | O72: 旭智主体累计实缴 | U72: 新增装机 | V72: 基金累计实缴 | W72: 旭智主体累计实缴
C73: 原有 | D73: 55 | L73: 原有 | M73: 55 | T73: 原有 | U73: 55
C74: 2026 | D74: =SUM(D39:D42) -> 500 | E74: =D33 -> 79972.505 | F74: =D35 -> 2225.9014 | G74: =F74/(4900-750) -> 0.53636178 | L74: 2026 | M74: =SUM(M39:M42) -> 300 | N74: =M33 -> 49941.559 | O74: =M35 -> 1420.9167 | P74: =O74/(4900-750) -> 0.34238956 | T74: 2026 | U74: 150 | V74: 27428.483 | W74: 1347.0918 | X74: 0.32460044
C75: 2027 | D75: =SUM(D47:D50) -> 300 | E75: =E33 -> 125842.73 | F75: =E35 -> 3502.6228 | G75: =F75/(4900-750) -> 0.84400549 | L75: 2027 | M75: =SUM(M47:M50) -> 300 | N75: =N33 -> 95626.981 | O75: =N35 -> 2661.6176 | P75: =O75/(4900-750) -> 0.64135365 | T75: 2027 | U75: 300 | V75: 72955.25 | W75: 2030.5878 | X75: 0.48929827
C76: 2028 | D76: =SUM(D55:D58) -> 100 | E76: =F33 -> 141939.41 | F76: =F35 -> 3950.647 | G76: =F76/(4900-750) -> 0.95196312 | L76: 2028 | M76: =SUM(M55:M58) -> 300 | N76: =O33 -> 141600.02 | O76: =O35 -> 3941.2005 | P76: =O76/(4900-750) -> 0.94968687 | T76: 2028 | U76: 300 | V76: 118769.2 | W76: 3305.7426 | X76: 0.79656449
C77: 累计 | D77: =SUM(D73:D76) -> 955 | L77: 累计 | M77: =SUM(M73:M76) -> 955 | T77: 累计 | U77: 805
B81: 输出 - 利润表 | D81: 人民币万元 | G81: 10000 | K81: 输出 - 利润表 | M81: 人民币万元 | P81: 10000 | S81: 输出 - 利润表 | U81: 人民币万元 | X81: 10000 | Y81: 10000
D82: 2026 | E82: 2027 | F82: 2028 | M82: 2026 | N82: 2027 | O82: 2028 | U82: 2026 | V82: 2027 | W82: 2028
C83: 基金管理费收入 | D83: =INDEX('Budget-合并'!$W:$W,MATCH($C83,'Budget-合并'!$B:$B,0))/$G$81 -> 96.678298 | E83: =SUM(情形1!T73:AE73) -> 474.21893 | F83: =SUM(情形1!AF73:AQ73) -> 634.44131 | L83: 基金管理费收入 | M83: =SUM(情形2!G73:S73) -> 64.782224 | N83: =SUM(情形2!T73:AE73) -> 343.45928 | O83: =SUM(情形2!AF73:AQ73) -> 546.95981 | T83: 基金管理费收入 | U83: 55.530362 | V83: 231.20335 | W83: 434.39549
C84: 咨询服务费收入 | D84: =INDEX('Budget-合并'!$W:$W,MATCH($C84,'Budget-合并'!$B:$B,0))/$G$81 -> 829.96089 | E84: =SUM(情形1!T78:AE78)+SUM(情形1!T76:AE76) -> 3539.7015 | F84: =SUM(情形1!AF78:AQ78)+SUM(情形1!AF76:AQ76) -> 5083.3126 | G84: 已扣除承担的项目公司费用 | L84: 咨询服务费收入 | M84: =SUM(情形2!G76:S76,情形2!G78:S78) -> 670.53634 | N84: =SUM(情形2!T76:AE76,情形2!T78:AE78) -> 2451.1911 | O84: =SUM(情形2!AF76:AQ76,情形2!AF78:AQ78) -> 3992.9761 | P84: 已扣除承担的项目公司费用 | T84: 咨询服务费收入 | U84: 599.98776 | V84: 1611.308 | W84: 3153.093 | X84: 已扣除承担的项目公司费用 | Y84: 已扣除承担的项目公司费用
C85: 总MAA收入（不含税，万元） | D85: =SUM(情形1!G43:S43) -> 1894.5464 | E85: =SUM(情形1!T43:AE43) -> 6170.8452 | F85: =SUM(情形1!AF43:AQ43) -> 8692.8147 | L85: 总MAA收入（不含税，万元） | M85: =SUM(情形2!G43:S43) -> 1620.2507 | N85: =SUM(情形2!T43:AE43) -> 4521.1941 | O85: =SUM(情形2!AF43:AQ43) -> 7115.5337 | P85: =N85/($M$51*100) -> 0.094043929 | T85: 总MAA收入（不含税，万元） | U85: 1503.9416 | V85: 3106.0998 | W85: 5700.4394 | X85: 0.093909829 | Y85: 0.094024557
C86: 运维费用（不含税，万元） | D86: =-SUM(情形1!G58:S58) -> -922.6669 | E86: =-SUM(情形1!T58:AE58) -> -2327.0883 | F86: =-SUM(情形1!AF58:AQ58) -> -3209.7776 | L86: 运维费用（不含税，万元） | M86: =-SUM(情形2!G58:S58) -> -826.66341 | N86: =-SUM(情形2!T58:AE58) -> -1749.7104 | O86: =-SUM(情形2!AF58:AQ58) -> -2657.7293 | P86: =N86/($M$51*100) -> -0.036395173 | T86: 运维费用（不含税，万元） | U86: -785.95522 | V86: -1254.4274 | W86: -2162.4462 | X86: -0.037926361 | Y86: -0.038735097
C87: 其他费用合计（不含税，万元） | D87: =-SUM(情形1!G68:S68) -> -134.0467 | E87: =-SUM(情形1!T68:AE68) -> -259.24902 | F87: =-SUM(情形1!AF68:AQ68) -> -335.37876 | L87: 其他费用合计（不含税，万元） | M87: =-SUM(情形2!G68:S68) -> -117.33633 | N87: =-SUM(情形2!T55:AE55) -> -302.44909 | O87: =-SUM(情形2!AF55:AQ55) -> -433.59909 | P87: =N87/($M$51*100) -> -0.0062911478 | T87: 其他费用合计（不含税，万元） | U87: -113.177 | V87: -229.64909 | W87: -360.79909 | X87: -0.0069432112 | Y87: -0.0050878798
C88: WHT | D88: =-SUM(情形1!G77:S77)*5% -> -7.8718978 | E88: =-SUM(情形1!T77:AE77)*5% -> -44.806349 | F88: =-SUM(情形1!AF77:AQ77)*5% -> -64.345729 | L88: WHT | M88: =-SUM(情形2!G77:S77)*5% -> -5.714625 | N88: =-SUM(情形2!T77:AE77)*5% -> -31.027735 | O88: =-SUM(情形2!AF77:AQ77)*5% -> -50.544001 | P88: =N88/($M$51*100) -> -0.0006453981 | T88: WHT | U88: -4.821605 | V88: -20.396304 | W88: -39.91257 | X88: -0.00061666191 | Y88: -0.00062751975
C89: 营业收入合计 | D89: =INDEX('Budget-合并'!$W:$W,MATCH($C89,'Budget-合并'!$B:$B,0))/$G$81 -> 926.63919 | E89: =SUM(E83:E84) -> 4013.9205 | F89: =SUM(F83:F84) -> 5717.7539 | L89: 营业收入合计 | M89: =SUM(M83:M84) -> 735.31856 | N89: =SUM(N83:N84) -> 2794.6503 | O89: =SUM(O83:O84) -> 4539.9359 | T89: 营业收入合计 | U89: 655.51812 | V89: 1842.5114 | W89: 3587.4885
C90: 税金及附加小计 | D90: =-INDEX('Budget-合并'!$W:$W,MATCH($C90,'Budget-合并'!$B:$B,0))/$G$81 -> -5.522927 | E90: =E89*D90/D89 -> -23.923648 | F90: =F89*E90/E89 -> -34.078785 | L90: 税金及附加小计 | M90: =-M89*6%*12% -> -5.2942937 | N90: =-N89*6%*12% -> -20.121482 | O90: =-O89*6%*12% -> -32.687538 | T90: 税金及附加小计 | U90: -4.7197305 | V90: -13.266082 | W90: -25.829917
C91: 管理人工费用小计 | D91: =-INDEX('Budget-合并'!$W:$W,MATCH($C91,'Budget-合并'!$B:$B,0))/$G$81 -> -2275.2256 | E91: =(-'Personnel-CN'!AV329-'[90]Personnel-HK 2026'!$AU$38)/10000-300 -> -2572.0189 | F91: =E91*1.05 -> -2700.6198 | L91: 管理人工费用小计 | M91: =-INDEX('Budget-合并'!$W:$W,MATCH($C91,'Budget-合并'!$B:$B,0))/$G$81 -> -2275.2256 | N91: =E91 -> -2572.0189 | O91: =F91 -> -2700.6198 | P91: =N91/($M$51*100) -> -0.053499751 | T91: 管理人工费用小计 | U91: -2275.2256 | V91: -2572.0189 | W91: -2700.6198 | X91: -0.077762425 | Y91: -0.090391503
C92: 管理费用合计 | D92: =-INDEX('Budget-合并'!$W:$W,MATCH($C92,'Budget-合并'!$B:$B,0))/$G$81 -> -819.07193 | E92: =D92+100 -> -719.07193 | F92: =E92 -> -719.07193 | L92: 管理费用合计 | M92: =-INDEX('Budget-合并'!$W:$W,MATCH($C92,'Budget-合并'!$B:$B,0))/$G$81 -> -819.07193 | N92: =E92 -> -719.07193 | O92: =F92 -> -719.07193 | P92: =N92/($M$51*100) -> -0.014957188 | T92: 管理费用合计 | U92: -819.07193 | V92: -719.07193 | W92: -719.07193 | X92: -0.021740423 | Y92: -0.025044013
C93: 财务费用合计 | D93: =-INDEX('Budget-合并'!$W:$W,MATCH($C93,'Budget-合并'!$B:$B,0))/$G$81 -> -16.016266 | E93: =D93*1.05 -> -16.817079 | F93: =E93*1.05 -> -17.657933 | L93: 财务费用合计 | M93: =-INDEX('Budget-合并'!$W:$W,MATCH($C93,'Budget-合并'!$B:$B,0))/$G$81 -> -16.016266 | N93: =M93 -> -16.016266 | O93: =N93 -> -16.016266 | P93: =N93/($M$51*100) -> -0.00033314928 | T93: 财务费用合计 | U93: -16.016266 | V93: -16.016266 | W93: -16.016266 | X93: -0.00048423583 | Y93: -0.00058570934
C94: 其他收益合计 | D94: =INDEX('Budget-合并'!$W:$W,MATCH($C94,'Budget-合并'!$B:$B,0))/$G$81 -> 1.646 | E94: =D94 -> 1.646 | F94: =E94 -> 1.646 | L94: 其他收益合计 | M94: =INDEX('Budget-合并'!$W:$W,MATCH($C94,'Budget-合并'!$B:$B,0))/$G$81 -> 1.646 | N94: =M94 -> 1.646 | O94: =N94 -> 1.646 | T94: 其他收益合计 | U94: 1.646 | V94: 1.646 | W94: 1.646
C95: 总费用 | D95: =SUM(D90:D94) -> -3114.1907 | E95: =SUM(E90:E94) -> -3330.1855 | F95: =SUM(F90:F94) -> -3469.7824 | L95: 总费用 | M95: =SUM(M90:M94) -> -3113.9621 | N95: =SUM(N90:N94) -> -3325.5825 | O95: =SUM(O90:O94) -> -3466.7495 | T95: 总费用 | U95: -3113.3875 | V95: -3318.7271 | W95: -3459.8919
C96: 营业利润 | D96: =INDEX('Budget-合并'!$W:$W,MATCH($C96,'Budget-合并'!$B:$B,0))/$G$81 -> -2187.5516 | E96: =SUM(E89:E94) -> 683.73497 | F96: =SUM(F89:F94) -> 2247.9715 | L96: 营业利润 | M96: =SUM(M89:M94) -> -2378.6435 | N96: =SUM(N89:N94) -> -530.93219 | O96: =SUM(O89:O94) -> 1073.1864 | P96: =N96/($M$51*100) -> -0.011043753 | T96: 营业利润 | U96: -2457.8694 | V96: -1476.2158 | W96: 127.59661 | X96: -0.044631912 | Y96: -0.059827269
C97: 营业外收入 (支-, 收+): | D97: =INDEX('Budget-合并'!$W:$W,MATCH($C97,'Budget-合并'!$B:$B,0))/$G$81 -> 0 | E97: 0 | F97: 0 | L97: 营业外收入 (支-, 收+): | M97: =INDEX('Budget-合并'!$W:$W,MATCH($C97,'Budget-合并'!$B:$B,0))/$G$81 -> 0 | N97: =INDEX('Budget-合并'!$W:$W,MATCH($C97,'Budget-合并'!$B:$B,0))/$G$81 -> 0 | O97: =INDEX('Budget-合并'!$W:$W,MATCH($C97,'Budget-合并'!$B:$B,0))/$G$81 -> 0 | T97: 营业外收入 (支-, 收+): | U97: 0 | V97: 0 | W97: 0
C98: 利润总额 (税前利润) | D98: =INDEX('Budget-合并'!$W:$W,MATCH($C98,'Budget-合并'!$B:$B,0))/$G$81 -> -2187.5516 | E98: =SUM(E96:E97) -> 683.73497 | F98: =SUM(F96:F97) -> 2247.9715 | L98: 利润总额 (税前利润) | M98: =SUM(M96:M97) -> -2378.6435 | N98: =SUM(N96:N97) -> -530.93219 | O98: =SUM(O96:O97) -> 1073.1864 | P98: =N98/($M$51*100) -> -0.011043753 | T98: 利润总额 (税前利润) | U98: -2457.8694 | V98: -1476.2158 | W98: 127.59661 | X98: -0.044631912 | Y98: -0.059827269
C99: 五 税后利润 | D99: =INDEX('Budget-合并'!$W:$W,MATCH($C99,'Budget-合并'!$B:$B,0))/$G$81 -> -2187.5516 | E99: =E98 -> 683.73497 | F99: =F98 -> 2247.9715 | L99: 五 税后利润 | M99: =M98 -> -2378.6435 | N99: =N98 -> -530.93219 | O99: =O98 -> 1073.1864 | T99: 五 税后利润 | U99: -2457.8694 | V99: -1476.2158 | W99: 127.59661
C101: 基金基础管理费收入 | D101: =D83 -> 96.678298 | E101: =E83 -> 474.21893 | F101: =F83 -> 634.44131 | L101: 基金基础管理费收入 | M101: =M83 -> 64.782224 | N101: =N83 -> 343.45928 | O101: =O83 -> 546.95981 | T101: 基金基础管理费收入 | U101: 55.530362 | V101: 231.20335 | W101: 434.39549
C102: MAA基础收入 | D102: =D85 -> 1894.5464 | E102: =E85 -> 6170.8452 | F102: =F85 -> 8692.8147 | L102: MAA基础收入 | M102: =M85 -> 1620.2507 | N102: =N85 -> 4521.1941 | O102: =O85 -> 7115.5337 | T102: MAA基础收入 | U102: 1503.9416 | V102: 3106.0998 | W102: 5700.4394
C103: 运维费用（不含税，万元） | D103: =D86 -> -922.6669 | E103: =E86 -> -2327.0883 | F103: =F86 -> -3209.7776 | G103: 200万buffer | L103: 运维费用（不含税，万元） | M103: =M86 -> -826.66341 | N103: =N86 -> -1749.7104 | O103: =O86 -> -2657.7293 | T103: 运维费用（不含税，万元） | U103: -785.95522 | V103: -1254.4274 | W103: -2162.4462
D104: =D103/D$111 -> 0.22079835 | E104: =E103/E$111 -> 0.390364 | F104: =F103/F$111 -> 0.45340424 | M104: =M103/M$111 -> 0.20342747 | N104: =N103/N$111 -> 0.32349508 | O104: =O103/O$111 -> 0.40216089 | U104: 0.19564064 | V104: 0.26008198 | W104: 0.35902845
C105: 管理人工费用小计 | D105: =D91 -> -2275.2256 | E105: =E91 -> -2572.0189 | F105: =F91 -> -2700.6198 | G105: 250万buffer | L105: 管理人工费用小计 | M105: =M91 -> -2275.2256 | N105: =N91 -> -2572.0189 | O105: =O91 -> -2700.6198 | T105: 管理人工费用小计 | U105: -2275.2256 | V105: -2572.0189 | W105: -2700.6198
D106: =D105/D$111 -> 0.54447175 | E106: =E105/E$111 -> 0.43145057 | F106: =F105/F$111 -> 0.38148203 | M106: =M105/M$111 -> 0.55989339 | N106: =N105/N$111 -> 0.47552752 | O106: =O105/O$111 -> 0.40865098 | U106: 0.56635108 | V106: 0.53325985 | W106: 0.44838078
C107: 管理费用合计 | D107: =D92 -> -819.07193 | E107: =E92 -> -719.07193 | F107: =F92 -> -719.07193 | L107: 管理费用合计 | M107: =M92 -> -819.07193 | N107: =N92 -> -719.07193 | O107: =O92 -> -719.07193 | T107: 管理费用合计 | U107: -819.07193 | V107: -719.07193 | W107: -719.07193
D108: =D107/D$111 -> 0.19600761 | E108: =E107/E$111 -> 0.12062275 | F108: =F107/F$111 -> 0.1015741 | M108: =M107/M$111 -> 0.20155933 | N108: =N107/N$111 -> 0.13294556 | O108: =O107/O$111 -> 0.10880815 | U108: 0.20388407 | V108: 0.14908607 | W108: 0.11938668
C109: 项目公司其他(电力交易，会计，人力等） | D109: =SUM(D87:D88,D90,D93:D94) -> -161.81179 | E109: =SUM(E87:E88,E90,E93:E94) -> -343.1501 | F109: =SUM(F87:F88,F90,F93:F94) -> -449.8152 | L109: 项目公司其他(电力交易，会计，人力等） | M109: =SUM(M87:M88,M90,M93:M94) -> -142.71552 | N109: =SUM(N87:N88,N90,N93:N94) -> -367.96857 | O109: =SUM(O87:O88,O90,O93:O94) -> -531.20089 | T109: 项目公司其他(电力交易，会计，人力等） | U109: -137.0886 | V109: -277.68174 | W109: -440.91184
D110: =D109/D$111 -> 0.038722292 | E110: =E109/E$111 -> 0.057562683 | F110: =F109/F$111 -> 0.063539642 | M110: =M109/M$111 -> 0.035119803 | N110: =N109/N$111 -> 0.068031842 | O110: =O109/O$111 -> 0.08037998 | U110: 0.03412421 | V110: 0.057572098 | W110: 0.073204083
C111: 总费用 | D111: =D103+D105+D107+D109 -> -4178.7762 | E111: =E103+E105+E107+E109 -> -5961.3291 | F111: =F103+F105+F107+F109 -> -7079.2845 | L111: 总费用 | M111: =M103+M105+M107+M109 -> -4063.6765 | N111: =N103+N105+N107+N109 -> -5408.7697 | O111: =O103+O105+O107+O109 -> -6608.6219 | T111: 总费用 | U111: -4017.3414 | V111: -4823.1999 | W111: -6023.0498
C112: 利润总额 (税前利润) | D112: =SUM(D101:D102,D111) -> -2187.5516 | E112: =SUM(E101:E102,E111) -> 683.73497 | F112: =SUM(F101:F102,F111) -> 2247.9715 | L112: 利润总额 (税前利润) | M112: =M98 -> -2378.6435 | N112: =N98 -> -530.93219 | O112: =O98 -> 1073.1864 | T112: 利润总额 (税前利润) | U112: -2457.8694 | V112: -1476.2158 | W112: 127.59661
C113: 基金激励管理费收入 | D113: =187.281342763379-D101 -> 90.603045 | E113: =677.45561064248-E101 -> 203.23668 | F113: =908.274395545008-F101 -> 273.83309 | L113: 基金激励管理费收入 | M113: =92.5460341330075-M101 -> 27.76381 | N113: =490.656108774486-N101 -> 147.19683 | O113: =783.300829436782-O101 -> 236.34102 | T113: 基金激励管理费收入 | U113: =79.3290882461211-U101 -> 23.798726 | V113: =330.290498680264-V101 -> 99.08715 | W113: =622.494654479664-W101 -> 188.09917
...

Sheet cashflow汇总实际
E1: ACPLHK | F1: ACPL | G1: ACPLSZ | H1: ACPLSZL | I1: ACPLGZ | J1: Yixing | K1: Total | M1: Albamen New Energy | N1: 深圳曦风 | O1: 深圳新融 | Q1: ACPLHK | R1: ACPL | S1: ACPLSZ | T1: ACPLSZL | U1: ACPLGZ | V1: Yixing | W1: Total
E2: RMB | F2: RMB | G2: RMB | H2: RMB | I2: RMB | J2: RMB | K2: RMB
B3: Cash balance | D3: 45866 | E3: =2765593+809735*0.91+46072*4.71 -> 3719451 | F3: =50223*0.91 -> 45702.93 | G3: 1757806 | H3: 5744218.3 | I3: 22134.7 | K3: =SUM(E3:I3) -> 11289313
B4: Transfer | E4: =-F4 -> -697963.14 | F4: =-F5 -> 697963.14 | K4: =SUM(E4:I4) -> 0
B5: Jul 2025 expenses | E5: -650484 | F5: -697963.14 | G5: -652247 | H5: -384285.96 | I5: -2321.86 | K5: =SUM(E5:I5) -> -2387302 | M5: +657k: ACPLSZ: 120k 鉴衡服务费; 普华22.5k咨询费；63k Q3深圳租金 ACPLHK: 82K IT服务; 62K 审计费； ACPL: 218k HK SPV费用; 90K 审计费
B6: Estimated Cash balance | D6: 45869 | E6: =SUM(E3:E5) -> 2371003.8 | F6: =SUM(F3:F5) -> 45702.93 | G6: =SUM(G3:G5) -> 1105559 | H6: =SUM(H3:H5) -> 5359932.3 | I6: =SUM(I3:I5) -> 19812.84 | K6: =SUM(K3:K5) -> 8902010.9
B8: Cash balance | D8: 45869 | E8: =2653612*0.91472 -> 2427312 | F8: =52344*0.91472 -> 47880.104 | G8: 1231689 | H8: 5444989 | I8: 49812.84 | K8: =SUM(E8:I8) -> 9201682.9
B9: Transfer | E9: =-F9 -> -360000 | F9: 360000 | K9: =SUM(E9:I9) -> 0
B10: injection | E10: =3600000*0.9 -> 3240000 | G10: =3600000*0.1 -> 360000 | K10: =SUM(E10:I10) -> 3600000
B11: Aug 2025 expenses | E11: =-香港!C213 -> -530274.16 | F11: =-香港!D213 -> -363985.38 | G11: =-'202601-202603（Forecast）'!#REF! -> #REF! | H11: =-'202601-202603（Forecast）'!#REF! -> #REF! | I11: =-'202601-202603（Forecast）'!#REF! -> #REF! | K11: =SUM(E11:I11) -> #REF! | M11: ACPLSZ: 普华22.5k咨询费 ACPLHK: 145K IT服务(license + cloud storage)
B12: Cash balance | D12: 45900 | E12: =SUM(E8:E11) -> 4777037.8 | F12: =SUM(F8:F11) -> 43894.721 | G12: =SUM(G8:G11) -> #REF! | H12: =SUM(H8:H11) -> #REF! | I12: =SUM(I8:I11) -> #REF! | K12: =SUM(K8:K11) -> #REF! | M12: *** ACPLHK will breach the liquid cap requirement after settlement of Aug expenses without capital injection
B14: Cash balance | D14: 45900 | E14: 4794239 | F14: 82455 | G14: 1111289 | H14: 5068590.2 | I14: 31863.6 | K14: =SUM(E14:I14) -> 11088437
B15: Transfer | E15: =-F15 -> -617625 | F15: =675000*0.915 -> 617625 | K15: =SUM(E15:I15) -> 0
B16: Sept 2025 expenses | E16: =-香港!C236 -> -499864.88 | F16: =-香港!D236+180000*0.915 -> -502745.06 | G16: =-'202601-202603（Forecast）'!#REF! -> #REF! | H16: =-'202601-202603（Forecast）'!O52 -> -766650.99 | I16: 0 | K16: =SUM(E16:I16) -> #REF!
B17: Cash balance | D17: 45930 | E17: =SUM(E14:E16) -> 3676749.1 | F17: =SUM(F14:F16) -> 197334.94 | G17: =SUM(G14:G16) -> #REF! | H17: =SUM(H14:H16) -> 4301939.2 | I17: =SUM(I14:I16) -> 31863.6 | K17: =SUM(K14:K16) -> #REF!
B18: Transfer | E18: =-F18 -> -502745.06 | F18: =-F20 -> 502745.06 | K18: =SUM(E18:I18) -> 0
B19: injection
B20: October 2025 expenses | E20: -520253 | F20: =F16 -> -502745.06 | G20: =-'202601-202603（Forecast）'!I52 -> -789872.76 | H20: =-'202601-202603（Forecast）'!P52 -> -344650.99 | I20: 0 | K20: =SUM(E20:I20) -> -2157521.8
B22: Cash balance | D22: 45961 | E22: =3251528*0.92 -> 2991405.8 | F22: =65292*0.92 -> 60068.64 | G22: =SUM('202601-202603（Forecast）'!I14,'202601-202603（Forecast）'!L14) -> 561081.68 | H22: ='202601-202603（Forecast）'!O14 -> 2694352.1 | I22: ='202601-202603（Forecast）'!F14 -> 86665.41 | K22: =SUM(E22:J22) -> 6393573.6
B23: Transfer | E23: =香港!C274*0.92 -> -368000 | F23: =-E23 -> 368000 | G23: =-H23 -> 450000 | H23: -450000 | I23: =-'202601-202603（Forecast）'!F52 -> -9982000 | K23: =SUM(E23:J23) -> -9982000
B24: November 2025 expenses | E24: =-香港!C272*0.92 -> -493674.76 | F24: =-香港!D272*0.92 -> -394737.96 | G24: -450000 | H24: -400000 | I24: 0 | K24: =SUM(E24:J24) -> -1738412.7
B25: Cash balance | D25: 45991 | E25: =SUM(E22:E24) -> 2129731 | F25: =SUM(F22:F24) -> 33330.68 | G25: =SUM(G22:G24) -> 561081.68 | H25: =SUM(H22:H24) -> 1844352.1 | I25: =SUM(I22:I24) -> -9895334.6 | K25: =SUM(K22:K24) -> -5326839.2
P26: Dec expense payments | R26: =-SUM(K35:K35) -> 1936677.9
B27: 实际现金余额 | D27: 45991 | E27: =2341169 -> 2341169 | F27: 46479 | G27: =104222.77+53825.34+17880.93 -> 175929.04 | H27: 3460729 | I27: 31951 | J27: 57445 | K27: =SUM(E27:J27) -> 6113702
B28: 利息收入 | E28: 3.34 | F28: 0.06 | G28: =5.68+3.33+2.26 -> 11.27 | H28: =3329.24+247.83+0.02 -> 3577.09 | I28: =41018+0.07+0.21+0.17+7.85 -> 41026.3 | J28: 7.26 | K28: =SUM(E28:J28) -> 44625.32
B29: 注资深圳曦和 | H29: -400000 | K29: =SUM(E29:J29) -> -400000 | P29: Dec non-routine items:
B30: IDG借款 | F30: =2000000*0.9 -> 1800000 | K30: =SUM(E30:J30) -> 1800000 | P30: IT cloud storage for 2025 | R30: =-香港!C286*0.92 -> -138000
B31: 现金分配 | G31: =-J31*10% -> 0 | I31: =-J31*0.9 -> 0 | K31: =SUM(E31:J31) -> 0 | P31: Huw 7-12 2025 service fee | R31: =-香港!C293*0.92 -> -276000
B32: 内部调拨 | K32: =SUM(E32:J32) -> 0 | P32: Cayman entity expenses | R32: =-SUM(香港!I283:I284)*7.1-香港!I293*7.1 -> -269912.25
B33: 减资款出境 | E33: =-I33 -> 0 | I33: =-SUM(I30:I32) -> 0 | K33: =SUM(E33:J33) -> 0 | P33: IDG Q1 service fee (Michael) | R33: =-'202601-202603（Forecast）'!I45 -> 0
B34: 内部调拨 | E34: =-F34 -> 647834.4 | F34: =-(800000-80000)*0.89977 -> -647834.4 | G34: 345000 | H34: -280000 | I34: -65000 | K34: =SUM(E34:J34) -> 0 | R34: =SUM(R30:R33) -> -683912.25
B35: 费用支出 | E35: =-395768.68 -> -395768.68 | F35: =-103720*0.9-637830.25 -> -731178.25 | G35: =-329240.35-105997.92 -> -435238.27 | H35: -374466.81 | I35: -0.9 | J35: -25 | K35: =SUM(E35:J35) -> -1936677.9 | P35: Dec routine expense payments | R35: =R26+R34 -> 1252765.7
B36: 现金余额 | D36: 46022 | E36: =SUM(E27:E35) -> 2593238.1 | F36: =SUM(F27:F35) -> 467466.41 | G36: =SUM(G27:G35) -> 85702.04 | H36: =SUM(H27:H35) -> 2409839.3 | I36: =SUM(I27:I35) -> 7976.4 | J36: =SUM(J27:J35) -> 57427.26 | K36: =SUM(K27:K35) -> 5621649.5
B37: 实际现金余额 | D37: 46022 | E37: 2574529 | F37: 466588 | G37: =G36 -> 85702.04 | H37: =H36 -> 2409839.3 | I37: =I36 -> 7976.4 | J37: =J36 -> 57427.26 | K37: =SUM(E37:J37) -> 5602062
B38: 曦和基金股转款 | D38: 46023 | I38: 10000000 | K38: =SUM(E38:J38) -> 10000000 | U38: 取得借款所收到的现金 | W38: 取得借款所收到的现金
B39: 内部调拨 | D39: 46023 | G39: 1540000 | I39: =-G39 -> -1540000 | K39: =SUM(E39:J39) -> 0 | Q39: =IF(E39>0,"收到的其他与筹资活动有关的现金","支付的其他与筹资活动有关的现金") -> 支付的其他与筹资活动有关的现金 | R39: =IF(F39>0,"收到的其他与筹资活动有关的现金","支付的其他与筹资活动有关的现金") -> 支付的其他与筹资活动有关的现金 | S39: =IF(G39>0,"收到的其他与筹资活动有关的现金","支付的其他与筹资活动有关的现金") -> 收到的其他与筹资活动有关的现金 | T39: =IF(H39>0,"收到的其他与筹资活动有关的现金","支付的其他与筹资活动有关的现金") -> 支付的其他与筹资活动有关的现金 | U39: =IF(I39>0,"收到的其他与筹资活动有关的现金","支付的其他与筹资活动有关的现金") -> 支付的其他与筹资活动有关的现金 | V39: =IF(J39>0,"收到的其他与筹资活动有关的现金","支付的其他与筹资活动有关的现金") -> 支付的其他与筹资活动有关的现金
B40: 注资深圳曦和 | D40: 46023 | H40: -400000 | K40: =SUM(E40:J40) -> -400000 | T40: 投资支付的现金 | W40: 投资支付的现金
B41: 注资宜兴旭智 | D41: 46023 | G41: -144000 | I41: -3516000 | J41: =-G41-I41 -> 3660000 | K41: =SUM(E41:J41) -> 0 | Q41: NA | S41: 投资支付的现金 | U41: 投资支付的现金 | V41: 吸收投资所收到的现金
B42: 内部调拨 | D42: 46023 | G42: =-H42 -> -780000 | H42: =500000+280000 -> 780000 | K42: =SUM(E42:J42) -> 0 | Q42: =IF(E42>0,"收到的其他与筹资活动有关的现金","支付的其他与筹资活动有关的现金") -> 支付的其他与筹资活动有关的现金 | R42: =IF(F42>0,"收到的其他与筹资活动有关的现金","支付的其他与筹资活动有关的现金") -> 支付的其他与筹资活动有关的现金 | S42: =IF(G42>0,"收到的其他与筹资活动有关的现金","支付的其他与筹资活动有关的现金") -> 支付的其他与筹资活动有关的现金 | T42: =IF(H42>0,"收到的其他与筹资活动有关的现金","支付的其他与筹资活动有关的现金") -> 收到的其他与筹资活动有关的现金 | U42: =IF(I42>0,"收到的其他与筹资活动有关的现金","支付的其他与筹资活动有关的现金") -> 支付的其他与筹资活动有关的现金 | V42: =IF(J42>0,"收到的其他与筹资活动有关的现金","支付的其他与筹资活动有关的现金") -> 支付的其他与筹资活动有关的现金
B43: 减资款出境 | D43: 46023 | E43: =-I43 -> 4924000 | I43: =-SUM(I38:I41)+20000 -> -4924000 | K43: =SUM(E43:J43) -> 0 | Q43: 收回投资所收到的现金 | U43: 支付的其他与筹资活动有关的现金
B44: 内部调拨 | D44: 46023 | E44: =-2000000*0.9 -> -1800000 | F44: =-E44 -> 1800000 | K44: =SUM(E44:J44) -> 0 | Q44: =IF(E44>0,"收到的其他与筹资活动有关的现金","支付的其他与筹资活动有关的现金") -> 支付的其他与筹资活动有关的现金 | R44: =IF(F44>0,"收到的其他与筹资活动有关的现金","支付的其他与筹资活动有关的现金") -> 收到的其他与筹资活动有关的现金 | S44: =IF(G44>0,"收到的其他与筹资活动有关的现金","支付的其他与筹资活动有关的现金") -> 支付的其他与筹资活动有关的现金 | T44: =IF(H44>0,"收到的其他与筹资活动有关的现金","支付的其他与筹资活动有关的现金") -> 支付的其他与筹资活动有关的现金 | U44: =IF(I44>0,"收到的其他与筹资活动有关的现金","支付的其他与筹资活动有关的现金") -> 支付的其他与筹资活动有关的现金 | V44: =IF(J44>0,"收到的其他与筹资活动有关的现金","支付的其他与筹资活动有关的现金") -> 支付的其他与筹资活动有关的现金
B45: 归还IDG借款 | D45: 46023 | F45: =-2003452*0.9 -> -1803106.8 | J45: -3649364.4 | K45: =SUM(E45:J45) -> -5452471.2 | R45: 偿还债务所支付的现金 | V45: 偿还债务所支付的现金 | W45: 偿还债务所支付的现金
B46: 现金余额 | D46: 46023 | E46: =SUM(E37:E45) -> 5698529 | F46: =SUM(F37:F45) -> 463481.2 | G46: =SUM(G37:G45) -> 701702.04 | H46: =SUM(H37:H45) -> 2789839.3 | I46: =SUM(I37:I45) -> 27976.4 | J46: =SUM(J37:J45) -> 68062.88 | K46: =SUM(K37:K45) -> 9749590.8
B47: 费用支出 | D47: 46023 | E47: =-香港!C313/1.1235-香港!C293/1.1235-7600/1.1235 -> -693407.53 | F47: =-香港!C315/1.1235-9000/1.1235 -> -510959.5 | G47: =-('202601-202603（Forecast）'!I52-'202601-202603（Forecast）'!I50-'202601-202603（Forecast）'!I47-'202601-202603（Forecast）'!I45)-30752.77-9434.66-40281.7 -> -726341.89 | H47: =-('202601-202603（Forecast）'!O52-'202601-202603（Forecast）'!O50)-57483.79 -> -424134.78 | I47: =-('202601-202603（Forecast）'!F52-'202601-202603（Forecast）'!F50-'202601-202603（Forecast）'!F48-'202601-202603（Forecast）'!F47) -> -2000 | K47: =SUM(E47:J47) -> -2356843.7
B48: 曦和基金股转款 | D48: 46023 | I48: 9650000 | K48: =SUM(E48:J48) -> 9650000 | U48: 取得借款所收到的现金 | W48: 取得借款所收到的现金
B49: 减资款出境 | D49: 46023 | E49: =-I49 -> 7000000 | I49: -7000000 | K49: =SUM(E49:J49) -> 0 | Q49: 收回投资所收到的现金 | U49: 支付的其他与筹资活动有关的现金
B50: 内部调拨 | D50: 46023 | E50: -100000 | F50: =-E50 -> 100000 | K50: =SUM(E50:J50) -> 0 | Q50: =IF(E50>0,"收到的其他与筹资活动有关的现金","支付的其他与筹资活动有关的现金") -> 支付的其他与筹资活动有关的现金 | R50: =IF(F50>0,"收到的其他与筹资活动有关的现金","支付的其他与筹资活动有关的现金") -> 收到的其他与筹资活动有关的现金 | S50: =IF(G50>0,"收到的其他与筹资活动有关的现金","支付的其他与筹资活动有关的现金") -> 支付的其他与筹资活动有关的现金 | T50: =IF(H50>0,"收到的其他与筹资活动有关的现金","支付的其他与筹资活动有关的现金") -> 支付的其他与筹资活动有关的现金 | U50: =IF(I50>0,"收到的其他与筹资活动有关的现金","支付的其他与筹资活动有关的现金") -> 支付的其他与筹资活动有关的现金 | V50: =IF(J50>0,"收到的其他与筹资活动有关的现金","支付的其他与筹资活动有关的现金") -> 支付的其他与筹资活动有关的现金
B51: 费用支出 | D51: 46023 | K51: =SUM(E51:J51) -> 0
B52: 现金余额 | D52: 46023 | E52: =SUM(E46:E51) -> 11905121 | F52: =SUM(F46:F51) -> 52521.698 | G52: =SUM(G46:G51) -> -24639.85 | H52: =SUM(H46:H51) -> 2365704.5 | I52: =SUM(I46:I51) -> 2675976.4 | J52: =SUM(J46:J51) -> 68062.88 | K52: =SUM(K46:K51) -> 17042747 | M52: =SUM(M46:M51) -> 0 | N52: =SUM(N46:N51) -> 0 | O52: =SUM(O46:O51) -> 0
B53: 现金余额实际 | D53: 46023 | E53: 11919036 | F53: 164967 | G53: 137924 | H53: 2577310 | I53: 2675380 | J53: 68037 | K53: =SUM(E53:J53) -> 17542654
B54: 内部调拨 | D54: 46054 | G54: =-I54-O54 -> 790000 | I54: -1000000 | K54: =SUM(E54:J54) -> -210000 | O54: 210000 | Q54: =IF(E54>0,"收到的其他与筹资活动有关的现金","支付的其他与筹资活动有关的现金") -> 支付的其他与筹资活动有关的现金 | R54: =IF(F54>0,"收到的其他与筹资活动有关的现金","支付的其他与筹资活动有关的现金") -> 支付的其他与筹资活动有关的现金 | S54: =IF(G54>0,"收到的其他与筹资活动有关的现金","支付的其他与筹资活动有关的现金") -> 收到的其他与筹资活动有关的现金 | T54: =IF(H54>0,"收到的其他与筹资活动有关的现金","支付的其他与筹资活动有关的现金") -> 支付的其他与筹资活动有关的现金 | U54: =IF(I54>0,"收到的其他与筹资活动有关的现金","支付的其他与筹资活动有关的现金") -> 支付的其他与筹资活动有关的现金 | V54: =IF(J54>0,"收到的其他与筹资活动有关的现金","支付的其他与筹资活动有关的现金") -> 支付的其他与筹资活动有关的现金
B55: 费用支出 | D55: 46054 | E55: =(-10272-6800)*0.88999 -> -15193.909 | K55: =SUM(E55:J55) -> -15193.909 | O55: -200000
B56: IDG借款 | D56: 46054 | J56: 15000000 | K56: =SUM(E56:J56) -> 15000000 | V56: 取得借款所收到的现金 | W56: 取得借款所收到的现金
B57: 减资款分配 | D57: 46054 | G57: =-$J$57*10% -> 1500000 | I57: =-$J$57*90% -> 13500000 | J57: =-J56 -> -15000000 | K57: =SUM(E57:J57) -> 0 | S57: 收回投资所收到的现金 | U57: 收回投资所收到的现金 | V57: 支付的其他与筹资活动有关的现金
B58: 内部调拨 | D58: 46054 | G58: =-G57 -> -1500000 | I58: =-G58 -> 1500000 | K58: =SUM(E58:J58) -> 0 | Q58: =IF(E58>0,"收到的其他与筹资活动有关的现金","支付的其他与筹资活动有关的现金") -> 支付的其他与筹资活动有关的现金 | R58: =IF(F58>0,"收到的其他与筹资活动有关的现金","支付的其他与筹资活动有关的现金") -> 支付的其他与筹资活动有关的现金 | S58: =IF(G58>0,"收到的其他与筹资活动有关的现金","支付的其他与筹资活动有关的现金") -> 支付的其他与筹资活动有关的现金 | T58: =IF(H58>0,"收到的其他与筹资活动有关的现金","支付的其他与筹资活动有关的现金") -> 支付的其他与筹资活动有关的现金 | U58: =IF(I58>0,"收到的其他与筹资活动有关的现金","支付的其他与筹资活动有关的现金") -> 收到的其他与筹资活动有关的现金 | V58: =IF(J58>0,"收到的其他与筹资活动有关的现金","支付的其他与筹资活动有关的现金") -> 支付的其他与筹资活动有关的现金
B59: 减资款出境 | D59: 46054 | E59: =-I59 -> 16500000 | I59: -16500000 | K59: =SUM(E59:J59) -> 0 | Q59: 收回投资所收到的现金 | U59: 支付的其他与筹资活动有关的现金
B60: 内部调拨 | D60: 46054 | E60: -15200000 | F60: =-E60 -> 15200000 | K60: =SUM(E60:J60) -> 0 | Q60: =IF(E60>0,"收到的其他与筹资活动有关的现金","支付的其他与筹资活动有关的现金") -> 支付的其他与筹资活动有关的现金 | R60: =IF(F60>0,"收到的其他与筹资活动有关的现金","支付的其他与筹资活动有关的现金") -> 收到的其他与筹资活动有关的现金 | S60: =IF(G60>0,"收到的其他与筹资活动有关的现金","支付的其他与筹资活动有关的现金") -> 支付的其他与筹资活动有关的现金 | T60: =IF(H60>0,"收到的其他与筹资活动有关的现金","支付的其他与筹资活动有关的现金") -> 支付的其他与筹资活动有关的现金 | U60: =IF(I60>0,"收到的其他与筹资活动有关的现金","支付的其他与筹资活动有关的现金") -> 支付的其他与筹资活动有关的现金 | V60: =IF(J60>0,"收到的其他与筹资活动有关的现金","支付的其他与筹资活动有关的现金") -> 支付的其他与筹资活动有关的现金
B61: 注资旭智私募 | D61: 46054 | E61: =-3920000-8000000*51% -> -8000000 | H61: =-E61 -> 8000000 | K61: =SUM(E61:J61) -> 0 | Q61: 投资支付的现金 | T61: 吸收投资所收到的现金
B62: 注资Albamen New Energy | D62: 46054 | F62: =-基金资金安排!C22*10000+10000 -> -7790000 | K62: =SUM(E62:J62) -> -7790000 | M62: =基金资金安排!C21*10000 -> 10400000 | R62: 投资支付的现金 | W62: =R62 -> 投资支付的现金
B63: 注资旭智咨询 | D63: 46054 | F63: =-ROUND(1052459*6.959,-3) -> -7324000 | G63: =-F63 -> 7324000 | K63: =SUM(E63:J63) -> 0 | R63: 投资支付的现金 | S63: 吸收投资所收到的现金
B64: 注资深圳曦风 | D64: 46054 | H64: =-基金资金安排!C18*10000 -> -2020408.2 | K64: =SUM(E64:J64) -> -2020408.2 | M64: =-基金资金安排!C17*10000 -> -8979591.8 | N64: =-M64-H64 -> 11000000 | T64: 投资支付的现金 | W64: 投资支付的现金
B65: 注资深圳新融 | D65: 46054 | G65: =-基金资金安排!C13*10000 -> -2375000 | K65: =SUM(E65:J65) -> -2375000 | N65: =-基金资金安排!C14*10000 -> -6935000 | O65: =-G65-N65+1000000 -> 10310000 | Q65: 投资支付的现金 | S65: 投资支付的现金 | W65: 投资支付的现金
B66: 内部调拨 | D66: 46054 | E66: =-F66 -> -350332 | F66: =400000*0.87583 -> 350332 | K66: =SUM(E66:J66) -> 0 | Q66: =IF(E66>0,"收到的其他与筹资活动有关的现金","支付的其他与筹资活动有关的现金") -> 支付的其他与筹资活动有关的现金 | R66: =IF(F66>0,"收到的其他与筹资活动有关的现金","支付的其他与筹资活动有关的现金") -> 收到的其他与筹资活动有关的现金 | S66: =IF(G66>0,"收到的其他与筹资活动有关的现金","支付的其他与筹资活动有关的现金") -> 支付的其他与筹资活动有关的现金 | T66: =IF(H66>0,"收到的其他与筹资活动有关的现金","支付的其他与筹资活动有关的现金") -> 支付的其他与筹资活动有关的现金 | U66: =IF(I66>0,"收到的其他与筹资活动有关的现金","支付的其他与筹资活动有关的现金") -> 支付的其他与筹资活动有关的现金 | V66: =IF(J66>0,"收到的其他与筹资活动有关的现金","支付的其他与筹资活动有关的现金") -> 支付的其他与筹资活动有关的现金
B67: 注资JV基金 | D67: 46054 | K67: =SUM(E67:J67) -> 0 | O67: =-基金资金安排!C7*10000 -> -5000000
B68: 费用支出 | D68: 46054 | E68: =-香港!C334*0.87583 -> -345423.71 | F68: =-(87932+9000+香港!D334)*0.87583 -> -460479.36 | G68: -707368 | H68: -333060 | I68: -2500 | J68: =INDEX('CF-ACPLYixing'!$E$29:$Q$29,MATCH($D68,'CF-ACPLYixing'!$E$4:$Q$4,0))+INDEX('CF-ACPLYixing'!$E$38:$Q$38,MATCH($D68,'CF-ACPLYixing'!$E$4:$Q$4,0)) -> -83.333333 | K68: =SUM(E68:J68) -> -1848914.4
B69: 现金余额 | D69: 46081 | E69: =SUM(E53:E68) -> 4508086.4 | F69: =SUM(F53:F68) -> 140819.64 | G69: =SUM(G53:G68) -> 5169556 | H69: =SUM(H53:H68) -> 8223841.8 | I69: =SUM(I53:I68) -> 172880 | J69: =SUM(J53:J68) -> 67953.667 | K69: =SUM(K53:K68) -> 18283138 | M69: =SUM(M53:M68) -> 1420408.2 | N69: =SUM(N53:N68) -> 4065000 | O69: =SUM(O53:O68) -> 5320000
B70: 现金余额实际3/6 | D70: 46082 | E70: =(7201987-(4598910-2500000))*0.87583 -> 4469427.9 | F70: =(238808-80000)*0.87583 -> 139088.81 | G70: =G69 -> 5169556 | H70: =H69 -> 8223841.8 | I70: =I69 -> 172880 | J70: =J69 -> 67953.667 | K70: =SUM(E70:J70) -> 18242748 | M70: =M69 -> 1420408.2 | N70: =N69 -> 4065000 | O70: =O69 -> 5320000
B71: 注资Albamen New Energy | D71: 46082 | K71: =SUM(E71:J71) -> 0 | M71: =-F71/75% -> 0 | R71: 投资支付的现金 | W71: =R71 -> 投资支付的现金
B72: 注资深圳曦风 | D72: 46082 | K72: =SUM(E72:J72) -> 0 | M72: =-M71 -> 0 | N72: =-H72-M72 -> 0 | T72: 投资支付的现金 | W72: 投资支付的现金
B73: 注资深圳新融 | D73: 46082 | K73: =SUM(E73:J73) -> 0 | N73: =G73/1250*3650 -> 0 | O73: =-G73-N73 -> 0 | Q73: 投资支付的现金 | W73: 投资支付的现金
B74: 注资JV基金 | D74: 46082 | K74: =SUM(E74:J74) -> 0
B75: 内部调拨 | D75: 46082 | E75: =-F75 -> -557979.18 | F75: =-F77 -> 557979.18 | G75: 210000 | K75: =SUM(E75:J75) -> 210000 | O75: =-G75 -> -210000 | Q75: =IF(E75>0,"收到的其他与筹资活动有关的现金","支付的其他与筹资活动有关的现金") -> 支付的其他与筹资活动有关的现金 | R75: =IF(F75>0,"收到的其他与筹资活动有关的现金","支付的其他与筹资活动有关的现金") -> 收到的其他与筹资活动有关的现金 | S75: =IF(G75>0,"收到的其他与筹资活动有关的现金","支付的其他与筹资活动有关的现金") -> 收到的其他与筹资活动有关的现金 | T75: =IF(H75>0,"收到的其他与筹资活动有关的现金","支付的其他与筹资活动有关的现金") -> 支付的其他与筹资活动有关的现金 | U75: =IF(I75>0,"收到的其他与筹资活动有关的现金","支付的其他与筹资活动有关的现金") -> 支付的其他与筹资活动有关的现金 | V75: =IF(J75>0,"收到的其他与筹资活动有关的现金","支付的其他与筹资活动有关的现金") -> 支付的其他与筹资活动有关的现金
B76: 减资款出境 | D76: 46082 | E76: =-I76 -> 0 | K76: =SUM(E76:J76) -> 0 | Q76: 收回投资所收到的现金 | U76: 支付的其他与筹资活动有关的现金
B77: 费用支出 | D77: 46082 | E77: =INDEX('CF-ACPLHK'!$E$29:$Q$29,MATCH(cashflow汇总实际!$D77,'CF-ACPLHK'!$E$4:$Q$4,0))+INDEX('CF-ACPLHK'!$E$38:$Q$38,MATCH($D77,'CF-ACPLHK'!$E$4:$Q$4,0)) -> -599170.54 | F77: =INDEX('CF-ACPL'!$E$29:$Q$29,MATCH($D77,'CF-ACPL'!$E$4:$Q$4,0))+INDEX('CF-ACPL'!$E$38:$Q$38,MATCH($D77,'CF-ACPL'!$E$4:$Q$4)) -> -557979.18 | G77: -614817 | H77: -360000 | I77: =INDEX('CF-ACPLGZ'!$E$29:$Q$29,MATCH(cashflow汇总实际!$D77,'CF-ACPLGZ'!$E$4:$Q$4,0))+INDEX('CF-ACPLGZ'!$E$38:$Q$38,MATCH($D77,'CF-ACPLGZ'!$E$4:$Q$4,0)) -> -475 | J77: =INDEX('CF-ACPLYixing'!$E$29:$Q$29,MATCH($D77,'CF-ACPLYixing'!$E$4:$Q$4,0))+INDEX('CF-ACPLYixing'!$E$38:$Q$38,MATCH($D77,'CF-ACPLYixing'!$E$4:$Q$4,0)) -> -83.333333 | K77: =SUM(E77:J77) -> -2132525.1
B78: 现金余额 | D78: 46112 | E78: =SUM(E70:E77) -> 3312278.2 | F78: =SUM(F70:F77) -> 139088.81 | G78: =SUM(G70:G77) -> 4764739 | H78: =SUM(H70:H77) -> 7863841.8 | I78: =SUM(I70:I77) -> 172405 | J78: =SUM(J70:J77) -> 67870.333 | K78: =SUM(K70:K77) -> 16320223 | M78: =SUM(M70:M77) -> 1420408.2 | N78: =SUM(N70:N77) -> 4065000 | O78: =SUM(O70:O77) -> 5110000
B79: 注资Albamen New Energy | D79: 46113 | F79: =-INDEX(情形1!$26:$26,MATCH(cashflow汇总实际!$D79,情形1!$3:$3,0))*10000 -> 0 | K79: =SUM(E79:J79) -> 0 | M79: =-F79/75% -> 0 | R79: 投资支付的现金 | W79: =R79 -> 投资支付的现金
B80: 注资深圳曦风 | D80: 46113 | H80: =-INDEX(情形1!$30:$30,MATCH(cashflow汇总实际!$D80,情形1!$3:$3,0))*10000 -> 0 | K80: =SUM(E80:J80) -> 0 | M80: =-M79 -> 0 | N80: =-H80-M80 -> 0 | T80: 投资支付的现金 | W80: 投资支付的现金
B81: 注资深圳新融 | D81: 46113 | G81: =-基金资金安排!H13*10000 -> -1275510.2 | K81: =SUM(E81:J81) -> -1275510.2 | N81: =-基金资金安排!H14*10000 -> -3724489.8 | O81: =-G81-N81 -> 5000000 | Q81: 投资支付的现金 | W81: 投资支付的现金
B82: 注资JV基金 | D82: 46113 | K82: =SUM(E82:J82) -> 0 | O82: =-10000000 -> -10000000
B83: 内部调拨 | D83: 46113 | E83: =-F83-M83 -> 66360.817 | F83: =-F84 -> 1353639.2 | K83: =SUM(E83:J83) -> 1420000 | M83: -1420000 | Q83: =IF(E83>0,"收到的其他与筹资活动有关的现金","支付的其他与筹资活动有关的现金") -> 收到的其他与筹资活动有关的现金 | R83: =IF(F83>0,"收到的其他与筹资活动有关的现金","支付的其他与筹资活动有关的现金") -> 收到的其他与筹资活动有关的现金 | S83: =IF(G83>0,"收到的其他与筹资活动有关的现金","支付的其他与筹资活动有关的现金") -> 支付的其他与筹资活动有关的现金 | T83: =IF(H83>0,"收到的其他与筹资活动有关的现金","支付的其他与筹资活动有关的现金") -> 支付的其他与筹资活动有关的现金 | U83: =IF(I83>0,"收到的其他与筹资活动有关的现金","支付的其他与筹资活动有关的现金") -> 支付的其他与筹资活动有关的现金 | V83: =IF(J83>0,"收到的其他与筹资活动有关的现金","支付的其他与筹资活动有关的现金") -> 支付的其他与筹资活动有关的现金
B84: 费用支出 | D84: 46113 | E84: =INDEX('CF-ACPLHK'!$E$29:$Q$29,MATCH(cashflow汇总实际!$D84,'CF-ACPLHK'!$E$4:$Q$4,0))+INDEX('CF-ACPLHK'!$E$38:$Q$38,MATCH($D84,'CF-ACPLHK'!$E$4:$Q$4,0)) -> -1049679 | F84: =INDEX('CF-ACPL'!$E$29:$Q$29,MATCH($D84,'CF-ACPL'!$E$4:$Q$4,0))+INDEX('CF-ACPL'!$E$38:$Q$38,MATCH($D84,'CF-ACPL'!$E$4:$Q$4)) -> -1353639.2 | G84: =-582167-17250*1.2-362250 -> -965117 | H84: =-340000-321000 -> -661000 | I84: =INDEX('CF-ACPLGZ'!$E$29:$Q$29,MATCH(cashflow汇总实际!$D84,'CF-ACPLGZ'!$E$4:$Q$4,0))+INDEX('CF-ACPLGZ'!$E$38:$Q$38,MATCH($D84,'CF-ACPLGZ'!$E$4:$Q$4,0)) -> -475 | J84: =INDEX('CF-ACPLYixing'!$E$29:$Q$29,MATCH($D84,'CF-ACPLYixing'!$E$4:$Q$4,0))+INDEX('CF-ACPLYixing'!$E$38:$Q$38,MATCH($D84,'CF-ACPLYixing'!$E$4:$Q$4,0)) -> -83.333333 | K84: =SUM(E84:J84) -> -4029993.6
B85: 现金余额 | D85: 46142 | E85: =SUM(E78:E84) -> 2328960 | F85: =SUM(F78:F84) -> 139088.81 | G85: =SUM(G78:G84) -> 2524111.8 | H85: =SUM(H78:H84) -> 7202841.8 | I85: =SUM(I78:I84) -> 171930 | J85: =SUM(J78:J84) -> 67787 | K85: =SUM(K78:K84) -> 12434719 | M85: =SUM(M78:M84) -> 408.16327 | N85: =SUM(N78:N84) -> 340510.2 | O85: =SUM(O78:O84) -> 110000
B86: 旭智富能股权转让款 | D86: 46143 | J86: 43500000 | K86: =SUM(E86:J86) -> 43500000 | V86: 收回投资所收到的现金 | W86: 收回投资所收到的现金
B87: 归还IDG借款 | D87: 46143 | J87: =J57*(1+4%*3/12) -> -15150000 | K87: =SUM(E87:J87) -> -15150000 | R87: 偿还债务所支付的现金 | V87: 偿还债务所支付的现金 | W87: 偿还债务所支付的现金
B88: 曦和基金退伙 | D88: 46143 | J88: =-19650000-250000 -> -19900000 | K88: =SUM(E88:J88) -> -19900000 | V88: 偿还债务所支付的现金 | W88: 偿还债务所支付的现金
B89: 现金分配 | D89: 46143 | G89: =-J89*10% -> 845000 | I89: =-J89*0.9 -> 7605000 | J89: =-SUM(J86:J88) -> -8450000 | K89: =SUM(E89:J89) -> 0 | Q89: NA | S89: 收回投资所收到的现金 | U89: 收回投资所收到的现金 | V89: 支付的其他与筹资活动有关的现金
B90: 内部调拨 | D90: 46143 | G90: 3000000 | I90: =-G90 -> -3000000 | K90: =SUM(E90:J90) -> 0 | M90: =-M54 -> 0 | Q90: =IF(E90>0,"收到的其他与筹资活动有关的现金","支付的其他与筹资活动有关的现金") -> 支付的其他与筹资活动有关的现金 | R90: =IF(F90>0,"收到的其他与筹资活动有关的现金","支付的其他与筹资活动有关的现金") -> 支付的其他与筹资活动有关的现金 | S90: =IF(G90>0,"收到的其他与筹资活动有关的现金","支付的其他与筹资活动有关的现金") -> 收到的其他与筹资活动有关的现金 | T90: =IF(H90>0,"收到的其他与筹资活动有关的现金","支付的其他与筹资活动有关的现金") -> 支付的其他与筹资活动有关的现金 | U90: =IF(I90>0,"收到的其他与筹资活动有关的现金","支付的其他与筹资活动有关的现金") -> 支付的其他与筹资活动有关的现金 | V90: =IF(J90>0,"收到的其他与筹资活动有关的现金","支付的其他与筹资活动有关的现金") -> 支付的其他与筹资活动有关的现金
B91: 减资款出境 | D91: 46143 | E91: =-I91 -> 4505000 | I91: =-SUM(I89:I90)+100000 -> -4505000 | K91: =SUM(E91:J91) -> 0 | Q91: 收回投资所收到的现金 | U91: 支付的其他与筹资活动有关的现金
B92: 注资特变新平台 | D92: 46143 | K92: =SUM(E92:J92) -> 0 | S92: 投资支付的现金
B93: 注资Albamen New Energy | D93: 46143 | F93: =-INDEX(情形1!$26:$26,MATCH(cashflow汇总实际!$D93,情形1!$3:$3,0))*10000 -> 0 | K93: =SUM(E93:J93) -> 0 | M93: =-F93/75% -> 0 | R93: 投资支付的现金 | W93: =R93 -> 投资支付的现金
B94: 注资深圳曦风 | D94: 46143 | H94: =-INDEX(情形1!$30:$30,MATCH(cashflow汇总实际!$D94,情形1!$3:$3,0))*10000 -> 0 | K94: =SUM(E94:J94) -> 0 | M94: =H94/900*4000 -> 0 | N94: =-H94-M94 -> 0 | T94: 投资支付的现金 | W94: 投资支付的现金
B95: 注资深圳新融 | D95: 46143 | G95: =-INDEX(情形1!$28:$28,MATCH(cashflow汇总实际!$D95,情形1!$3:$3))*10000 -> 0 | K95: =SUM(E95:J95) -> 0 | N95: =G95/1250*3650 -> 0 | O95: =-G95-N95 -> 0 | Q95: 投资支付的现金 | W95: 投资支付的现金
B96: 注资JV基金 | D96: 46143 | K96: =SUM(E96:J96) -> 0 | O96: =-INDEX(情形1!$32:$32,MATCH(cashflow汇总实际!D96,情形1!$3:$3,0))*10000 -> 0
B97: 内部调拨 | D97: 46143 | E97: =-F97-M97 -> -2093969 | F97: =-F98 -> 673968.98 | K97: =SUM(E97:J97) -> -1420000 | M97: =-M83 -> 1420000 | Q97: =IF(E97>0,"收到的其他与筹资活动有关的现金","支付的其他与筹资活动有关的现金") -> 支付的其他与筹资活动有关的现金 | R97: =IF(F97>0,"收到的其他与筹资活动有关的现金","支付的其他与筹资活动有关的现金") -> 收到的其他与筹资活动有关的现金 | S97: =IF(G97>0,"收到的其他与筹资活动有关的现金","支付的其他与筹资活动有关的现金") -> 支付的其他与筹资活动有关的现金 | T97: =IF(H97>0,"收到的其他与筹资活动有关的现金","支付的其他与筹资活动有关的现金") -> 支付的其他与筹资活动有关的现金 | U97: =IF(I97>0,"收到的其他与筹资活动有关的现金","支付的其他与筹资活动有关的现金") -> 支付的其他与筹资活动有关的现金 | V97: =IF(J97>0,"收到的其他与筹资活动有关的现金","支付的其他与筹资活动有关的现金") -> 支付的其他与筹资活动有关的现金
B98: 费用支出 | D98: 46143 | E98: =INDEX('CF-ACPLHK'!$E$29:$Q$29,MATCH(cashflow汇总实际!$D98,'CF-ACPLHK'!$E$4:$Q$4,0))+INDEX('CF-ACPLHK'!$E$38:$Q$38,MATCH($D98,'CF-ACPLHK'!$E$4:$Q$4,0)) -> -434813.39 | F98: =INDEX('CF-ACPL'!$E$29:$Q$29,MATCH($D98,'CF-ACPL'!$E$4:$Q$4,0))+INDEX('CF-ACPL'!$E$38:$Q$38,MATCH($D98,'CF-ACPL'!$E$4:$Q$4)) -> -673968.98 | G98: =INDEX('CF-ACPLSZ'!$E$29:$Q$29,MATCH($D98,'CF-ACPLSZ'!$E$4:$Q$4,0))+INDEX('CF-ACPLSZ'!$E$38:$Q$38,MATCH($D98,'CF-ACPLSZ'!$E$4:$Q$4)) -> 1946329.3 | H98: =INDEX('CF-ACPSZL'!$E$29:$Q$29,MATCH(cashflow汇总实际!$D98,'CF-ACPSZL'!$E$4:$Q$4,0))+INDEX('CF-ACPSZL'!$E$38:$Q$38,MATCH($D98,'CF-ACPSZL'!$E$4:$Q$4,0)) -> -358787.24 | I98: =INDEX('CF-ACPLGZ'!$E$29:$Q$29,MATCH(cashflow汇总实际!$D98,'CF-ACPLGZ'!$E$4:$Q$4,0))+INDEX('CF-ACPLGZ'!$E$38:$Q$38,MATCH($D98,'CF-ACPLGZ'!$E$4:$Q$4,0)) -> -475 | J98: =INDEX('CF-ACPLYixing'!$E$29:$Q$29,MATCH($D98,'CF-ACPLYixing'!$E$4:$Q$4,0))+INDEX('CF-ACPLYixing'!$E$38:$Q$38,MATCH($D98,'CF-ACPLYixing'!$E$4:$Q$4,0)) -> -83.333333 | K98: =SUM(E98:J98) -> 478201.31
B99: 现金余额 | D99: 46173 | E99: =SUM(E85:E98) -> 4305177.6 | F99: =SUM(F85:F98) -> 139088.81 | G99: =SUM(G85:G98) -> 8315441.1 | H99: =SUM(H85:H98) -> 6844054.6 | I99: =SUM(I85:I98) -> 271455 | J99: =SUM(J85:J98) -> 67703.667 | K99: =SUM(K85:K98) -> 19942921 | M99: =SUM(M85:M98) -> 1420408.2 | N99: =SUM(N85:N98) -> 340510.2 | O99: =SUM(O85:O98) -> 110000
B100: 注资Albamen New Energy | D100: 46174 | F100: =-INDEX(情形1!$26:$26,MATCH(cashflow汇总实际!$D100,情形1!$3:$3,0))*10000 -> 0 | K100: =SUM(E100:J100) -> 0 | M100: =-F100/75% -> 0 | R100: 投资支付的现金 | W100: =R100 -> 投资支付的现金
B101: 注资深圳曦风 | D101: 46174 | H101: =-INDEX(情形1!$30:$30,MATCH(cashflow汇总实际!$D101,情形1!$3:$3,0))*10000 -> 0 | K101: =SUM(E101:J101) -> 0 | M101: =H101/900*4000 -> 0 | N101: =-H101-M101 -> 0 | T101: 投资支付的现金 | W101: 投资支付的现金
B102: 注资深圳新融 | D102: 46174 | G102: =-INDEX(情形1!$28:$28,MATCH(cashflow汇总实际!$D102,情形1!$3:$3))*10000 -> 0 | K102: =SUM(E102:J102) -> 0 | N102: =G102/1250*3650 -> 0 | O102: =-G102-N102 -> 0 | Q102: 投资支付的现金 | W102: 投资支付的现金
B103: 注资JV基金 | D103: 46174 | K103: =SUM(E103:J103) -> 0 | O103: =-INDEX(情形1!$32:$32,MATCH(cashflow汇总实际!D103,情形1!$3:$3,0))*10000 -> 0
...

Sheet cashflow汇总预算2026
E1: ACPLHK | F1: ACPL | G1: ACPLSZ | H1: ACPLSZL | I1: ACPLGZ | J1: Yixing | K1: Total | M1: Albamen New Energy | N1: 深圳曦风 | O1: 深圳新融 | Q1: ACPLHK | R1: ACPL | S1: ACPLSZ | T1: ACPLSZL | U1: ACPLGZ | V1: Yixing | W1: Total
E2: RMB | F2: RMB | G2: RMB | H2: RMB | I2: RMB | J2: RMB | K2: RMB
B3: Cash balance | D3: 45866 | E3: =2765593+809735*0.91+46072*4.71 -> 3719451 | F3: =50223*0.91 -> 45702.93 | G3: 1757806 | H3: 5744218.3 | I3: 22134.7 | K3: =SUM(E3:I3) -> 11289313
B4: Transfer | E4: =-F4 -> -697963.14 | F4: =-F5 -> 697963.14 | K4: =SUM(E4:I4) -> 0
B5: Jul 2025 expenses | E5: -650484 | F5: -697963.14 | G5: -652247 | H5: -384285.96 | I5: -2321.86 | K5: =SUM(E5:I5) -> -2387302 | M5: +657k: ACPLSZ: 120k 鉴衡服务费; 普华22.5k咨询费；63k Q3深圳租金 ACPLHK: 82K IT服务; 62K 审计费； ACPL: 218k HK SPV费用; 90K 审计费
B6: Estimated Cash balance | D6: 45869 | E6: =SUM(E3:E5) -> 2371003.8 | F6: =SUM(F3:F5) -> 45702.93 | G6: =SUM(G3:G5) -> 1105559 | H6: =SUM(H3:H5) -> 5359932.3 | I6: =SUM(I3:I5) -> 19812.84 | K6: =SUM(K3:K5) -> 8902010.9
B8: Cash balance | D8: 45869 | E8: =2653612*0.91472 -> 2427312 | F8: =52344*0.91472 -> 47880.104 | G8: 1231689 | H8: 5444989 | I8: 49812.84 | K8: =SUM(E8:I8) -> 9201682.9
B9: Transfer | E9: =-F9 -> -360000 | F9: 360000 | K9: =SUM(E9:I9) -> 0
B10: injection | E10: =3600000*0.9 -> 3240000 | G10: =3600000*0.1 -> 360000 | K10: =SUM(E10:I10) -> 3600000
B11: Aug 2025 expenses | E11: =-香港!C213 -> -530274.16 | F11: =-香港!D213 -> -363985.38 | G11: =-'202601-202603（Forecast）'!#REF! -> #REF! | H11: =-'202601-202603（Forecast）'!#REF! -> #REF! | I11: =-'202601-202603（Forecast）'!#REF! -> #REF! | K11: =SUM(E11:I11) -> #REF! | M11: ACPLSZ: 普华22.5k咨询费 ACPLHK: 145K IT服务(license + cloud storage)
B12: Cash balance | D12: 45900 | E12: =SUM(E8:E11) -> 4777037.8 | F12: =SUM(F8:F11) -> 43894.721 | G12: =SUM(G8:G11) -> #REF! | H12: =SUM(H8:H11) -> #REF! | I12: =SUM(I8:I11) -> #REF! | K12: =SUM(K8:K11) -> #REF! | M12: *** ACPLHK will breach the liquid cap requirement after settlement of Aug expenses without capital injection
B14: Cash balance | D14: 45900 | E14: 4794239 | F14: 82455 | G14: 1111289 | H14: 5068590.2 | I14: 31863.6 | K14: =SUM(E14:I14) -> 11088437
B15: Transfer | E15: =-F15 -> -617625 | F15: =675000*0.915 -> 617625 | K15: =SUM(E15:I15) -> 0
B16: Sept 2025 expenses | E16: =-香港!C236 -> -499864.88 | F16: =-香港!D236+180000*0.915 -> -502745.06 | G16: =-'202601-202603（Forecast）'!#REF! -> #REF! | H16: =-'202601-202603（Forecast）'!O52 -> -766650.99 | I16: 0 | K16: =SUM(E16:I16) -> #REF!
B17: Cash balance | D17: 45930 | E17: =SUM(E14:E16) -> 3676749.1 | F17: =SUM(F14:F16) -> 197334.94 | G17: =SUM(G14:G16) -> #REF! | H17: =SUM(H14:H16) -> 4301939.2 | I17: =SUM(I14:I16) -> 31863.6 | K17: =SUM(K14:K16) -> #REF!
B18: Transfer | E18: =-F18 -> -502745.06 | F18: =-F20 -> 502745.06 | K18: =SUM(E18:I18) -> 0
B19: injection
B20: October 2025 expenses | E20: -520253 | F20: =F16 -> -502745.06 | G20: =-'202601-202603（Forecast）'!I52 -> -789872.76 | H20: =-'202601-202603（Forecast）'!P52 -> -344650.99 | I20: 0 | K20: =SUM(E20:I20) -> -2157521.8
B22: Cash balance | D22: 45961 | E22: =3251528*0.92 -> 2991405.8 | F22: =65292*0.92 -> 60068.64 | G22: =SUM('202601-202603（Forecast）'!I14,'202601-202603（Forecast）'!L14) -> 561081.68 | H22: ='202601-202603（Forecast）'!O14 -> 2694352.1 | I22: ='202601-202603（Forecast）'!F14 -> 86665.41 | K22: =SUM(E22:J22) -> 6393573.6
B23: Transfer | E23: =香港!C274*0.92 -> -368000 | F23: =-E23 -> 368000 | G23: =-H23 -> 450000 | H23: -450000 | I23: =-'202601-202603（Forecast）'!F52 -> -9982000 | K23: =SUM(E23:J23) -> -9982000
B24: November 2025 expenses | E24: =-香港!C272*0.92 -> -493674.76 | F24: =-香港!D272*0.92 -> -394737.96 | G24: -450000 | H24: -400000 | I24: 0 | K24: =SUM(E24:J24) -> -1738412.7
B25: Cash balance | D25: 45991 | E25: =SUM(E22:E24) -> 2129731 | F25: =SUM(F22:F24) -> 33330.68 | G25: =SUM(G22:G24) -> 561081.68 | H25: =SUM(H22:H24) -> 1844352.1 | I25: =SUM(I22:I24) -> -9895334.6 | K25: =SUM(K22:K24) -> -5326839.2
P26: Dec expense payments | R26: =-SUM(K35:K35) -> 1936677.9
B27: 实际现金余额 | D27: 45991 | E27: =2341169 -> 2341169 | F27: 46479 | G27: =104222.77+53825.34+17880.93 -> 175929.04 | H27: 3460729 | I27: 31951 | J27: 57445 | K27: =SUM(E27:J27) -> 6113702
B28: 利息收入 | E28: 3.34 | F28: 0.06 | G28: =5.68+3.33+2.26 -> 11.27 | H28: =3329.24+247.83+0.02 -> 3577.09 | I28: =41018+0.07+0.21+0.17+7.85 -> 41026.3 | J28: 7.26 | K28: =SUM(E28:J28) -> 44625.32
B29: 注资深圳曦和 | H29: -400000 | K29: =SUM(E29:J29) -> -400000 | P29: Dec non-routine items:
B30: IDG借款 | F30: =2000000*0.9 -> 1800000 | K30: =SUM(E30:J30) -> 1800000 | P30: IT cloud storage for 2025 | R30: =-香港!C286*0.92 -> -138000
B31: 现金分配 | G31: =-J31*10% -> 0 | I31: =-J31*0.9 -> 0 | K31: =SUM(E31:J31) -> 0 | P31: Huw 7-12 2025 service fee | R31: =-香港!C293*0.92 -> -276000
B32: 内部调拨 | K32: =SUM(E32:J32) -> 0 | P32: Cayman entity expenses | R32: =-SUM(香港!I283:I284)*7.1-香港!I293*7.1 -> -269912.25
B33: 减资款出境 | E33: =-I33 -> 0 | I33: =-SUM(I30:I32) -> 0 | K33: =SUM(E33:J33) -> 0 | P33: IDG Q1 service fee (Michael) | R33: =-'202601-202603（Forecast）'!I45 -> 0
B34: 内部调拨 | E34: =-F34 -> 647834.4 | F34: =-(800000-80000)*0.89977 -> -647834.4 | G34: 345000 | H34: -280000 | I34: -65000 | K34: =SUM(E34:J34) -> 0 | R34: =SUM(R30:R33) -> -683912.25
B35: 费用支出 | E35: =-395768.68 -> -395768.68 | F35: =-103720*0.9-637830.25 -> -731178.25 | G35: =-329240.35-105997.92 -> -435238.27 | H35: -374466.81 | I35: -0.9 | J35: -25 | K35: =SUM(E35:J35) -> -1936677.9 | P35: Dec routine expense payments | R35: =R26+R34 -> 1252765.7
B36: 现金余额 | D36: 46022 | E36: =SUM(E27:E35) -> 2593238.1 | F36: =SUM(F27:F35) -> 467466.41 | G36: =SUM(G27:G35) -> 85702.04 | H36: =SUM(H27:H35) -> 2409839.3 | I36: =SUM(I27:I35) -> 7976.4 | J36: =SUM(J27:J35) -> 57427.26 | K36: =SUM(K27:K35) -> 5621649.5
B37: 实际现金余额 | D37: 46022 | E37: 2574529 | F37: 466588 | G37: =G36 -> 85702.04 | H37: =H36 -> 2409839.3 | I37: =I36 -> 7976.4 | J37: =J36 -> 57427.26 | K37: =SUM(E37:J37) -> 5602062
B38: 曦和基金股转款 | D38: 46023 | I38: 10000000 | K38: =SUM(E38:J38) -> 10000000 | U38: 取得借款所收到的现金 | W38: 取得借款所收到的现金
B39: 内部调拨 | D39: 46023 | G39: 1540000 | I39: =-G39 -> -1540000 | K39: =SUM(E39:J39) -> 0 | Q39: =IF(E39>0,"收到的其他与筹资活动有关的现金","支付的其他与筹资活动有关的现金") -> 支付的其他与筹资活动有关的现金 | R39: =IF(F39>0,"收到的其他与筹资活动有关的现金","支付的其他与筹资活动有关的现金") -> 支付的其他与筹资活动有关的现金 | S39: =IF(G39>0,"收到的其他与筹资活动有关的现金","支付的其他与筹资活动有关的现金") -> 收到的其他与筹资活动有关的现金 | T39: =IF(H39>0,"收到的其他与筹资活动有关的现金","支付的其他与筹资活动有关的现金") -> 支付的其他与筹资活动有关的现金 | U39: =IF(I39>0,"收到的其他与筹资活动有关的现金","支付的其他与筹资活动有关的现金") -> 支付的其他与筹资活动有关的现金 | V39: =IF(J39>0,"收到的其他与筹资活动有关的现金","支付的其他与筹资活动有关的现金") -> 支付的其他与筹资活动有关的现金
B40: 注资深圳曦和 | D40: 46023 | H40: -400000 | K40: =SUM(E40:J40) -> -400000 | T40: 投资支付的现金 | W40: 投资支付的现金
B41: 注资宜兴旭智 | D41: 46023 | G41: -144000 | I41: -3516000 | J41: =-G41-I41 -> 3660000 | K41: =SUM(E41:J41) -> 0 | Q41: NA | S41: 投资支付的现金 | U41: 投资支付的现金 | V41: 吸收投资所收到的现金
B42: 内部调拨 | D42: 46023 | G42: =-H42 -> -780000 | H42: =500000+280000 -> 780000 | K42: =SUM(E42:J42) -> 0 | Q42: =IF(E42>0,"收到的其他与筹资活动有关的现金","支付的其他与筹资活动有关的现金") -> 支付的其他与筹资活动有关的现金 | R42: =IF(F42>0,"收到的其他与筹资活动有关的现金","支付的其他与筹资活动有关的现金") -> 支付的其他与筹资活动有关的现金 | S42: =IF(G42>0,"收到的其他与筹资活动有关的现金","支付的其他与筹资活动有关的现金") -> 支付的其他与筹资活动有关的现金 | T42: =IF(H42>0,"收到的其他与筹资活动有关的现金","支付的其他与筹资活动有关的现金") -> 收到的其他与筹资活动有关的现金 | U42: =IF(I42>0,"收到的其他与筹资活动有关的现金","支付的其他与筹资活动有关的现金") -> 支付的其他与筹资活动有关的现金 | V42: =IF(J42>0,"收到的其他与筹资活动有关的现金","支付的其他与筹资活动有关的现金") -> 支付的其他与筹资活动有关的现金
B43: 减资款出境 | D43: 46023 | E43: =-I43 -> 4924000 | I43: =-SUM(I38:I41)+20000 -> -4924000 | K43: =SUM(E43:J43) -> 0 | Q43: 收回投资所收到的现金 | U43: 支付的其他与筹资活动有关的现金
B44: 内部调拨 | D44: 46023 | E44: =-2000000*0.9 -> -1800000 | F44: =-E44 -> 1800000 | K44: =SUM(E44:J44) -> 0 | Q44: =IF(E44>0,"收到的其他与筹资活动有关的现金","支付的其他与筹资活动有关的现金") -> 支付的其他与筹资活动有关的现金 | R44: =IF(F44>0,"收到的其他与筹资活动有关的现金","支付的其他与筹资活动有关的现金") -> 收到的其他与筹资活动有关的现金 | S44: =IF(G44>0,"收到的其他与筹资活动有关的现金","支付的其他与筹资活动有关的现金") -> 支付的其他与筹资活动有关的现金 | T44: =IF(H44>0,"收到的其他与筹资活动有关的现金","支付的其他与筹资活动有关的现金") -> 支付的其他与筹资活动有关的现金 | U44: =IF(I44>0,"收到的其他与筹资活动有关的现金","支付的其他与筹资活动有关的现金") -> 支付的其他与筹资活动有关的现金 | V44: =IF(J44>0,"收到的其他与筹资活动有关的现金","支付的其他与筹资活动有关的现金") -> 支付的其他与筹资活动有关的现金
B45: 归还IDG借款 | D45: 46023 | F45: =-2003452*0.9 -> -1803106.8 | J45: -3649364.4 | K45: =SUM(E45:J45) -> -5452471.2 | R45: 偿还债务所支付的现金 | V45: 偿还债务所支付的现金 | W45: 偿还债务所支付的现金
B46: 现金余额 | D46: 46023 | E46: =SUM(E37:E45) -> 5698529 | F46: =SUM(F37:F45) -> 463481.2 | G46: =SUM(G37:G45) -> 701702.04 | H46: =SUM(H37:H45) -> 2789839.3 | I46: =SUM(I37:I45) -> 27976.4 | J46: =SUM(J37:J45) -> 68062.88 | K46: =SUM(K37:K45) -> 9749590.8
B47: 费用支出 | D47: 46023 | E47: =-香港!C313*0.92-香港!C293*0.92-7600*0.9 -> -716567.89 | F47: =-香港!C315*0.92-9000*0.9 -> -527957.96 | G47: =-('202601-202603（Forecast）'!I52-'202601-202603（Forecast）'!I50-'202601-202603（Forecast）'!I47-'202601-202603（Forecast）'!I45)-30752.77-9434.66-40281.7 -> -726341.89 | H47: =-('202601-202603（Forecast）'!O52-'202601-202603（Forecast）'!O50)-57483.79 -> -424134.78 | I47: =-('202601-202603（Forecast）'!F52-'202601-202603（Forecast）'!F50-'202601-202603（Forecast）'!F48-'202601-202603（Forecast）'!F47) -> -2000 | K47: =SUM(E47:J47) -> -2397002.5
B48: 曦和基金股转款 | D48: 46023 | I48: 9650000 | K48: =SUM(E48:J48) -> 9650000 | U48: 取得借款所收到的现金 | W48: 取得借款所收到的现金
B49: 减资款出境 | D49: 46023 | E49: =-I49 -> 7000000 | I49: -7000000 | K49: =SUM(E49:J49) -> 0 | Q49: 收回投资所收到的现金 | U49: 支付的其他与筹资活动有关的现金
B50: 内部调拨 | D50: 46023 | E50: -100000 | F50: =-E50 -> 100000 | K50: =SUM(E50:J50) -> 0 | Q50: =IF(E50>0,"收到的其他与筹资活动有关的现金","支付的其他与筹资活动有关的现金") -> 支付的其他与筹资活动有关的现金 | R50: =IF(F50>0,"收到的其他与筹资活动有关的现金","支付的其他与筹资活动有关的现金") -> 收到的其他与筹资活动有关的现金 | S50: =IF(G50>0,"收到的其他与筹资活动有关的现金","支付的其他与筹资活动有关的现金") -> 支付的其他与筹资活动有关的现金 | T50: =IF(H50>0,"收到的其他与筹资活动有关的现金","支付的其他与筹资活动有关的现金") -> 支付的其他与筹资活动有关的现金 | U50: =IF(I50>0,"收到的其他与筹资活动有关的现金","支付的其他与筹资活动有关的现金") -> 支付的其他与筹资活动有关的现金 | V50: =IF(J50>0,"收到的其他与筹资活动有关的现金","支付的其他与筹资活动有关的现金") -> 支付的其他与筹资活动有关的现金
B51: 费用支出 | D51: 46023 | K51: =SUM(E51:J51) -> 0
B52: 现金余额 | D52: 46023 | E52: =SUM(E46:E51) -> 11881961 | F52: =SUM(F46:F51) -> 35523.24 | G52: =SUM(G46:G51) -> -24639.85 | H52: =SUM(H46:H51) -> 2365704.5 | I52: =SUM(I46:I51) -> 2675976.4 | J52: =SUM(J46:J51) -> 68062.88 | K52: =SUM(K46:K51) -> 17002588 | M52: =SUM(M46:M51) -> 0 | N52: =SUM(N46:N51) -> 0 | O52: =SUM(O46:O51) -> 0
B53: IDG借款 | D53: 46054 | J53: 15000000 | K53: =SUM(E53:J53) -> 15000000 | V53: 取得借款所收到的现金 | W53: 取得借款所收到的现金
B54: 减资款分配 | D54: 46054 | G54: =-$J$54*10% -> 1500000 | I54: =-$J$54*90% -> 13500000 | J54: =-J53 -> -15000000 | K54: =SUM(E54:J54) -> 0 | S54: 收回投资所收到的现金 | U54: 收回投资所收到的现金 | V54: 支付的其他与筹资活动有关的现金
B55: 内部调拨 | D55: 46054 | G55: =-G54+1000000 -> -500000 | I55: =-G55 -> 500000 | K55: =SUM(E55:J55) -> 0 | Q55: =IF(E55>0,"收到的其他与筹资活动有关的现金","支付的其他与筹资活动有关的现金") -> 支付的其他与筹资活动有关的现金 | R55: =IF(F55>0,"收到的其他与筹资活动有关的现金","支付的其他与筹资活动有关的现金") -> 支付的其他与筹资活动有关的现金 | S55: =IF(G55>0,"收到的其他与筹资活动有关的现金","支付的其他与筹资活动有关的现金") -> 支付的其他与筹资活动有关的现金 | T55: =IF(H55>0,"收到的其他与筹资活动有关的现金","支付的其他与筹资活动有关的现金") -> 支付的其他与筹资活动有关的现金 | U55: =IF(I55>0,"收到的其他与筹资活动有关的现金","支付的其他与筹资活动有关的现金") -> 收到的其他与筹资活动有关的现金 | V55: =IF(J55>0,"收到的其他与筹资活动有关的现金","支付的其他与筹资活动有关的现金") -> 支付的其他与筹资活动有关的现金
B56: 减资款出境 | D56: 46054 | E56: =-I56 -> 16500000 | I56: -16500000 | K56: =SUM(E56:J56) -> 0 | Q56: 收回投资所收到的现金 | U56: 支付的其他与筹资活动有关的现金
B57: 内部调拨 | D57: 46054 | E57: =-F57 -> -15200000 | F57: 15200000 | G57: =-210000 -> -210000 | K57: =SUM(E57:J57) -> -210000 | O57: =-G57 -> 210000 | Q57: =IF(E57>0,"收到的其他与筹资活动有关的现金","支付的其他与筹资活动有关的现金") -> 支付的其他与筹资活动有关的现金 | R57: =IF(F57>0,"收到的其他与筹资活动有关的现金","支付的其他与筹资活动有关的现金") -> 收到的其他与筹资活动有关的现金 | S57: =IF(G57>0,"收到的其他与筹资活动有关的现金","支付的其他与筹资活动有关的现金") -> 支付的其他与筹资活动有关的现金 | T57: =IF(H57>0,"收到的其他与筹资活动有关的现金","支付的其他与筹资活动有关的现金") -> 支付的其他与筹资活动有关的现金 | U57: =IF(I57>0,"收到的其他与筹资活动有关的现金","支付的其他与筹资活动有关的现金") -> 支付的其他与筹资活动有关的现金 | V57: =IF(J57>0,"收到的其他与筹资活动有关的现金","支付的其他与筹资活动有关的现金") -> 支付的其他与筹资活动有关的现金
B58: 注资旭智私募 | D58: 46054 | E58: -8000000 | H58: =-E58 -> 8000000 | K58: =SUM(E58:J58) -> 0 | Q58: 投资支付的现金 | T58: 吸收投资所收到的现金
B59: 注资Albamen New Energy | D59: 46054 | F59: =-INDEX(情形1!$32:$32,MATCH(cashflow汇总预算2026!$D59,情形1!$3:$3,0))*10000 -> 0 | K59: =SUM(E59:J59) -> 0 | R59: 投资支付的现金 | W59: =R59 -> 投资支付的现金
B60: 注资旭智咨询 | D60: 46054 | F60: -7324000 | G60: =-F60 -> 7324000 | K60: =SUM(E60:J60) -> 0 | R60: 投资支付的现金 | S60: 吸收投资所收到的现金
B61: 内部调拨 | D61: 46054 | E61: -400000 | F61: =-E61 -> 400000 | K61: =SUM(E61:J61) -> 0 | M61: =-F61 -> -400000 | Q61: =IF(E61>0,"收到的其他与筹资活动有关的现金","支付的其他与筹资活动有关的现金") -> 支付的其他与筹资活动有关的现金 | R61: =IF(F61>0,"收到的其他与筹资活动有关的现金","支付的其他与筹资活动有关的现金") -> 收到的其他与筹资活动有关的现金 | S61: =IF(G61>0,"收到的其他与筹资活动有关的现金","支付的其他与筹资活动有关的现金") -> 支付的其他与筹资活动有关的现金 | T61: =IF(H61>0,"收到的其他与筹资活动有关的现金","支付的其他与筹资活动有关的现金") -> 支付的其他与筹资活动有关的现金 | U61: =IF(I61>0,"收到的其他与筹资活动有关的现金","支付的其他与筹资活动有关的现金") -> 支付的其他与筹资活动有关的现金 | V61: =IF(J61>0,"收到的其他与筹资活动有关的现金","支付的其他与筹资活动有关的现金") -> 支付的其他与筹资活动有关的现金
B62: 注资深圳曦风 | D62: 46054 | H62: =-INDEX(情形1!$32:$32,MATCH(cashflow汇总预算2026!$D62,情形1!$3:$3,0))*10000 -> 0 | K62: =SUM(E62:J62) -> 0 | N62: =-M62-H62 -> 0 | T62: 投资支付的现金 | W62: 投资支付的现金
B63: 注资深圳新融 | D63: 46054 | G63: =-INDEX(情形1!$32:$32,MATCH(cashflow汇总预算2026!$D63,情形1!$3:$3,0))*10000 -> 0 | K63: =SUM(E63:J63) -> 0 | Q63: 投资支付的现金 | S63: 投资支付的现金 | W63: 投资支付的现金
B64: 注资JV基金 | D64: 46054 | K64: =SUM(E64:J64) -> 0 | O64: =-INDEX(情形1!$32:$32,MATCH(cashflow汇总预算2026!D64,情形1!$3:$3,0))*10000 -> 0
B65: 费用支出 | D65: 46054 | E65: =INDEX('CF-ACPLHK'!$E$29:$Q$29,MATCH(cashflow汇总预算2026!$D65,'CF-ACPLHK'!$E$4:$Q$4,0))+INDEX('CF-ACPLHK'!$E$38:$Q$38,MATCH($D65,'CF-ACPLHK'!$E$4:$Q$4,0)) -> -458780.54 | F65: =INDEX('CF-ACPL'!$E$29:$Q$29,MATCH($D65,'CF-ACPL'!$E$4:$Q$4,0))+INDEX('CF-ACPL'!$E$38:$Q$38,MATCH($D65,'CF-ACPL'!$E$4:$Q$4)) -> -445479.18 | G65: =INDEX('CF-ACPLSZ'!$E$29:$Q$29,MATCH($D65,'CF-ACPLSZ'!$E$4:$Q$4,0))+INDEX('CF-ACPLSZ'!$E$38:$Q$38,MATCH($D65,'CF-ACPLSZ'!$E$4:$Q$4)) -> -674810.96 | H65: =INDEX('CF-ACPSZL'!$E$29:$Q$29,MATCH(cashflow汇总预算2026!$D65,'CF-ACPSZL'!$E$4:$Q$4,0))+INDEX('CF-ACPSZL'!$E$38:$Q$38,MATCH($D65,'CF-ACPSZL'!$E$4:$Q$4,0)) -> -316982.28 | I65: =INDEX('CF-ACPLGZ'!$E$29:$Q$29,MATCH(cashflow汇总预算2026!$D65,'CF-ACPLGZ'!$E$4:$Q$4,0))+INDEX('CF-ACPLGZ'!$E$38:$Q$38,MATCH($D65,'CF-ACPLGZ'!$E$4:$Q$4,0)) -> -475 | J65: =INDEX('CF-ACPLYixing'!$E$29:$Q$29,MATCH($D65,'CF-ACPLYixing'!$E$4:$Q$4,0))+INDEX('CF-ACPLYixing'!$E$38:$Q$38,MATCH($D65,'CF-ACPLYixing'!$E$4:$Q$4,0)) -> -83.333333 | K65: =SUM(E65:J65) -> -1896611.3 | O65: -200000
B66: 现金余额 | D66: 46081 | E66: =SUM(E52:E65) -> 4323180.6 | F66: =SUM(F52:F65) -> 7866044.1 | G66: =SUM(G52:G65) -> 7414549.2 | H66: =SUM(H52:H65) -> 10048722 | I66: =SUM(I52:I65) -> 175501.4 | J66: =SUM(J52:J65) -> 67979.547 | K66: =SUM(K52:K65) -> 29895977 | M66: =SUM(M52:M65) -> -400000 | N66: =SUM(N52:N65) -> 0 | O66: =SUM(O52:O65) -> 10000
B67: 注资Albamen New Energy | D67: 46082 | F67: =-INDEX(情形1!$26:$26,MATCH(cashflow汇总预算2026!$D67,情形1!$3:$3,0))*10000 -> -7800000 | K67: =SUM(E67:J67) -> -7800000 | M67: =-F67/75% -> 10400000 | R67: 投资支付的现金 | W67: =R67 -> 投资支付的现金
B68: 注资深圳曦风 | D68: 46082 | H68: =-INDEX(情形1!$30:$30,MATCH(cashflow汇总预算2026!$D68,情形1!$3:$3,0))*10000 -> -2020408.2 | K68: =SUM(E68:J68) -> -2020408.2 | M68: =4000/4900*H68/(900/4900) -> -8979591.8 | N68: =-H68-M68 -> 11000000 | T68: 投资支付的现金 | W68: 投资支付的现金
B69: 注资深圳新融 | D69: 46082 | G69: =-INDEX(情形1!$28:$28,MATCH(cashflow汇总预算2026!$D69,情形1!$3:$3))*10000 -> -2375000 | K69: =SUM(E69:J69) -> -2375000 | N69: =G69/1250*3650 -> -6935000 | O69: =-G69-N69+1000000 -> 10310000 | Q69: 投资支付的现金 | W69: 投资支付的现金
B70: 注资JV基金 | D70: 46082 | K70: =SUM(E70:J70) -> 0 | O70: =-INDEX(情形1!$32:$32,MATCH(cashflow汇总预算2026!$D70,情形1!$3:$3,0))*10000 -> -5000000
B71: 内部调拨 | D71: 46082 | E71: =-F71 -> -557979.18 | F71: =-F72 -> 557979.18 | G71: 210000 | K71: =SUM(E71:J71) -> 210000 | M71: =-M61 -> 400000 | O71: =-G71 -> -210000 | Q71: =IF(E71>0,"收到的其他与筹资活动有关的现金","支付的其他与筹资活动有关的现金") -> 支付的其他与筹资活动有关的现金 | R71: =IF(F71>0,"收到的其他与筹资活动有关的现金","支付的其他与筹资活动有关的现金") -> 收到的其他与筹资活动有关的现金 | S71: =IF(G71>0,"收到的其他与筹资活动有关的现金","支付的其他与筹资活动有关的现金") -> 收到的其他与筹资活动有关的现金 | T71: =IF(H71>0,"收到的其他与筹资活动有关的现金","支付的其他与筹资活动有关的现金") -> 支付的其他与筹资活动有关的现金 | U71: =IF(I71>0,"收到的其他与筹资活动有关的现金","支付的其他与筹资活动有关的现金") -> 支付的其他与筹资活动有关的现金 | V71: =IF(J71>0,"收到的其他与筹资活动有关的现金","支付的其他与筹资活动有关的现金") -> 支付的其他与筹资活动有关的现金
B72: 费用支出 | D72: 46082 | E72: =INDEX('CF-ACPLHK'!$E$29:$Q$29,MATCH(cashflow汇总预算2026!$D72,'CF-ACPLHK'!$E$4:$Q$4,0))+INDEX('CF-ACPLHK'!$E$38:$Q$38,MATCH($D72,'CF-ACPLHK'!$E$4:$Q$4,0)) -> -599170.54 | F72: =INDEX('CF-ACPL'!$E$29:$Q$29,MATCH($D72,'CF-ACPL'!$E$4:$Q$4,0))+INDEX('CF-ACPL'!$E$38:$Q$38,MATCH($D72,'CF-ACPL'!$E$4:$Q$4)) -> -557979.18 | G72: =INDEX('CF-ACPLSZ'!$E$29:$Q$29,MATCH($D72,'CF-ACPLSZ'!$E$4:$Q$4,0))+INDEX('CF-ACPLSZ'!$E$38:$Q$38,MATCH($D72,'CF-ACPLSZ'!$E$4:$Q$4)) -> -554432.85 | H72: =INDEX('CF-ACPSZL'!$E$29:$Q$29,MATCH(cashflow汇总预算2026!$D72,'CF-ACPSZL'!$E$4:$Q$4,0))+INDEX('CF-ACPSZL'!$E$38:$Q$38,MATCH($D72,'CF-ACPSZL'!$E$4:$Q$4,0)) -> -297382.28 | I72: =INDEX('CF-ACPLGZ'!$E$29:$Q$29,MATCH(cashflow汇总预算2026!$D72,'CF-ACPLGZ'!$E$4:$Q$4,0))+INDEX('CF-ACPLGZ'!$E$38:$Q$38,MATCH($D72,'CF-ACPLGZ'!$E$4:$Q$4,0)) -> -475 | J72: =INDEX('CF-ACPLYixing'!$E$29:$Q$29,MATCH($D72,'CF-ACPLYixing'!$E$4:$Q$4,0))+INDEX('CF-ACPLYixing'!$E$38:$Q$38,MATCH($D72,'CF-ACPLYixing'!$E$4:$Q$4,0)) -> -83.333333 | K72: =SUM(E72:J72) -> -2009523.2
B73: 现金余额 | D73: 46112 | E73: =SUM(E66:E72) -> 3166030.8 | F73: =SUM(F66:F72) -> 66044.057 | G73: =SUM(G66:G72) -> 4695116.3 | H73: =SUM(H66:H72) -> 7730931.8 | I73: =SUM(I66:I72) -> 175026.4 | J73: =SUM(J66:J72) -> 67896.213 | K73: =SUM(K66:K72) -> 15901046 | M73: =SUM(M66:M72) -> 1420408.2 | N73: =SUM(N66:N72) -> 4065000 | O73: =SUM(O66:O72) -> 5110000
B74: 旭智富能股权转让款 | D74: 46113 | J74: 43500000 | K74: =SUM(E74:J74) -> 43500000 | V74: 收回投资所收到的现金 | W74: 收回投资所收到的现金
B75: 归还IDG借款 | D75: 46113 | J75: =J54*(1+4%*3/12) -> -15150000 | K75: =SUM(E75:J75) -> -15150000 | M75: 0 | R75: 偿还债务所支付的现金 | V75: 偿还债务所支付的现金 | W75: 偿还债务所支付的现金
B76: 曦和基金退伙 | D76: 46113 | J76: =-19650000-250000 -> -19900000 | K76: =SUM(E76:J76) -> -19900000 | V76: 偿还债务所支付的现金 | W76: 偿还债务所支付的现金
B77: 现金分配 | D77: 46113 | G77: =-J77*10% -> 845000 | I77: =-J77*0.9 -> 7605000 | J77: =-SUM(J74:J76) -> -8450000 | K77: =SUM(E77:J77) -> 0 | Q77: NA | S77: 收回投资所收到的现金 | U77: 收回投资所收到的现金 | V77: 支付的其他与筹资活动有关的现金
B78: 内部调拨 | D78: 46113 | G78: =-I78 -> 3000000 | I78: -3000000 | K78: =SUM(E78:J78) -> 0 | M78: =-M55 -> 0 | Q78: =IF(E78>0,"收到的其他与筹资活动有关的现金","支付的其他与筹资活动有关的现金") -> 支付的其他与筹资活动有关的现金 | R78: =IF(F78>0,"收到的其他与筹资活动有关的现金","支付的其他与筹资活动有关的现金") -> 支付的其他与筹资活动有关的现金 | S78: =IF(G78>0,"收到的其他与筹资活动有关的现金","支付的其他与筹资活动有关的现金") -> 收到的其他与筹资活动有关的现金 | T78: =IF(H78>0,"收到的其他与筹资活动有关的现金","支付的其他与筹资活动有关的现金") -> 支付的其他与筹资活动有关的现金 | U78: =IF(I78>0,"收到的其他与筹资活动有关的现金","支付的其他与筹资活动有关的现金") -> 支付的其他与筹资活动有关的现金 | V78: =IF(J78>0,"收到的其他与筹资活动有关的现金","支付的其他与筹资活动有关的现金") -> 支付的其他与筹资活动有关的现金
B79: 减资款出境 | D79: 46113 | E79: =-I79 -> 4505000 | I79: =-SUM(I77:I78)+100000 -> -4505000 | K79: =SUM(E79:J79) -> 0 | Q79: 收回投资所收到的现金 | U79: 支付的其他与筹资活动有关的现金
B80: 注资Albamen New Energy | D80: 46113 | F80: =-INDEX(情形1!$26:$26,MATCH(cashflow汇总预算2026!$D80,情形1!$3:$3,0))*10000 -> 0 | K80: =SUM(E80:J80) -> 0 | M80: =-F80/75% -> 0 | R80: 投资支付的现金 | W80: =R80 -> 投资支付的现金
B81: 注资深圳曦风 | D81: 46113 | H81: =-INDEX(情形1!$30:$30,MATCH(cashflow汇总预算2026!$D81,情形1!$3:$3,0))*10000 -> 0 | K81: =SUM(E81:J81) -> 0 | M81: =-M80 -> 0 | N81: =-H81-M81 -> 0 | T81: 投资支付的现金 | W81: 投资支付的现金
B82: 注资深圳新融 | D82: 46113 | G82: =-INDEX(情形1!$28:$28,MATCH(cashflow汇总预算2026!$D82,情形1!$3:$3))*10000 -> -1275510.2 | K82: =SUM(E82:J82) -> -1275510.2 | N82: =G82/1250*3650 -> -3724489.8 | O82: =-G82-N82 -> 5000000 | S82: 投资支付的现金 | W82: 投资支付的现金
B83: 注资JV基金 | D83: 46113 | K83: =SUM(E83:J83) -> 0 | O83: =-INDEX(情形1!$32:$32,MATCH(cashflow汇总预算2026!D83,情形1!$3:$3,0))*10000 -> -10000000
B84: 内部调拨 | D84: 46113 | E84: =-F84 -> -1353639.2 | F84: =-F85 -> 1353639.2 | K84: =SUM(E84:J84) -> 0 | M84: =-M74 -> 0 | Q84: =IF(E84>0,"收到的其他与筹资活动有关的现金","支付的其他与筹资活动有关的现金") -> 支付的其他与筹资活动有关的现金 | R84: =IF(F84>0,"收到的其他与筹资活动有关的现金","支付的其他与筹资活动有关的现金") -> 收到的其他与筹资活动有关的现金 | S84: =IF(G84>0,"收到的其他与筹资活动有关的现金","支付的其他与筹资活动有关的现金") -> 支付的其他与筹资活动有关的现金 | T84: =IF(H84>0,"收到的其他与筹资活动有关的现金","支付的其他与筹资活动有关的现金") -> 支付的其他与筹资活动有关的现金 | U84: =IF(I84>0,"收到的其他与筹资活动有关的现金","支付的其他与筹资活动有关的现金") -> 支付的其他与筹资活动有关的现金 | V84: =IF(J84>0,"收到的其他与筹资活动有关的现金","支付的其他与筹资活动有关的现金") -> 支付的其他与筹资活动有关的现金
B85: 费用支出 | D85: 46113 | E85: =INDEX('CF-ACPLHK'!$E$29:$Q$29,MATCH(cashflow汇总预算2026!$D85,'CF-ACPLHK'!$E$4:$Q$4,0))+INDEX('CF-ACPLHK'!$E$38:$Q$38,MATCH($D85,'CF-ACPLHK'!$E$4:$Q$4,0)) -> -1049679 | F85: =INDEX('CF-ACPL'!$E$29:$Q$29,MATCH($D85,'CF-ACPL'!$E$4:$Q$4,0))+INDEX('CF-ACPL'!$E$38:$Q$38,MATCH($D85,'CF-ACPL'!$E$4:$Q$4)) -> -1353639.2 | G85: =INDEX('CF-ACPLSZ'!$E$29:$Q$29,MATCH($D85,'CF-ACPLSZ'!$E$4:$Q$4,0))+INDEX('CF-ACPLSZ'!$E$38:$Q$38,MATCH($D85,'CF-ACPLSZ'!$E$4:$Q$4)) -> -810101.39 | H85: =INDEX('CF-ACPSZL'!$E$29:$Q$29,MATCH(cashflow汇总预算2026!$D85,'CF-ACPSZL'!$E$4:$Q$4,0))+INDEX('CF-ACPSZL'!$E$38:$Q$38,MATCH($D85,'CF-ACPSZL'!$E$4:$Q$4,0)) -> -679787.24 | I85: =INDEX('CF-ACPLGZ'!$E$29:$Q$29,MATCH(cashflow汇总预算2026!$D85,'CF-ACPLGZ'!$E$4:$Q$4,0))+INDEX('CF-ACPLGZ'!$E$38:$Q$38,MATCH($D85,'CF-ACPLGZ'!$E$4:$Q$4,0)) -> -475 | J85: =INDEX('CF-ACPLYixing'!$E$29:$Q$29,MATCH($D85,'CF-ACPLYixing'!$E$4:$Q$4,0))+INDEX('CF-ACPLYixing'!$E$38:$Q$38,MATCH($D85,'CF-ACPLYixing'!$E$4:$Q$4,0)) -> -83.333333 | K85: =SUM(E85:J85) -> -3893765.2
B86: 现金余额 | D86: 46142 | E86: =SUM(E73:E85) -> 5267712.6 | F86: =SUM(F73:F85) -> 66044.057 | G86: =SUM(G73:G85) -> 6454504.8 | H86: =SUM(H73:H85) -> 7051144.5 | I86: =SUM(I73:I85) -> 274551.4 | J86: =SUM(J73:J85) -> 67812.88 | K86: =SUM(K73:K85) -> 19181770 | M86: =SUM(M73:M85) -> 1420408.2 | N86: =SUM(N73:N85) -> 340510.2 | O86: =SUM(O73:O85) -> 110000
B87: 注资Albamen New Energy | D87: 46143 | F87: =-INDEX(情形1!$26:$26,MATCH(cashflow汇总预算2026!$D87,情形1!$3:$3,0))*10000 -> 0 | K87: =SUM(E87:J87) -> 0 | M87: =-F87/75% -> 0 | R87: 投资支付的现金 | W87: =R87 -> 投资支付的现金
B88: 注资深圳曦风 | D88: 46143 | H88: =-INDEX(情形1!$30:$30,MATCH(cashflow汇总预算2026!$D88,情形1!$3:$3,0))*10000 -> 0 | K88: =SUM(E88:J88) -> 0 | M88: =H88/900*4000 -> 0 | N88: =-H88-M88 -> 0 | T88: 投资支付的现金 | W88: 投资支付的现金
B89: 注资深圳新融 | D89: 46143 | G89: =-INDEX(情形1!$28:$28,MATCH(cashflow汇总预算2026!$D89,情形1!$3:$3))*10000 -> 0 | K89: =SUM(E89:J89) -> 0 | N89: =G89/1250*3650 -> 0 | O89: =-G89-N89 -> 0 | Q89: 投资支付的现金 | W89: 投资支付的现金
B90: 注资JV基金 | D90: 46143 | K90: =SUM(E90:J90) -> 0 | O90: =-INDEX(情形1!$32:$32,MATCH(cashflow汇总预算2026!D90,情形1!$3:$3,0))*10000 -> 0
B91: 注资特变新平台 | D91: 46143 | G91: -5000000 | K91: =SUM(E91:J91) -> -5000000 | S91: 投资支付的现金 | W91: 投资支付的现金
B92: 内部调拨 | D92: 46143 | E92: =-F92 -> -673968.98 | F92: =-F93 -> 673968.98 | K92: =SUM(E92:J92) -> 0 | Q92: =IF(E92>0,"收到的其他与筹资活动有关的现金","支付的其他与筹资活动有关的现金") -> 支付的其他与筹资活动有关的现金 | R92: =IF(F92>0,"收到的其他与筹资活动有关的现金","支付的其他与筹资活动有关的现金") -> 收到的其他与筹资活动有关的现金 | S92: =IF(G92>0,"收到的其他与筹资活动有关的现金","支付的其他与筹资活动有关的现金") -> 支付的其他与筹资活动有关的现金 | T92: =IF(H92>0,"收到的其他与筹资活动有关的现金","支付的其他与筹资活动有关的现金") -> 支付的其他与筹资活动有关的现金 | U92: =IF(I92>0,"收到的其他与筹资活动有关的现金","支付的其他与筹资活动有关的现金") -> 支付的其他与筹资活动有关的现金 | V92: =IF(J92>0,"收到的其他与筹资活动有关的现金","支付的其他与筹资活动有关的现金") -> 支付的其他与筹资活动有关的现金
B93: 费用支出 | D93: 46143 | E93: =INDEX('CF-ACPLHK'!$E$29:$Q$29,MATCH(cashflow汇总预算2026!$D93,'CF-ACPLHK'!$E$4:$Q$4,0))+INDEX('CF-ACPLHK'!$E$38:$Q$38,MATCH($D93,'CF-ACPLHK'!$E$4:$Q$4,0)) -> -434813.39 | F93: =INDEX('CF-ACPL'!$E$29:$Q$29,MATCH($D93,'CF-ACPL'!$E$4:$Q$4,0))+INDEX('CF-ACPL'!$E$38:$Q$38,MATCH($D93,'CF-ACPL'!$E$4:$Q$4)) -> -673968.98 | G93: =INDEX('CF-ACPLSZ'!$E$29:$Q$29,MATCH($D93,'CF-ACPLSZ'!$E$4:$Q$4,0))+INDEX('CF-ACPLSZ'!$E$38:$Q$38,MATCH($D93,'CF-ACPLSZ'!$E$4:$Q$4)) -> 1946329.3 | H93: =INDEX('CF-ACPSZL'!$E$29:$Q$29,MATCH(cashflow汇总预算2026!$D93,'CF-ACPSZL'!$E$4:$Q$4,0))+INDEX('CF-ACPSZL'!$E$38:$Q$38,MATCH($D93,'CF-ACPSZL'!$E$4:$Q$4,0)) -> -358787.24 | I93: =INDEX('CF-ACPLGZ'!$E$29:$Q$29,MATCH(cashflow汇总预算2026!$D93,'CF-ACPLGZ'!$E$4:$Q$4,0))+INDEX('CF-ACPLGZ'!$E$38:$Q$38,MATCH($D93,'CF-ACPLGZ'!$E$4:$Q$4,0)) -> -475 | J93: =INDEX('CF-ACPLYixing'!$E$29:$Q$29,MATCH($D93,'CF-ACPLYixing'!$E$4:$Q$4,0))+INDEX('CF-ACPLYixing'!$E$38:$Q$38,MATCH($D93,'CF-ACPLYixing'!$E$4:$Q$4,0)) -> -83.333333 | K93: =SUM(E93:J93) -> 478201.31
B94: 现金余额 | D94: 46173 | E94: =SUM(E86:E93) -> 4158930.2 | F94: =SUM(F86:F93) -> 66044.057 | G94: =SUM(G86:G93) -> 3400834 | H94: =SUM(H86:H93) -> 6692357.3 | I94: =SUM(I86:I93) -> 274076.4 | J94: =SUM(J86:J93) -> 67729.547 | K94: =SUM(K86:K93) -> 14659972 | M94: =SUM(M86:M93) -> 1420408.2 | N94: =SUM(N86:N93) -> 340510.2 | O94: =SUM(O86:O93) -> 110000
B95: 注资Albamen New Energy | D95: 46174 | F95: =-INDEX(情形1!$26:$26,MATCH(cashflow汇总预算2026!$D95,情形1!$3:$3,0))*10000 -> 0 | K95: =SUM(E95:J95) -> 0 | M95: =-F95/75% -> 0 | R95: 投资支付的现金 | W95: =R95 -> 投资支付的现金
B96: 注资深圳曦风 | D96: 46174 | H96: =-INDEX(情形1!$30:$30,MATCH(cashflow汇总预算2026!$D96,情形1!$3:$3,0))*10000 -> 0 | K96: =SUM(E96:J96) -> 0 | M96: =H96/900*4000 -> 0 | N96: =-H96-M96 -> 0 | T96: 投资支付的现金 | W96: 投资支付的现金
B97: 注资深圳新融 | D97: 46174 | G97: =-INDEX(情形1!$28:$28,MATCH(cashflow汇总预算2026!$D97,情形1!$3:$3))*10000 -> 0 | K97: =SUM(E97:J97) -> 0 | N97: =G97/1250*3650 -> 0 | O97: =-G97-N97 -> 0 | Q97: 投资支付的现金 | W97: 投资支付的现金
B98: 注资JV基金 | D98: 46174 | K98: =SUM(E98:J98) -> 0 | O98: =-INDEX(情形1!$32:$32,MATCH(cashflow汇总预算2026!D98,情形1!$3:$3,0))*10000 -> 0
B99: 内部调拨 | D99: 46174 | E99: =-F99 -> -524347.86 | F99: =-F100 -> 524347.86 | K99: =SUM(E99:J99) -> 0 | Q99: =IF(E99>0,"收到的其他与筹资活动有关的现金","支付的其他与筹资活动有关的现金") -> 支付的其他与筹资活动有关的现金 | R99: =IF(F99>0,"收到的其他与筹资活动有关的现金","支付的其他与筹资活动有关的现金") -> 收到的其他与筹资活动有关的现金 | S99: =IF(G99>0,"收到的其他与筹资活动有关的现金","支付的其他与筹资活动有关的现金") -> 支付的其他与筹资活动有关的现金 | T99: =IF(H99>0,"收到的其他与筹资活动有关的现金","支付的其他与筹资活动有关的现金") -> 支付的其他与筹资活动有关的现金 | U99: =IF(I99>0,"收到的其他与筹资活动有关的现金","支付的其他与筹资活动有关的现金") -> 支付的其他与筹资活动有关的现金 | V99: =IF(J99>0,"收到的其他与筹资活动有关的现金","支付的其他与筹资活动有关的现金") -> 支付的其他与筹资活动有关的现金
B100: 费用支出 | D100: 46174 | E100: =INDEX('CF-ACPLHK'!$E$29:$Q$29,MATCH(cashflow汇总预算2026!$D100,'CF-ACPLHK'!$E$4:$Q$4,0))+INDEX('CF-ACPLHK'!$E$38:$Q$38,MATCH($D100,'CF-ACPLHK'!$E$4:$Q$4,0)) -> -559980.99 | F100: =INDEX('CF-ACPL'!$E$29:$Q$29,MATCH($D100,'CF-ACPL'!$E$4:$Q$4,0))+INDEX('CF-ACPL'!$E$38:$Q$38,MATCH($D100,'CF-ACPL'!$E$4:$Q$4)) -> -524347.86 | G100: =INDEX('CF-ACPLSZ'!$E$29:$Q$29,MATCH($D100,'CF-ACPLSZ'!$E$4:$Q$4,0))+INDEX('CF-ACPLSZ'!$E$38:$Q$38,MATCH($D100,'CF-ACPLSZ'!$E$4:$Q$4)) -> -838944.1 | H100: =INDEX('CF-ACPSZL'!$E$29:$Q$29,MATCH(cashflow汇总预算2026!$D100,'CF-ACPSZL'!$E$4:$Q$4,0))+INDEX('CF-ACPSZL'!$E$38:$Q$38,MATCH($D100,'CF-ACPSZL'!$E$4:$Q$4,0)) -> -453307.24 | I100: =INDEX('CF-ACPLGZ'!$E$29:$Q$29,MATCH(cashflow汇总预算2026!$D100,'CF-ACPLGZ'!$E$4:$Q$4,0))+INDEX('CF-ACPLGZ'!$E$38:$Q$38,MATCH($D100,'CF-ACPLGZ'!$E$4:$Q$4,0)) -> -52345 | J100: =INDEX('CF-ACPLYixing'!$E$29:$Q$29,MATCH($D100,'CF-ACPLYixing'!$E$4:$Q$4,0))+INDEX('CF-ACPLYixing'!$E$38:$Q$38,MATCH($D100,'CF-ACPLYixing'!$E$4:$Q$4,0)) -> -17083.333 | K100: =SUM(E100:J100) -> -2446008.5
B101: 现金余额 | D101: 46203 | E101: =SUM(E94:E100) -> 3074601.4 | F101: =SUM(F94:F100) -> 66044.057 | G101: =SUM(G94:G100) -> 2561889.9 | H101: =SUM(H94:H100) -> 6239050.1 | I101: =SUM(I94:I100) -> 221731.4 | J101: =SUM(J94:J100) -> 50646.213 | K101: =SUM(K94:K100) -> 12213963 | M101: =SUM(M94:M100) -> 1420408.2 | N101: =SUM(N94:N100) -> 340510.2 | O101: =SUM(O94:O100) -> 110000
B102: 注资Albamen New Energy | D102: 46204 | F102: =-INDEX(情形1!$26:$26,MATCH(cashflow汇总预算2026!$D102,情形1!$3:$3,0))*10000 -> 0 | K102: =SUM(E102:J102) -> 0 | M102: =-F102/75% -> 0 | R102: 投资支付的现金 | W102: =R102 -> 投资支付的现金
B103: 注资深圳曦风 | D103: 46204 | H103: =-INDEX(情形1!$30:$30,MATCH(cashflow汇总预算2026!$D103,情形1!$3:$3,0))*10000 -> 0 | K103: =SUM(E103:J103) -> 0 | M103: =H103/900*4000 -> 0 | N103: =-H103-M103 -> 0 | T103: 投资支付的现金 | W103: 投资支付的现金
...

Sheet cashflow汇总预算 2027
B1: 0.05 | E1: ACPLHK | F1: ACPL | G1: ACPLSZ | H1: ACPLSZL | I1: ACPLGZ | J1: Yixing | K1: Total | M1: Albamen New Energy | N1: 深圳曦风 | O1: 深圳新融 | Q1: ACPLHK | R1: ACPL | S1: ACPLSZ | T1: ACPLSZL | U1: ACPLGZ | V1: Yixing | W1: Total
E2: RMB | F2: RMB | G2: RMB | H2: RMB | I2: RMB | J2: RMB | K2: RMB
B3: Cash balance | D3: 45866 | E3: =2765593+809735*0.91+46072*4.71 -> 3719451 | F3: =50223*0.91 -> 45702.93 | G3: 1757806 | H3: 5744218.3 | I3: 22134.7 | K3: =SUM(E3:I3) -> 11289313
B4: Transfer | E4: =-F4 -> -697963.14 | F4: =-F5 -> 697963.14 | K4: =SUM(E4:I4) -> 0
B5: Jul 2025 expenses | E5: -650484 | F5: -697963.14 | G5: -652247 | H5: -384285.96 | I5: -2321.86 | K5: =SUM(E5:I5) -> -2387302 | M5: +657k: ACPLSZ: 120k 鉴衡服务费; 普华22.5k咨询费；63k Q3深圳租金 ACPLHK: 82K IT服务; 62K 审计费； ACPL: 218k HK SPV费用; 90K 审计费
B6: Estimated Cash balance | D6: 45869 | E6: =SUM(E3:E5) -> 2371003.8 | F6: =SUM(F3:F5) -> 45702.93 | G6: =SUM(G3:G5) -> 1105559 | H6: =SUM(H3:H5) -> 5359932.3 | I6: =SUM(I3:I5) -> 19812.84 | K6: =SUM(K3:K5) -> 8902010.9
B8: Cash balance | D8: 45869 | E8: =2653612*0.91472 -> 2427312 | F8: =52344*0.91472 -> 47880.104 | G8: 1231689 | H8: 5444989 | I8: 49812.84 | K8: =SUM(E8:I8) -> 9201682.9
B9: Transfer | E9: =-F9 -> -360000 | F9: 360000 | K9: =SUM(E9:I9) -> 0
B10: injection | E10: =3600000*0.9 -> 3240000 | G10: =3600000*0.1 -> 360000 | K10: =SUM(E10:I10) -> 3600000
B11: Aug 2025 expenses | E11: =-香港!C213 -> -530274.16 | F11: =-香港!D213 -> -363985.38 | G11: =-'202601-202603（Forecast）'!#REF! -> #REF! | H11: =-'202601-202603（Forecast）'!#REF! -> #REF! | I11: =-'202601-202603（Forecast）'!#REF! -> #REF! | K11: =SUM(E11:I11) -> #REF! | M11: ACPLSZ: 普华22.5k咨询费 ACPLHK: 145K IT服务(license + cloud storage)
B12: Cash balance | D12: 45900 | E12: =SUM(E8:E11) -> 4777037.8 | F12: =SUM(F8:F11) -> 43894.721 | G12: =SUM(G8:G11) -> #REF! | H12: =SUM(H8:H11) -> #REF! | I12: =SUM(I8:I11) -> #REF! | K12: =SUM(K8:K11) -> #REF! | M12: *** ACPLHK will breach the liquid cap requirement after settlement of Aug expenses without capital injection
B14: Cash balance | D14: 45900 | E14: 4794239 | F14: 82455 | G14: 1111289 | H14: 5068590.2 | I14: 31863.6 | K14: =SUM(E14:I14) -> 11088437
B15: Transfer | E15: =-F15 -> -617625 | F15: =675000*0.915 -> 617625 | K15: =SUM(E15:I15) -> 0
B16: Sept 2025 expenses | E16: =-香港!C236 -> -499864.88 | F16: =-香港!D236+180000*0.915 -> -502745.06 | G16: =-'202601-202603（Forecast）'!#REF! -> #REF! | H16: =-'202601-202603（Forecast）'!O52 -> -766650.99 | I16: 0 | K16: =SUM(E16:I16) -> #REF!
B17: Cash balance | D17: 45930 | E17: =SUM(E14:E16) -> 3676749.1 | F17: =SUM(F14:F16) -> 197334.94 | G17: =SUM(G14:G16) -> #REF! | H17: =SUM(H14:H16) -> 4301939.2 | I17: =SUM(I14:I16) -> 31863.6 | K17: =SUM(K14:K16) -> #REF!
B18: Transfer | E18: =-F18 -> -502745.06 | F18: =-F20 -> 502745.06 | K18: =SUM(E18:I18) -> 0
B19: injection
B20: October 2025 expenses | E20: -520253 | F20: =F16 -> -502745.06 | G20: =-'202601-202603（Forecast）'!I52 -> -789872.76 | H20: =-'202601-202603（Forecast）'!P52 -> -344650.99 | I20: 0 | K20: =SUM(E20:I20) -> -2157521.8
B22: Cash balance | D22: 45961 | E22: =3251528*0.92 -> 2991405.8 | F22: =65292*0.92 -> 60068.64 | G22: =SUM('202601-202603（Forecast）'!I14,'202601-202603（Forecast）'!L14) -> 561081.68 | H22: ='202601-202603（Forecast）'!O14 -> 2694352.1 | I22: ='202601-202603（Forecast）'!F14 -> 86665.41 | K22: =SUM(E22:J22) -> 6393573.6
B23: Transfer | E23: =香港!C274*0.92 -> -368000 | F23: =-E23 -> 368000 | G23: =-H23 -> 450000 | H23: -450000 | I23: =-'202601-202603（Forecast）'!F52 -> -9982000 | K23: =SUM(E23:J23) -> -9982000
B24: November 2025 expenses | E24: =-香港!C272*0.92 -> -493674.76 | F24: =-香港!D272*0.92 -> -394737.96 | G24: -450000 | H24: -400000 | I24: 0 | K24: =SUM(E24:J24) -> -1738412.7
B25: Cash balance | D25: 45991 | E25: =SUM(E22:E24) -> 2129731 | F25: =SUM(F22:F24) -> 33330.68 | G25: =SUM(G22:G24) -> 561081.68 | H25: =SUM(H22:H24) -> 1844352.1 | I25: =SUM(I22:I24) -> -9895334.6 | K25: =SUM(K22:K24) -> -5326839.2
P26: Dec expense payments | R26: =-SUM(K35:K35) -> 1936677.9
B27: 实际现金余额 | D27: 45991 | E27: =2341169 -> 2341169 | F27: 46479 | G27: =104222.77+53825.34+17880.93 -> 175929.04 | H27: 3460729 | I27: 31951 | J27: 57445 | K27: =SUM(E27:J27) -> 6113702
B28: 利息收入 | E28: 3.34 | F28: 0.06 | G28: =5.68+3.33+2.26 -> 11.27 | H28: =3329.24+247.83+0.02 -> 3577.09 | I28: =41018+0.07+0.21+0.17+7.85 -> 41026.3 | J28: 7.26 | K28: =SUM(E28:J28) -> 44625.32
B29: 注资深圳曦和 | H29: -400000 | K29: =SUM(E29:J29) -> -400000 | P29: Dec non-routine items:
B30: IDG借款 | F30: =2000000*0.9 -> 1800000 | K30: =SUM(E30:J30) -> 1800000 | P30: IT cloud storage for 2025 | R30: =-香港!C286*0.92 -> -138000
B31: 现金分配 | G31: =-J31*10% -> 0 | I31: =-J31*0.9 -> 0 | K31: =SUM(E31:J31) -> 0 | P31: Huw 7-12 2025 service fee | R31: =-香港!C293*0.92 -> -276000
B32: 内部调拨 | K32: =SUM(E32:J32) -> 0 | P32: Cayman entity expenses | R32: =-SUM(香港!I283:I284)*7.1-香港!I293*7.1 -> -269912.25
B33: 减资款出境 | E33: =-I33 -> 0 | I33: =-SUM(I30:I32) -> 0 | K33: =SUM(E33:J33) -> 0 | P33: IDG Q1 service fee (Michael) | R33: =-'202601-202603（Forecast）'!I45 -> 0
B34: 内部调拨 | E34: =-F34 -> 647834.4 | F34: =-(800000-80000)*0.89977 -> -647834.4 | G34: 345000 | H34: -280000 | I34: -65000 | K34: =SUM(E34:J34) -> 0 | R34: =SUM(R30:R33) -> -683912.25
B35: 费用支出 | E35: =-395768.68 -> -395768.68 | F35: =-103720*0.9-637830.25 -> -731178.25 | G35: =-329240.35-105997.92 -> -435238.27 | H35: -374466.81 | I35: -0.9 | J35: -25 | K35: =SUM(E35:J35) -> -1936677.9 | P35: Dec routine expense payments | R35: =R26+R34 -> 1252765.7
B36: 现金余额 | D36: 46022 | E36: =SUM(E27:E35) -> 2593238.1 | F36: =SUM(F27:F35) -> 467466.41 | G36: =SUM(G27:G35) -> 85702.04 | H36: =SUM(H27:H35) -> 2409839.3 | I36: =SUM(I27:I35) -> 7976.4 | J36: =SUM(J27:J35) -> 57427.26 | K36: =SUM(K27:K35) -> 5621649.5
B37: 现金余额 | D37: 46387 | E37: =cashflow汇总预算2026!E146 -> 2520994.5 | F37: =cashflow汇总预算2026!F146 -> 6860650.6 | G37: =cashflow汇总预算2026!G146 -> 2783341.9 | H37: =cashflow汇总预算2026!H146 -> 930638.48 | I37: =cashflow汇总预算2026!I146 -> 168881.4 | J37: =cashflow汇总预算2026!J146 -> 47146.213 | K37: =cashflow汇总预算2026!K146 -> 13311653 | M37: =cashflow汇总预算2026!M146 -> 0 | N37: =cashflow汇总预算2026!N146 -> 133287.51 | O37: =cashflow汇总预算2026!O146 -> 266849.96
B38: 注资Albamen New Energy | D38: 46388 | F38: =-INDEX(情形1!$26:$26,MATCH($D38,情形1!$3:$3))*10000 -> -114668.91 | K38: =SUM(E38:J38) -> -114668.91 | M38: =-F38/75% -> 152891.88 | R38: 投资支付的现金 | W38: =R38 -> 投资支付的现金
B39: 注资深圳曦风 | D39: 46388 | H39: =-INDEX(情形1!$30:$30,MATCH($D39,情形1!$3:$3))*10000 -> -34400.672 | K39: =SUM(E39:J39) -> -34400.672 | M39: =H39/900*4000 -> -152891.88 | N39: =-H39-M39 -> 187292.55 | T39: 投资支付的现金 | W39: 投资支付的现金
B40: 注资深圳新融 | D40: 46388 | G40: =-INDEX(情形1!$28:$28,MATCH($D40,情形1!$3:$3))*10000 -> -63704.949 | K40: =SUM(E40:J40) -> -63704.949 | N40: =G40/1250*3650 -> -186018.45 | O40: =-G40-N40 -> 249723.4 | Q40: 投资支付的现金 | W40: 投资支付的现金
B41: 注资JV基金 | D41: 46388 | K41: =SUM(E41:J41) -> 0 | O41: =-INDEX(情形1!$32:$32,MATCH($D41,情形1!$3:$3))*10000 -> -254819.8
B42: 内部调拨 | D42: 46388 | E42: =-F42 -> -554355.86 | F42: =-F43 -> 554355.86 | G42: 1500000 | H42: =-G42 -> -1500000 | K42: =SUM(E42:J42) -> 0 | Q42: =IF(E42>0,"收到的其他与筹资活动有关的现金","支付的其他与筹资活动有关的现金") -> 支付的其他与筹资活动有关的现金 | R42: =IF(F42>0,"收到的其他与筹资活动有关的现金","支付的其他与筹资活动有关的现金") -> 收到的其他与筹资活动有关的现金 | S42: =IF(G42>0,"收到的其他与筹资活动有关的现金","支付的其他与筹资活动有关的现金") -> 收到的其他与筹资活动有关的现金 | T42: =IF(H42>0,"收到的其他与筹资活动有关的现金","支付的其他与筹资活动有关的现金") -> 支付的其他与筹资活动有关的现金 | U42: =IF(I42>0,"收到的其他与筹资活动有关的现金","支付的其他与筹资活动有关的现金") -> 支付的其他与筹资活动有关的现金 | V42: =IF(J42>0,"收到的其他与筹资活动有关的现金","支付的其他与筹资活动有关的现金") -> 支付的其他与筹资活动有关的现金
B43: 费用支出 | D43: 46388 | E43: =cashflow汇总预算2026!E47*(1+'cashflow汇总预算 2027'!$B$1) -> -752396.29 | F43: =cashflow汇总预算2026!F47*(1+'cashflow汇总预算 2027'!$B$1) -> -554355.86 | G43: =cashflow汇总预算2026!G47*(1+'cashflow汇总预算 2027'!$B$1) -> -762658.98 | H43: =cashflow汇总预算2026!H47*(1+'cashflow汇总预算 2027'!$B$1) -> -445341.52 | I43: =cashflow汇总预算2026!I47*(1+'cashflow汇总预算 2027'!$B$1) -> -2100 | J43: =cashflow汇总预算2026!J47*(1+'cashflow汇总预算 2027'!$B$1) -> 0 | K43: =SUM(E43:J43) -> -2516852.6
B44: 现金余额 | D44: 46388 | E44: =SUM(E37:E43) -> 1214242.4 | F44: =SUM(F37:F43) -> 6745981.7 | G44: =SUM(G37:G43) -> 3456977.9 | H44: =SUM(H37:H43) -> -1049103.7 | I44: =SUM(I37:I43) -> 166781.4 | J44: =SUM(J37:J43) -> 47146.213 | K44: =SUM(K37:K43) -> 10582026 | M44: =SUM(M37:M43) -> -1.542503e-09 | N44: =SUM(N37:N43) -> 134561.61 | O44: =SUM(O37:O43) -> 261753.57
B45: 注资Albamen New Energy | D45: 46419 | F45: =-INDEX(情形1!$26:$26,MATCH($D45,情形1!$3:$3))*10000 -> 0 | K45: =SUM(E45:J45) -> 0 | M45: =-F45/75% -> 0 | R45: 投资支付的现金 | W45: =R45 -> 投资支付的现金
B46: 注资深圳曦风 | D46: 46419 | H46: =-INDEX(情形1!$30:$30,MATCH($D46,情形1!$3:$3))*10000 -> 0 | K46: =SUM(E46:J46) -> 0 | M46: =H46/900*4000 -> 0 | N46: =-H46-M46 -> 0 | T46: 投资支付的现金 | W46: 投资支付的现金
B47: 注资深圳新融 | D47: 46419 | G47: =-INDEX(情形1!$28:$28,MATCH($D47,情形1!$3:$3))*10000 -> 0 | K47: =SUM(E47:J47) -> 0 | N47: =G47/1250*3650 -> 0 | O47: =-G47-N47 -> 0 | Q47: 投资支付的现金 | W47: 投资支付的现金
B48: 注资JV基金 | D48: 46419 | K48: =SUM(E48:J48) -> 0 | O48: =-INDEX(情形1!$32:$32,MATCH($D48,情形1!$3:$3))*10000 -> 0
B49: 内部调拨 | D49: 46419 | E49: =-F49 -> -467753.14 | F49: =-F50 -> 467753.14 | G49: 1500000 | H49: =-G49 -> -1500000 | K49: =SUM(E49:J49) -> 0 | Q49: =IF(E49>0,"收到的其他与筹资活动有关的现金","支付的其他与筹资活动有关的现金") -> 支付的其他与筹资活动有关的现金 | R49: =IF(F49>0,"收到的其他与筹资活动有关的现金","支付的其他与筹资活动有关的现金") -> 收到的其他与筹资活动有关的现金 | S49: =IF(G49>0,"收到的其他与筹资活动有关的现金","支付的其他与筹资活动有关的现金") -> 收到的其他与筹资活动有关的现金 | T49: =IF(H49>0,"收到的其他与筹资活动有关的现金","支付的其他与筹资活动有关的现金") -> 支付的其他与筹资活动有关的现金 | U49: =IF(I49>0,"收到的其他与筹资活动有关的现金","支付的其他与筹资活动有关的现金") -> 支付的其他与筹资活动有关的现金 | V49: =IF(J49>0,"收到的其他与筹资活动有关的现金","支付的其他与筹资活动有关的现金") -> 支付的其他与筹资活动有关的现金
B50: 费用支出 | D50: 46419 | E50: =cashflow汇总预算2026!E65*(1+'cashflow汇总预算 2027'!$B$1) -> -481719.57 | F50: =cashflow汇总预算2026!F65*(1+'cashflow汇总预算 2027'!$B$1) -> -467753.14 | G50: =cashflow汇总预算2026!G65*(1+'cashflow汇总预算 2027'!$B$1) -> -708551.51 | H50: =cashflow汇总预算2026!H65*(1+'cashflow汇总预算 2027'!$B$1) -> -332831.39 | I50: =cashflow汇总预算2026!I65*(1+'cashflow汇总预算 2027'!$B$1) -> -498.75 | J50: =cashflow汇总预算2026!J65*(1+'cashflow汇总预算 2027'!$B$1) -> -87.5 | K50: =SUM(E50:J50) -> -1991441.9
B51: 现金余额 | D51: 46419 | E51: =SUM(E44:E50) -> 264769.64 | F51: =SUM(F44:F50) -> 6745981.7 | G51: =SUM(G44:G50) -> 4248426.4 | H51: =SUM(H44:H50) -> -2881935.1 | I51: =SUM(I44:I50) -> 166282.65 | J51: =SUM(J44:J50) -> 47058.713 | K51: =SUM(K44:K50) -> 8590584.1 | M51: =SUM(M44:M50) -> -1.542503e-09 | N51: =SUM(N44:N50) -> 134561.61 | O51: =SUM(O44:O50) -> 261753.57
B52: 注资Albamen New Energy | D52: 46447 | F52: =-INDEX(情形1!$26:$26,MATCH($D52,情形1!$3:$3))*10000 -> 0 | K52: =SUM(E52:J52) -> 0 | M52: =-F52/75% -> 0 | R52: 投资支付的现金 | W52: =R52 -> 投资支付的现金
B53: 注资深圳曦风 | D53: 46447 | H53: =-INDEX(情形1!$30:$30,MATCH($D53,情形1!$3:$3))*10000 -> 0 | K53: =SUM(E53:J53) -> 0 | M53: =H53/900*4000 -> 0 | N53: =-H53-M53 -> 0 | T53: 投资支付的现金 | W53: 投资支付的现金
B54: 注资深圳新融 | D54: 46447 | G54: =-INDEX(情形1!$28:$28,MATCH($D54,情形1!$3:$3))*10000 -> 0 | K54: =SUM(E54:J54) -> 0 | N54: =G54/1250*3650 -> 0 | O54: =-G54-N54 -> 0 | Q54: 投资支付的现金 | W54: 投资支付的现金
B55: 注资JV基金 | D55: 46447 | K55: =SUM(E55:J55) -> 0 | O55: =-INDEX(情形1!$32:$32,MATCH($D55,情形1!$3:$3))*10000 -> 0
B56: 内部调拨 | D56: 46447 | E56: =-F56 -> -585878.14 | F56: =-F57 -> 585878.14 | G56: 1500000 | H56: =-G56 -> -1500000 | K56: =SUM(E56:J56) -> 0 | Q56: =IF(E56>0,"收到的其他与筹资活动有关的现金","支付的其他与筹资活动有关的现金") -> 支付的其他与筹资活动有关的现金 | R56: =IF(F56>0,"收到的其他与筹资活动有关的现金","支付的其他与筹资活动有关的现金") -> 收到的其他与筹资活动有关的现金 | S56: =IF(G56>0,"收到的其他与筹资活动有关的现金","支付的其他与筹资活动有关的现金") -> 收到的其他与筹资活动有关的现金 | T56: =IF(H56>0,"收到的其他与筹资活动有关的现金","支付的其他与筹资活动有关的现金") -> 支付的其他与筹资活动有关的现金 | U56: =IF(I56>0,"收到的其他与筹资活动有关的现金","支付的其他与筹资活动有关的现金") -> 支付的其他与筹资活动有关的现金 | V56: =IF(J56>0,"收到的其他与筹资活动有关的现金","支付的其他与筹资活动有关的现金") -> 支付的其他与筹资活动有关的现金
B57: 费用支出 | D57: 46447 | E57: =cashflow汇总预算2026!E72*(1+'cashflow汇总预算 2027'!$B$1) -> -629129.07 | F57: =cashflow汇总预算2026!F72*(1+'cashflow汇总预算 2027'!$B$1) -> -585878.14 | G57: =cashflow汇总预算2026!G72*(1+'cashflow汇总预算 2027'!$B$1) -> -582154.49 | H57: =cashflow汇总预算2026!H72*(1+'cashflow汇总预算 2027'!$B$1) -> -312251.39 | I57: =cashflow汇总预算2026!I72*(1+'cashflow汇总预算 2027'!$B$1) -> -498.75 | J57: =cashflow汇总预算2026!J72*(1+'cashflow汇总预算 2027'!$B$1) -> -87.5 | K57: =SUM(E57:J57) -> -2109999.3
B58: 现金余额 | D58: 46447 | E58: =SUM(E51:E57) -> -950237.57 | F58: =SUM(F51:F57) -> 6745981.7 | G58: =SUM(G51:G57) -> 5166271.9 | H58: =SUM(H51:H57) -> -4694186.5 | I58: =SUM(I51:I57) -> 165783.9 | J58: =SUM(J51:J57) -> 46971.213 | K58: =SUM(K51:K57) -> 6480584.7 | M58: =SUM(M51:M57) -> -1.542503e-09 | N58: =SUM(N51:N57) -> 134561.61 | O58: =SUM(O51:O57) -> 261753.57
B59: 注资Albamen New Energy | D59: 46478 | F59: =-INDEX(情形1!$26:$26,MATCH($D59,情形1!$3:$3))*10000 -> 0 | K59: =SUM(E59:J59) -> 0 | M59: =-F59/75% -> 0 | R59: 投资支付的现金 | W59: =R59 -> 投资支付的现金
B60: 注资深圳曦风 | D60: 46478 | H60: =-INDEX(情形1!$30:$30,MATCH($D60,情形1!$3:$3))*10000 -> 0 | K60: =SUM(E60:J60) -> 0 | M60: =H60/900*4000 -> 0 | N60: =-H60-M60 -> 0 | T60: 投资支付的现金 | W60: 投资支付的现金
B61: 注资深圳新融 | D61: 46478 | G61: =-INDEX(情形1!$28:$28,MATCH($D61,情形1!$3:$3))*10000 -> 0 | K61: =SUM(E61:J61) -> 0 | N61: =G61/1250*3650 -> 0 | O61: =-G61-N61 -> 0 | Q61: 投资支付的现金 | W61: 投资支付的现金
B62: 注资JV基金 | D62: 46478 | K62: =SUM(E62:J62) -> 0 | O62: =-INDEX(情形1!$32:$32,MATCH($D62,情形1!$3:$3))*10000 -> 0
B63: 内部调拨 | D63: 46478 | E63: =-F63 -> #N/A | F63: =-F64 -> #N/A | G63: 1500000 | H63: =-G63 -> -1500000 | K63: =SUM(E63:J63) -> #N/A | Q63: =IF(E63>0,"收到的其他与筹资活动有关的现金","支付的其他与筹资活动有关的现金") -> #N/A | R63: =IF(F63>0,"收到的其他与筹资活动有关的现金","支付的其他与筹资活动有关的现金") -> #N/A | S63: =IF(G63>0,"收到的其他与筹资活动有关的现金","支付的其他与筹资活动有关的现金") -> 收到的其他与筹资活动有关的现金 | T63: =IF(H63>0,"收到的其他与筹资活动有关的现金","支付的其他与筹资活动有关的现金") -> 支付的其他与筹资活动有关的现金 | U63: =IF(I63>0,"收到的其他与筹资活动有关的现金","支付的其他与筹资活动有关的现金") -> 支付的其他与筹资活动有关的现金 | V63: =IF(J63>0,"收到的其他与筹资活动有关的现金","支付的其他与筹资活动有关的现金") -> 支付的其他与筹资活动有关的现金
B64: 费用支出 | D64: 46478 | E64: =INDEX('CF-ACPLHK'!$E$29:$Q$29,MATCH('cashflow汇总预算 2027'!$D64,'CF-ACPLHK'!$E$4:$Q$4,0))+INDEX('CF-ACPLHK'!$E$38:$Q$38,MATCH($D64,'CF-ACPLHK'!$E$4:$Q$4,0)) -> #N/A | F64: =INDEX('CF-ACPL'!$E$29:$Q$29,MATCH($D64,'CF-ACPL'!$E$4:$Q$4,0))+INDEX('CF-ACPL'!$E$38:$Q$38,MATCH($D64,'CF-ACPL'!$E$4:$Q$4)) -> #N/A | G64: =INDEX('CF-ACPLSZ'!$E$29:$Q$29,MATCH($D64,'CF-ACPLSZ'!$E$4:$Q$4,0))+INDEX('CF-ACPLSZ'!$E$38:$Q$38,MATCH($D64,'CF-ACPLSZ'!$E$4:$Q$4)) -> #N/A | H64: =INDEX('CF-ACPSZL'!$E$29:$Q$29,MATCH('cashflow汇总预算 2027'!$D64,'CF-ACPSZL'!$E$4:$Q$4,0))+INDEX('CF-ACPSZL'!$E$38:$Q$38,MATCH($D64,'CF-ACPSZL'!$E$4:$Q$4,0)) -> #N/A | I64: =INDEX('CF-ACPLGZ'!$E$29:$Q$29,MATCH('cashflow汇总预算 2027'!$D64,'CF-ACPLGZ'!$E$4:$Q$4,0))+INDEX('CF-ACPLGZ'!$E$38:$Q$38,MATCH($D64,'CF-ACPLGZ'!$E$4:$Q$4,0)) -> #N/A | J64: =INDEX('CF-ACPLYixing'!$E$29:$Q$29,MATCH($D64,'CF-ACPLYixing'!$E$4:$Q$4,0))+INDEX('CF-ACPLYixing'!$E$38:$Q$38,MATCH($D64,'CF-ACPLYixing'!$E$4:$Q$4,0)) -> #N/A | K64: =SUM(E64:J64) -> #N/A
B65: 现金余额 | D65: 46478 | E65: =SUM(E58:E64) -> #N/A | F65: =SUM(F58:F64) -> #N/A | G65: =SUM(G58:G64) -> #N/A | H65: =SUM(H58:H64) -> #N/A | I65: =SUM(I58:I64) -> #N/A | J65: =SUM(J58:J64) -> #N/A | K65: =SUM(K58:K64) -> #N/A | M65: =SUM(M58:M64) -> -1.542503e-09 | N65: =SUM(N58:N64) -> 134561.61 | O65: =SUM(O58:O64) -> 261753.57
B66: 注资Albamen New Energy | D66: 46508 | F66: =-INDEX(情形1!$26:$26,MATCH($D66,情形1!$3:$3))*10000 -> 0 | K66: =SUM(E66:J66) -> 0 | M66: =-F66/75% -> 0 | R66: 投资支付的现金 | W66: =R66 -> 投资支付的现金
B67: 注资深圳曦风 | D67: 46508 | H67: =-INDEX(情形1!$30:$30,MATCH($D67,情形1!$3:$3))*10000 -> 0 | K67: =SUM(E67:J67) -> 0 | M67: =H67/900*4000 -> 0 | N67: =-H67-M67 -> 0 | T67: 投资支付的现金 | W67: 投资支付的现金
B68: 注资深圳新融 | D68: 46508 | G68: =-INDEX(情形1!$28:$28,MATCH($D68,情形1!$3:$3))*10000 -> 0 | K68: =SUM(E68:J68) -> 0 | N68: =G68/1250*3650 -> 0 | O68: =-G68-N68 -> 0 | Q68: 投资支付的现金 | W68: 投资支付的现金
B69: 注资JV基金 | D69: 46508 | K69: =SUM(E69:J69) -> 0 | O69: =-INDEX(情形1!$32:$32,MATCH($D69,情形1!$3:$3))*10000 -> 0
B70: 内部调拨 | D70: 46508 | E70: =-F70 -> #N/A | F70: =-F71 -> #N/A | G70: 1500000 | H70: =-G70 -> -1500000 | K70: =SUM(E70:J70) -> #N/A | Q70: =IF(E70>0,"收到的其他与筹资活动有关的现金","支付的其他与筹资活动有关的现金") -> #N/A | R70: =IF(F70>0,"收到的其他与筹资活动有关的现金","支付的其他与筹资活动有关的现金") -> #N/A | S70: =IF(G70>0,"收到的其他与筹资活动有关的现金","支付的其他与筹资活动有关的现金") -> 收到的其他与筹资活动有关的现金 | T70: =IF(H70>0,"收到的其他与筹资活动有关的现金","支付的其他与筹资活动有关的现金") -> 支付的其他与筹资活动有关的现金 | U70: =IF(I70>0,"收到的其他与筹资活动有关的现金","支付的其他与筹资活动有关的现金") -> 支付的其他与筹资活动有关的现金 | V70: =IF(J70>0,"收到的其他与筹资活动有关的现金","支付的其他与筹资活动有关的现金") -> 支付的其他与筹资活动有关的现金
B71: 费用支出 | D71: 46508 | E71: =INDEX('CF-ACPLHK'!$E$29:$Q$29,MATCH('cashflow汇总预算 2027'!$D71,'CF-ACPLHK'!$E$4:$Q$4,0))+INDEX('CF-ACPLHK'!$E$38:$Q$38,MATCH($D71,'CF-ACPLHK'!$E$4:$Q$4,0)) -> #N/A | F71: =INDEX('CF-ACPL'!$E$29:$Q$29,MATCH($D71,'CF-ACPL'!$E$4:$Q$4,0))+INDEX('CF-ACPL'!$E$38:$Q$38,MATCH($D71,'CF-ACPL'!$E$4:$Q$4)) -> #N/A | G71: =INDEX('CF-ACPLSZ'!$E$29:$Q$29,MATCH($D71,'CF-ACPLSZ'!$E$4:$Q$4,0))+INDEX('CF-ACPLSZ'!$E$38:$Q$38,MATCH($D71,'CF-ACPLSZ'!$E$4:$Q$4)) -> #N/A | H71: =INDEX('CF-ACPSZL'!$E$29:$Q$29,MATCH('cashflow汇总预算 2027'!$D71,'CF-ACPSZL'!$E$4:$Q$4,0))+INDEX('CF-ACPSZL'!$E$38:$Q$38,MATCH($D71,'CF-ACPSZL'!$E$4:$Q$4,0)) -> #N/A | I71: =INDEX('CF-ACPLGZ'!$E$29:$Q$29,MATCH('cashflow汇总预算 2027'!$D71,'CF-ACPLGZ'!$E$4:$Q$4,0))+INDEX('CF-ACPLGZ'!$E$38:$Q$38,MATCH($D71,'CF-ACPLGZ'!$E$4:$Q$4,0)) -> #N/A | J71: =INDEX('CF-ACPLYixing'!$E$29:$Q$29,MATCH($D71,'CF-ACPLYixing'!$E$4:$Q$4,0))+INDEX('CF-ACPLYixing'!$E$38:$Q$38,MATCH($D71,'CF-ACPLYixing'!$E$4:$Q$4,0)) -> #N/A | K71: =SUM(E71:J71) -> #N/A
B72: 现金余额 | D72: 46508 | E72: =SUM(E65:E71) -> #N/A | F72: =SUM(F65:F71) -> #N/A | G72: =SUM(G65:G71) -> #N/A | H72: =SUM(H65:H71) -> #N/A | I72: =SUM(I65:I71) -> #N/A | J72: =SUM(J65:J71) -> #N/A | K72: =SUM(K65:K71) -> #N/A | M72: =SUM(M65:M71) -> -1.542503e-09 | N72: =SUM(N65:N71) -> 134561.61 | O72: =SUM(O65:O71) -> 261753.57
B73: 注资Albamen New Energy | D73: 46539 | F73: =-INDEX(情形1!$26:$26,MATCH($D73,情形1!$3:$3))*10000 -> -2259283.9 | K73: =SUM(E73:J73) -> -2259283.9 | M73: =-F73/75% -> 3012378.6 | R73: 投资支付的现金 | W73: =R73 -> 投资支付的现金
B74: 注资深圳曦风 | D74: 46539 | H74: =-INDEX(情形1!$30:$30,MATCH($D74,情形1!$3:$3))*10000 -> -677785.18 | K74: =SUM(E74:J74) -> -677785.18 | M74: =H74/900*4000 -> -3012378.6 | N74: =-H74-M74 -> 3690163.8 | T74: 投资支付的现金 | W74: 投资支付的现金
B75: 注资深圳新融 | D75: 46539 | G75: =-INDEX(情形1!$28:$28,MATCH($D75,情形1!$3:$3))*10000 -> -1255157.7 | K75: =SUM(E75:J75) -> -1255157.7 | N75: =G75/1250*3650 -> -3665060.6 | O75: =-G75-N75 -> 4920218.3 | Q75: 投资支付的现金 | W75: 投资支付的现金
B76: 注资JV基金 | D76: 46539 | K76: =SUM(E76:J76) -> 0 | O76: =-INDEX(情形1!$32:$32,MATCH($D76,情形1!$3:$3))*10000 -> -5020631
B77: 内部调拨 | D77: 46539 | E77: =-F77 -> #N/A | F77: =-F78 -> #N/A | G77: 1500000 | H77: =-G77 -> -1500000 | K77: =SUM(E77:J77) -> #N/A | Q77: =IF(E77>0,"收到的其他与筹资活动有关的现金","支付的其他与筹资活动有关的现金") -> #N/A | R77: =IF(F77>0,"收到的其他与筹资活动有关的现金","支付的其他与筹资活动有关的现金") -> #N/A | S77: =IF(G77>0,"收到的其他与筹资活动有关的现金","支付的其他与筹资活动有关的现金") -> 收到的其他与筹资活动有关的现金 | T77: =IF(H77>0,"收到的其他与筹资活动有关的现金","支付的其他与筹资活动有关的现金") -> 支付的其他与筹资活动有关的现金 | U77: =IF(I77>0,"收到的其他与筹资活动有关的现金","支付的其他与筹资活动有关的现金") -> 支付的其他与筹资活动有关的现金 | V77: =IF(J77>0,"收到的其他与筹资活动有关的现金","支付的其他与筹资活动有关的现金") -> 支付的其他与筹资活动有关的现金
B78: 费用支出 | D78: 46539 | E78: =INDEX('CF-ACPLHK'!$E$29:$Q$29,MATCH('cashflow汇总预算 2027'!$D78,'CF-ACPLHK'!$E$4:$Q$4,0))+INDEX('CF-ACPLHK'!$E$38:$Q$38,MATCH($D78,'CF-ACPLHK'!$E$4:$Q$4,0)) -> #N/A | F78: =INDEX('CF-ACPL'!$E$29:$Q$29,MATCH($D78,'CF-ACPL'!$E$4:$Q$4,0))+INDEX('CF-ACPL'!$E$38:$Q$38,MATCH($D78,'CF-ACPL'!$E$4:$Q$4)) -> #N/A | G78: =INDEX('CF-ACPLSZ'!$E$29:$Q$29,MATCH($D78,'CF-ACPLSZ'!$E$4:$Q$4,0))+INDEX('CF-ACPLSZ'!$E$38:$Q$38,MATCH($D78,'CF-ACPLSZ'!$E$4:$Q$4)) -> #N/A | H78: =INDEX('CF-ACPSZL'!$E$29:$Q$29,MATCH('cashflow汇总预算 2027'!$D78,'CF-ACPSZL'!$E$4:$Q$4,0))+INDEX('CF-ACPSZL'!$E$38:$Q$38,MATCH($D78,'CF-ACPSZL'!$E$4:$Q$4,0)) -> #N/A | I78: =INDEX('CF-ACPLGZ'!$E$29:$Q$29,MATCH('cashflow汇总预算 2027'!$D78,'CF-ACPLGZ'!$E$4:$Q$4,0))+INDEX('CF-ACPLGZ'!$E$38:$Q$38,MATCH($D78,'CF-ACPLGZ'!$E$4:$Q$4,0)) -> #N/A | J78: =INDEX('CF-ACPLYixing'!$E$29:$Q$29,MATCH($D78,'CF-ACPLYixing'!$E$4:$Q$4,0))+INDEX('CF-ACPLYixing'!$E$38:$Q$38,MATCH($D78,'CF-ACPLYixing'!$E$4:$Q$4,0)) -> #N/A | K78: =SUM(E78:J78) -> #N/A
B79: 现金余额 | D79: 46539 | E79: =SUM(E72:E78) -> #N/A | F79: =SUM(F72:F78) -> #N/A | G79: =SUM(G72:G78) -> #N/A | H79: =SUM(H72:H78) -> #N/A | I79: =SUM(I72:I78) -> #N/A | J79: =SUM(J72:J78) -> #N/A | K79: =SUM(K72:K78) -> #N/A | M79: =SUM(M72:M78) -> 0 | N79: =SUM(N72:N78) -> 159664.76 | O79: =SUM(O72:O78) -> 161340.95
B80: 注资Albamen New Energy | D80: 46569 | F80: =-INDEX(情形1!$26:$26,MATCH($D80,情形1!$3:$3))*10000 -> 0 | K80: =SUM(E80:J80) -> 0 | M80: =-F80/75% -> 0 | R80: 投资支付的现金 | W80: =R80 -> 投资支付的现金
B81: 注资深圳曦风 | D81: 46569 | H81: =-INDEX(情形1!$30:$30,MATCH($D81,情形1!$3:$3))*10000 -> 0 | K81: =SUM(E81:J81) -> 0 | M81: =H81/900*4000 -> 0 | N81: =-H81-M81 -> 0 | T81: 投资支付的现金 | W81: 投资支付的现金
B82: 注资深圳新融 | D82: 46569 | G82: =-INDEX(情形1!$28:$28,MATCH($D82,情形1!$3:$3))*10000 -> 0 | K82: =SUM(E82:J82) -> 0 | N82: =G82/1250*3650 -> 0 | O82: =-G82-N82 -> 0 | Q82: 投资支付的现金 | W82: 投资支付的现金
B83: 注资JV基金 | D83: 46569 | K83: =SUM(E83:J83) -> 0 | O83: =-INDEX(情形1!$32:$32,MATCH($D83,情形1!$3:$3))*10000 -> 0
B84: 内部调拨 | D84: 46569 | E84: =-F84 -> #N/A | F84: =-F85 -> #N/A | G84: 1500000 | H84: =-G84 -> -1500000 | K84: =SUM(E84:J84) -> #N/A | Q84: =IF(E84>0,"收到的其他与筹资活动有关的现金","支付的其他与筹资活动有关的现金") -> #N/A | R84: =IF(F84>0,"收到的其他与筹资活动有关的现金","支付的其他与筹资活动有关的现金") -> #N/A | S84: =IF(G84>0,"收到的其他与筹资活动有关的现金","支付的其他与筹资活动有关的现金") -> 收到的其他与筹资活动有关的现金 | T84: =IF(H84>0,"收到的其他与筹资活动有关的现金","支付的其他与筹资活动有关的现金") -> 支付的其他与筹资活动有关的现金 | U84: =IF(I84>0,"收到的其他与筹资活动有关的现金","支付的其他与筹资活动有关的现金") -> 支付的其他与筹资活动有关的现金 | V84: =IF(J84>0,"收到的其他与筹资活动有关的现金","支付的其他与筹资活动有关的现金") -> 支付的其他与筹资活动有关的现金
B85: 费用支出 | D85: 46569 | E85: =INDEX('CF-ACPLHK'!$E$29:$Q$29,MATCH('cashflow汇总预算 2027'!$D85,'CF-ACPLHK'!$E$4:$Q$4,0))+INDEX('CF-ACPLHK'!$E$38:$Q$38,MATCH($D85,'CF-ACPLHK'!$E$4:$Q$4,0)) -> #N/A | F85: =INDEX('CF-ACPL'!$E$29:$Q$29,MATCH($D85,'CF-ACPL'!$E$4:$Q$4,0))+INDEX('CF-ACPL'!$E$38:$Q$38,MATCH($D85,'CF-ACPL'!$E$4:$Q$4)) -> #N/A | G85: =INDEX('CF-ACPLSZ'!$E$29:$Q$29,MATCH($D85,'CF-ACPLSZ'!$E$4:$Q$4,0))+INDEX('CF-ACPLSZ'!$E$38:$Q$38,MATCH($D85,'CF-ACPLSZ'!$E$4:$Q$4)) -> #N/A | H85: =INDEX('CF-ACPSZL'!$E$29:$Q$29,MATCH('cashflow汇总预算 2027'!$D85,'CF-ACPSZL'!$E$4:$Q$4,0))+INDEX('CF-ACPSZL'!$E$38:$Q$38,MATCH($D85,'CF-ACPSZL'!$E$4:$Q$4,0)) -> #N/A | I85: =INDEX('CF-ACPLGZ'!$E$29:$Q$29,MATCH('cashflow汇总预算 2027'!$D85,'CF-ACPLGZ'!$E$4:$Q$4,0))+INDEX('CF-ACPLGZ'!$E$38:$Q$38,MATCH($D85,'CF-ACPLGZ'!$E$4:$Q$4,0)) -> #N/A | J85: =INDEX('CF-ACPLYixing'!$E$29:$Q$29,MATCH($D85,'CF-ACPLYixing'!$E$4:$Q$4,0))+INDEX('CF-ACPLYixing'!$E$38:$Q$38,MATCH($D85,'CF-ACPLYixing'!$E$4:$Q$4,0)) -> #N/A | K85: =SUM(E85:J85) -> #N/A
B86: 现金余额 | D86: 46569 | E86: =SUM(E79:E85) -> #N/A | F86: =SUM(F79:F85) -> #N/A | G86: =SUM(G79:G85) -> #N/A | H86: =SUM(H79:H85) -> #N/A | I86: =SUM(I79:I85) -> #N/A | J86: =SUM(J79:J85) -> #N/A | K86: =SUM(K79:K85) -> #N/A | M86: =SUM(M79:M85) -> 0 | N86: =SUM(N79:N85) -> 159664.76 | O86: =SUM(O79:O85) -> 161340.95
B87: 注资Albamen New Energy | D87: 46600 | F87: =-INDEX(情形1!$26:$26,MATCH($D87,情形1!$3:$3))*10000 -> 0 | K87: =SUM(E87:J87) -> 0 | M87: =-F87/75% -> 0 | R87: 投资支付的现金 | W87: =R87 -> 投资支付的现金
B88: 注资深圳曦风 | D88: 46600 | H88: =-INDEX(情形1!$30:$30,MATCH($D88,情形1!$3:$3))*10000 -> 0 | K88: =SUM(E88:J88) -> 0 | M88: =H88/900*4000 -> 0 | N88: =-H88-M88 -> 0 | T88: 投资支付的现金 | W88: 投资支付的现金
B89: 注资深圳新融 | D89: 46600 | G89: =-INDEX(情形1!$28:$28,MATCH($D89,情形1!$3:$3))*10000 -> 0 | K89: =SUM(E89:J89) -> 0 | N89: =G89/1250*3650 -> 0 | O89: =-G89-N89 -> 0 | Q89: 投资支付的现金 | W89: 投资支付的现金
B90: 注资JV基金 | D90: 46600 | K90: =SUM(E90:J90) -> 0 | O90: =-INDEX(情形1!$32:$32,MATCH($D90,情形1!$3:$3))*10000 -> 0
B91: 内部调拨 | D91: 46600 | E91: =-F91 -> #N/A | F91: =-F92 -> #N/A | G91: 1500000 | H91: =-G91 -> -1500000 | K91: =SUM(E91:J91) -> #N/A | Q91: =IF(E91>0,"收到的其他与筹资活动有关的现金","支付的其他与筹资活动有关的现金") -> #N/A | R91: =IF(F91>0,"收到的其他与筹资活动有关的现金","支付的其他与筹资活动有关的现金") -> #N/A | S91: =IF(G91>0,"收到的其他与筹资活动有关的现金","支付的其他与筹资活动有关的现金") -> 收到的其他与筹资活动有关的现金 | T91: =IF(H91>0,"收到的其他与筹资活动有关的现金","支付的其他与筹资活动有关的现金") -> 支付的其他与筹资活动有关的现金 | U91: =IF(I91>0,"收到的其他与筹资活动有关的现金","支付的其他与筹资活动有关的现金") -> 支付的其他与筹资活动有关的现金 | V91: =IF(J91>0,"收到的其他与筹资活动有关的现金","支付的其他与筹资活动有关的现金") -> 支付的其他与筹资活动有关的现金
B92: 费用支出 | D92: 46600 | E92: =INDEX('CF-ACPLHK'!$E$29:$Q$29,MATCH('cashflow汇总预算 2027'!$D92,'CF-ACPLHK'!$E$4:$Q$4,0))+INDEX('CF-ACPLHK'!$E$38:$Q$38,MATCH($D92,'CF-ACPLHK'!$E$4:$Q$4,0)) -> #N/A | F92: =INDEX('CF-ACPL'!$E$29:$Q$29,MATCH($D92,'CF-ACPL'!$E$4:$Q$4,0))+INDEX('CF-ACPL'!$E$38:$Q$38,MATCH($D92,'CF-ACPL'!$E$4:$Q$4)) -> #N/A | G92: =INDEX('CF-ACPLSZ'!$E$29:$Q$29,MATCH($D92,'CF-ACPLSZ'!$E$4:$Q$4,0))+INDEX('CF-ACPLSZ'!$E$38:$Q$38,MATCH($D92,'CF-ACPLSZ'!$E$4:$Q$4)) -> #N/A | H92: =INDEX('CF-ACPSZL'!$E$29:$Q$29,MATCH('cashflow汇总预算 2027'!$D92,'CF-ACPSZL'!$E$4:$Q$4,0))+INDEX('CF-ACPSZL'!$E$38:$Q$38,MATCH($D92,'CF-ACPSZL'!$E$4:$Q$4,0)) -> #N/A | I92: =INDEX('CF-ACPLGZ'!$E$29:$Q$29,MATCH('cashflow汇总预算 2027'!$D92,'CF-ACPLGZ'!$E$4:$Q$4,0))+INDEX('CF-ACPLGZ'!$E$38:$Q$38,MATCH($D92,'CF-ACPLGZ'!$E$4:$Q$4,0)) -> #N/A | J92: =INDEX('CF-ACPLYixing'!$E$29:$Q$29,MATCH($D92,'CF-ACPLYixing'!$E$4:$Q$4,0))+INDEX('CF-ACPLYixing'!$E$38:$Q$38,MATCH($D92,'CF-ACPLYixing'!$E$4:$Q$4,0)) -> #N/A | K92: =SUM(E92:J92) -> #N/A
B93: 现金余额 | D93: 46600 | E93: =SUM(E86:E92) -> #N/A | F93: =SUM(F86:F92) -> #N/A | G93: =SUM(G86:G92) -> #N/A | H93: =SUM(H86:H92) -> #N/A | I93: =SUM(I86:I92) -> #N/A | J93: =SUM(J86:J92) -> #N/A | K93: =SUM(K86:K92) -> #N/A | M93: =SUM(M86:M92) -> 0 | N93: =SUM(N86:N92) -> 159664.76 | O93: =SUM(O86:O92) -> 161340.95
B94: 注资Albamen New Energy | D94: 46631 | F94: =-INDEX(情形1!$26:$26,MATCH($D94,情形1!$3:$3))*10000 -> -2255274 | K94: =SUM(E94:J94) -> -2255274 | M94: =-F94/75% -> 3007032 | R94: 投资支付的现金 | W94: =R94 -> 投资支付的现金
B95: 注资深圳曦风 | D95: 46631 | H95: =-INDEX(情形1!$30:$30,MATCH($D95,情形1!$3:$3))*10000 -> -676582.19 | K95: =SUM(E95:J95) -> -676582.19 | M95: =H95/900*4000 -> -3007032 | N95: =-H95-M95 -> 3683614.2 | T95: 投资支付的现金 | W95: 投资支付的现金
B96: 注资深圳新融 | D96: 46631 | G96: =-INDEX(情形1!$28:$28,MATCH($D96,情形1!$3:$3))*10000 -> -1252930 | K96: =SUM(E96:J96) -> -1252930 | N96: =G96/1250*3650 -> -3658555.6 | O96: =-G96-N96 -> 4911485.5 | Q96: 投资支付的现金 | W96: 投资支付的现金
B97: 注资JV基金 | D97: 46631 | K97: =SUM(E97:J97) -> 0 | O97: =-INDEX(情形1!$32:$32,MATCH($D97,情形1!$3:$3))*10000 -> -5011719.9
B98: 内部调拨 | D98: 46631 | E98: =-F98 -> #N/A | F98: =-F99 -> #N/A | G98: 1500000 | H98: =-G98 -> -1500000 | K98: =SUM(E98:J98) -> #N/A | Q98: =IF(E98>0,"收到的其他与筹资活动有关的现金","支付的其他与筹资活动有关的现金") -> #N/A | R98: =IF(F98>0,"收到的其他与筹资活动有关的现金","支付的其他与筹资活动有关的现金") -> #N/A | S98: =IF(G98>0,"收到的其他与筹资活动有关的现金","支付的其他与筹资活动有关的现金") -> 收到的其他与筹资活动有关的现金 | T98: =IF(H98>0,"收到的其他与筹资活动有关的现金","支付的其他与筹资活动有关的现金") -> 支付的其他与筹资活动有关的现金 | U98: =IF(I98>0,"收到的其他与筹资活动有关的现金","支付的其他与筹资活动有关的现金") -> 支付的其他与筹资活动有关的现金 | V98: =IF(J98>0,"收到的其他与筹资活动有关的现金","支付的其他与筹资活动有关的现金") -> 支付的其他与筹资活动有关的现金
B99: 费用支出 | D99: 46631 | E99: =INDEX('CF-ACPLHK'!$E$29:$Q$29,MATCH('cashflow汇总预算 2027'!$D99,'CF-ACPLHK'!$E$4:$Q$4,0))+INDEX('CF-ACPLHK'!$E$38:$Q$38,MATCH($D99,'CF-ACPLHK'!$E$4:$Q$4,0)) -> #N/A | F99: =INDEX('CF-ACPL'!$E$29:$Q$29,MATCH($D99,'CF-ACPL'!$E$4:$Q$4,0))+INDEX('CF-ACPL'!$E$38:$Q$38,MATCH($D99,'CF-ACPL'!$E$4:$Q$4)) -> #N/A | G99: =INDEX('CF-ACPLSZ'!$E$29:$Q$29,MATCH($D99,'CF-ACPLSZ'!$E$4:$Q$4,0))+INDEX('CF-ACPLSZ'!$E$38:$Q$38,MATCH($D99,'CF-ACPLSZ'!$E$4:$Q$4)) -> #N/A | H99: =INDEX('CF-ACPSZL'!$E$29:$Q$29,MATCH('cashflow汇总预算 2027'!$D99,'CF-ACPSZL'!$E$4:$Q$4,0))+INDEX('CF-ACPSZL'!$E$38:$Q$38,MATCH($D99,'CF-ACPSZL'!$E$4:$Q$4,0)) -> #N/A | I99: =INDEX('CF-ACPLGZ'!$E$29:$Q$29,MATCH('cashflow汇总预算 2027'!$D99,'CF-ACPLGZ'!$E$4:$Q$4,0))+INDEX('CF-ACPLGZ'!$E$38:$Q$38,MATCH($D99,'CF-ACPLGZ'!$E$4:$Q$4,0)) -> #N/A | J99: =INDEX('CF-ACPLYixing'!$E$29:$Q$29,MATCH($D99,'CF-ACPLYixing'!$E$4:$Q$4,0))+INDEX('CF-ACPLYixing'!$E$38:$Q$38,MATCH($D99,'CF-ACPLYixing'!$E$4:$Q$4,0)) -> #N/A | K99: =SUM(E99:J99) -> #N/A
B100: 现金余额 | D100: 46631 | E100: =SUM(E93:E99) -> #N/A | F100: =SUM(F93:F99) -> #N/A | G100: =SUM(G93:G99) -> #N/A | H100: =SUM(H93:H99) -> #N/A | I100: =SUM(I93:I99) -> #N/A | J100: =SUM(J93:J99) -> #N/A | K100: =SUM(K93:K99) -> #N/A | M100: =SUM(M93:M99) -> 0 | N100: =SUM(N93:N99) -> 184723.36 | O100: =SUM(O93:O99) -> 61106.55
B101: 注资Albamen New Energy | D101: 46661 | F101: =-INDEX(情形1!$26:$26,MATCH($D101,情形1!$3:$3))*10000 -> 0 | K101: =SUM(E101:J101) -> 0 | M101: =-F101/75% -> 0 | R101: 投资支付的现金 | W101: =R101 -> 投资支付的现金
B102: 注资深圳曦风 | D102: 46661 | H102: =-INDEX(情形1!$30:$30,MATCH($D102,情形1!$3:$3))*10000 -> 0 | K102: =SUM(E102:J102) -> 0 | M102: =H102/900*4000 -> 0 | N102: =-H102-M102 -> 0 | T102: 投资支付的现金 | W102: 投资支付的现金
B103: 注资深圳新融 | D103: 46661 | G103: =-INDEX(情形1!$28:$28,MATCH($D103,情形1!$3:$3))*10000 -> 0 | K103: =SUM(E103:J103) -> 0 | N103: =G103/1250*3650 -> 0 | O103: =-G103-N103 -> 0 | Q103: 投资支付的现金 | W103: 投资支付的现金
...

Sheet 情形1
C2: 1 | D2: 2 | F2: 3 | G2: 18 | H2: 19 | I2: 20 | J2: 21 | K2: 22 | L2: 23 | M2: 24 | N2: 25 | O2: 26 | P2: 27 | Q2: 28 | R2: 29 | S2: 30 | T2: 31 | U2: 32 | V2: 33 | W2: 34 | X2: 35 | Y2: 36 | Z2: 37 | AA2: 38 | AB2: 39 | AC2: 40 | AD2: 41 | AE2: 42 | AF2: 43 | AG2: 44 | AH2: 45 | AI2: 46 | AJ2: 47 | AK2: 48
A3: 1 | G3: 45992 | H3: 46023 | I3: 46054 | J3: 46082 | K3: 46113 | L3: 46143 | M3: 46174 | N3: 46204 | O3: 46235 | P3: 46266 | Q3: 46296 | R3: 46327 | S3: 46357 | T3: 46388 | U3: 46419 | V3: 46447 | W3: 46478 | X3: 46508 | Y3: 46539 | Z3: 46569 | AA3: 46600 | AB3: 46631 | AC3: 46661 | AD3: 46692 | AE3: 46722 | AF3: 46753 | AG3: 46784 | AH3: 46813 | AI3: 46844 | AJ3: 46874 | AK3: 46905 | AL3: 46935 | AM3: 46966 | AN3: 46997 | AO3: 47027 | AP3: 47058 | AQ3: 47088 | AR3: 47119 | AS3: 47150 | AT3: 47178 | AU3: 47209 | AV3: 47239 | AW3: 47270 | AX3: 47300 | AY3: 47331 | AZ3: 47362 | BA3: 47392 | BB3: 47423 | BC3: 47453 | BD3: 47484 | BE3: 47515 | BF3: 47543 | BG3: 47574 | BH3: 47604 | BI3: 47635 | BJ3: 47665 | BK3: 47696 | BL3: 47727 | BM3: 47757 | BN3: 47788 | BO3: 47818
C4: MAA季度管理费支付期间 | H4: 1 | I4: 0 | J4: 0 | K4: 1 | L4: 0 | M4: 0 | N4: 1 | O4: 0 | P4: 0 | Q4: 1 | R4: 0 | S4: 0 | T4: 1 | U4: 0 | V4: 0 | W4: 1 | X4: 0 | Y4: 0 | Z4: 1 | AA4: 0 | AB4: 0 | AC4: 1 | AD4: 0 | AE4: 0 | AF4: 1 | AG4: 0 | AH4: 0 | AI4: 1 | AJ4: 0 | AK4: 0 | AL4: 1 | AM4: 0 | AN4: 0 | AO4: 1 | AP4: 0 | AQ4: 0 | AR4: 1 | AS4: 0 | AT4: 0 | AU4: 1 | AV4: 0 | AW4: 0 | AX4: 1 | AY4: 0 | AZ4: 0 | BA4: 1 | BB4: 0 | BC4: 0 | BD4: 1 | BE4: 0 | BF4: 0 | BG4: 1 | BH4: 0 | BI4: 0 | BJ4: 1 | BK4: 0 | BL4: 0 | BM4: 1 | BN4: 0 | BO4: 0 | BP4: 1 | BQ4: 0 | BR4: 0 | BS4: 1 | BT4: 0 | BU4: 0
A5: 2 | C5: MAA新增资本管理费支付期间 | H5: 0 | I5: 1 | J5: 1 | K5: 0 | L5: 1 | M5: 1 | N5: 0 | O5: 1 | P5: 1 | Q5: 0 | R5: 1 | S5: 1 | T5: 0 | U5: 1 | V5: 1 | W5: 0 | X5: 1 | Y5: 1 | Z5: 0 | AA5: 1 | AB5: 1 | AC5: 0 | AD5: 1 | AE5: 1 | AF5: 0 | AG5: 1 | AH5: 1 | AI5: 0 | AJ5: 1 | AK5: 1 | AL5: 0 | AM5: 1 | AN5: 1 | AO5: 0 | AP5: 1 | AQ5: 1 | AR5: 0 | AS5: 1 | AT5: 1 | AU5: 0 | AV5: 1 | AW5: 1 | AX5: 0 | AY5: 1 | AZ5: 1 | BA5: 0 | BB5: 1 | BC5: 1 | BD5: 0 | BE5: 1 | BF5: 1 | BG5: 0 | BH5: 1 | BI5: 1 | BJ5: 0 | BK5: 1 | BL5: 1 | BM5: 0 | BN5: 1 | BO5: 1 | BP5: 0 | BQ5: 1 | BR5: 1 | BS5: 0 | BT5: 1 | BU5: 1
C6: 天数 | H6: =DAY(EOMONTH(H3,0)) -> 31 | I6: =DAY(EOMONTH(I3,0)) -> 28 | J6: =DAY(EOMONTH(J3,0)) -> 31 | K6: =DAY(EOMONTH(K3,0)) -> 30 | L6: =DAY(EOMONTH(L3,0)) -> 31 | M6: =DAY(EOMONTH(M3,0)) -> 30 | N6: =DAY(EOMONTH(N3,0)) -> 31 | O6: =DAY(EOMONTH(O3,0)) -> 31 | ... AJ6: =DAY(EOMONTH(AJ3,0)) -> 31 | AK6: =DAY(EOMONTH(AP3,0)) -> 30 | AL6: =DAY(EOMONTH(AL3,0)) -> 31 | AM6: =DAY(EOMONTH(AM3,0)) -> 31 | AN6: =DAY(EOMONTH(AN3,0)) -> 30 | AO6: =DAY(EOMONTH(AO3,0)) -> 31 | AP6: =DAY(EOMONTH(AP3,0)) -> 30 | AQ6: =DAY(EOMONTH(AQ3,0)) -> 31 | AR6: =DAY(EOMONTH(AR3,0)) -> 31 | AS6: =DAY(EOMONTH(AS3,0)) -> 28 | ... AV6: =DAY(EOMONTH(AV3,0)) -> 31 | AW6: =DAY(EOMONTH(BB3,0)) -> 30 | AX6: =DAY(EOMONTH(AX3,0)) -> 31 | AY6: =DAY(EOMONTH(AY3,0)) -> 31 | AZ6: =DAY(EOMONTH(AZ3,0)) -> 30 | BA6: =DAY(EOMONTH(BA3,0)) -> 31 | BB6: =DAY(EOMONTH(BB3,0)) -> 30 | BC6: =DAY(EOMONTH(BC3,0)) -> 31 | BD6: =DAY(EOMONTH(BD3,0)) -> 31 | BE6: =DAY(EOMONTH(BE3,0)) -> 28 | ... BH6: =DAY(EOMONTH(BH3,0)) -> 31 | BI6: =DAY(EOMONTH(BN3,0)) -> 30 | BJ6: =DAY(EOMONTH(BJ3,0)) -> 31 | BK6: =DAY(EOMONTH(BK3,0)) -> 31 | BL6: =DAY(EOMONTH(BL3,0)) -> 30 | BM6: =DAY(EOMONTH(BM3,0)) -> 31 | BN6: =DAY(EOMONTH(BN3,0)) -> 30 | BO6: =DAY(EOMONTH(BO3,0)) -> 31 | BP6: =DAY(EOMONTH(BP3,0)) -> 31 | BQ6: =DAY(EOMONTH(BQ3,0)) -> 31 | ... BT6: =DAY(EOMONTH(BT3,0)) -> 31 | BU6: =DAY(EOMONTH(BZ3,0)) -> 31
C7: 新增装机（MW） | H7: 55 | I7: 0 | J7: =汇总!D39 -> 0 | K7: 0 | L7: 0 | M7: =汇总!D40 -> 100 | P7: =汇总!D41 -> 0 | S7: =汇总!D42 -> 400 | V7: =汇总!D47 -> 0 | Y7: =汇总!D48 -> 100 | AB7: =汇总!D49 -> 100 | AE7: =汇总!D50 -> 100 | AH7: =汇总!D55 -> 0 | AK7: =汇总!D56 -> 100 | AN7: =汇总!D57 -> 0 | AQ7: =汇总!D58 -> 0
C8: 累计装机（MW） | G8: =G7 -> 0 | H8: =G8+H7 -> 55 | I8: =H8+I7 -> 55 | J8: =I8+J7 -> 55 | K8: =J8+K7 -> 55 | L8: =K8+L7 -> 55 | M8: =L8+M7 -> 155 | N8: =M8+N7 -> 155 | O8: =N8+O7 -> 155 | ... BO8: =BN8+BO7 -> 955
C9: 累计装机（MW）- annual cumulative average | S9: =SUMPRODUCT($H$8:S8,$H$6:S6)/365 -> 147.60274 | AE9: =SUMPRODUCT($T$8:AE8,$T$6:AE6)/365 -> 655.54795 | AQ9: =SUMPRODUCT($AF$8:AQ8,$AF$6:AQ6)/365 -> 915.9726
C10: 项目数量 | H10: {=G10+_xlfn.IFS(H7=0,0,H7<=100,1,H7<=200,2)} -> 1 | I10: {=H10+_xlfn.IFS(I7=0,0,I7<=100,1,I7<=200,2)} -> 1 | J10: {=I10+_xlfn.IFS(J7=0,0,J7<=100,1,J7<=200,2)} -> 1 | K10: {=J10+_xlfn.IFS(K7=0,0,K7<=100,1,K7<=200,2)} -> 1 | L10: {=K10+_xlfn.IFS(L7=0,0,L7<=100,1,L7<=200,2)} -> 1 | M10: {=L10+_xlfn.IFS(M7=0,0,M7<=100,1,M7<=200,2)} -> 2 | N10: {=M10+_xlfn.IFS(N7=0,0,N7<=100,1,N7<=200,2)} -> 2 | O10: {=N10+_xlfn.IFS(O7=0,0,O7<=100,1,O7<=200,2)} -> 2 | ... R10: {=Q10+_xlfn.IFS(R7=0,0,R7<=100,1,R7<=200,2)} -> 2 | S10: =S7/70 -> 5.7142857 | T10: {=S10+_xlfn.IFS(T7=0,0,T7<=100,1,T7<=200,2)} -> 5.7142857 | U10: {=T10+_xlfn.IFS(U7=0,0,U7<=100,1,U7<=200,2)} -> 5.7142857 | V10: {=U10+_xlfn.IFS(V7=0,0,V7<=100,1,V7<=200,2)} -> 5.7142857 | W10: {=V10+_xlfn.IFS(W7=0,0,W7<=100,1,W7<=200,2)} -> 5.7142857 | X10: {=W10+_xlfn.IFS(X7=0,0,X7<=100,1,X7<=200,2)} -> 5.7142857 | Y10: {=X10+_xlfn.IFS(Y7=0,0,Y7<=100,1,Y7<=200,2)} -> 6.7142857 | Z10: {=Y10+_xlfn.IFS(Z7=0,0,Z7<=100,1,Z7<=200,2)} -> 6.7142857 | AA10: {=Z10+_xlfn.IFS(AA7=0,0,AA7<=100,1,AA7<=200,2)} -> 6.7142857 | ... BO10: {=BN10+_xlfn.IFS(BO7=0,0,BO7<=100,1,BO7<=200,2)} -> 9.7142857
C11: 区域数量 | G11: =G10 -> 0 | H11: =H10 -> 1 | I11: =I10 -> 1 | J11: =J10 -> 1 | K11: =K10 -> 1 | L11: =L10 -> 1 | M11: =M10 -> 2 | N11: =M11 -> 2 | O11: =N11 -> 2 | P11: =O11 -> 2 | Q11: =P11 -> 2 | R11: =Q11 -> 2 | S11: =S10/2 -> 2.8571429 | T11: =S11 -> 2.8571429 | U11: =T11 -> 2.8571429 | V11: =U11 -> 2.8571429 | W11: =V11 -> 2.8571429 | X11: =W11 -> 2.8571429 | Y11: =X11+1 -> 3.8571429 | Z11: =Y11 -> 3.8571429 | AA11: =Z11 -> 3.8571429 | AB11: =AA11 -> 3.8571429 | AC11: =AB11 -> 3.8571429 | AD11: =AC11 -> 3.8571429 | AE11: =AD11 -> 3.8571429 | AF11: =AE11 -> 3.8571429 | AG11: =AF11 -> 3.8571429 | ... AP11: =AO11 -> 3.8571429 | AQ11: 4 | AR11: =AQ11 -> 4 | AS11: =AR11 -> 4 | AT11: =AS11 -> 4 | AU11: =AT11 -> 4 | AV11: =AU11 -> 4 | AW11: =AV11 -> 4 | AX11: =AW11 -> 4 | AY11: =AX11 -> 4 | ... BO11: =BN11 -> 4
C12: 平均单瓦股权价格（元/W) | F12: =汇总!$D$64 -> 2 | H12: =$F$12 -> 2 | I12: =$F$12 -> 2 | J12: =$F$12 -> 2 | K12: =$F$12 -> 2 | L12: =$F$12 -> 2 | M12: =$F$12 -> 2 | N12: =$F$12 -> 2 | O12: =$F$12 -> 2 | ... BO12: =$F$12 -> 2
C13: JV股权新增出资额（万元） | G13: 0 | H13: 0 | I13: =+I7*I12*100 -> 0 | J13: =+J7*J12*100 -> 0 | K13: =+K7*K12*100 -> 0 | L13: =+L7*L12*100 -> 0 | M13: =+M7*M12*100 -> 20000 | N13: =+N7*N12*100 -> 0 | O13: =+O7*O12*100 -> 0 | P13: =+P7*P12*100 -> 0 | ... BO13: =+BO7*BO12*100 -> 0
C14: JV股权累计出资额（万元） | G14: =8700 -> 8700 | H14: =G14+H13 -> 8700 | I14: =H14+I13 -> 8700 | J14: =I14+J13 -> 8700 | K14: =J14+K13 -> 8700 | L14: =K14+L13 -> 8700 | M14: =L14+M13 -> 28700 | N14: =M14+N13 -> 28700 | O14: =N14+O13 -> 28700 | ... BO14: =BN14+BO13 -> 188700
C16: 基金股权新增出资额（万元） | F16: 0.75 | G16: =G13*$F$16 -> 0 | H16: =H13*$F$16 -> 0 | I16: =I13*$F$16 -> 0 | J16: =J13*$F$16 -> 0 | K16: =K14*50% -> 4350 | L16: =L13*$F$16 -> 0 | M16: =M13*$F$16 -> 15000 | N16: =N13*$F$16 -> 0 | O16: =O13*$F$16 -> 0 | P16: =P13*$F$16 -> 0 | Q16: =Q13*$F$16 -> 0 | R16: =R13*$F$16 -> 0 | S16: =S13*$F$16 -> 60000 | ... BO16: =BO13*$F$16 -> 0
C17: 基金股权累计出资额（万元） | F17: 0.75 | G17: =G16 -> 0 | H17: =G17+H16 -> 0 | I17: =H17+I16 -> 0 | J17: =I17+J16 -> 0 | K17: =J17+K16 -> 4350 | L17: =K17+L16 -> 4350 | M17: =L17+M16 -> 19350 | N17: =M17+N16 -> 19350 | O17: =N17+O16 -> 19350 | ... BO17: =BN17+BO16 -> 139350
A18: 8 | C18: 基金费用新增出资额（万元） | G18: 0 | H18: 0 | I18: 0 | J18: 0 | K18: 500 | L18: 0 | M18: 0 | N18: 0 | O18: 0 | P18: 0 | Q18: 0 | R18: 0 | S18: 0 | T18: 200 | U18: 0 | V18: 0 | W18: 0 | X18: 0 | Y18: 0 | Z18: 0 | AA18: 0 | AB18: 0 | AC18: 0 | AD18: 0 | AE18: 0 | AF18: 200 | AG18: 0 | AH18: 0 | AI18: 0 | AJ18: 0 | AK18: 0 | AL18: 0 | AM18: 0 | AN18: 0 | AO18: 0 | AP18: 0 | AQ18: 0 | AR18: 200 | AS18: 0 | AT18: 0 | AU18: 0 | AV18: 0 | AW18: 0 | AX18: 0 | AY18: 0 | AZ18: 0 | BA18: 0 | BB18: 0 | BC18: 0 | BD18: 200 | BE18: 0 | BF18: 0 | BG18: 0 | BH18: 0 | BI18: 0 | BJ18: 0 | BK18: 0 | BL18: 0 | BM18: 0 | BN18: 0 | BO18: 0
A19: 8 | C19: 基金费用累计出资额（万元） | G19: =G18 -> 0 | H19: =G19+H18 -> 0 | I19: =H19+I18 -> 0 | J19: =I19+J18 -> 0 | K19: =J19+K18 -> 500 | L19: =K19+L18 -> 500 | M19: =L19+M18 -> 500 | N19: =M19+N18 -> 500 | O19: =N19+O18 -> 500 | ... BO19: =BN19+BO18 -> 1300
A20: 8 | C20: 基金基础管理费出资额（含税，万元） | F20: 0.7 | G20: =(G$17+G$19)/99%*1%*(DATE(YEAR(G$3),12,31)-G$3)/365 -> 0 | H20: =(H$17+H$19)/99%*1%*(DATE(YEAR(H$3),12,31)-H$3)/365*$F$20 -> 0 | I20: =(I$16+I$18)/99%*1%*(DATE(YEAR(I$3),12,31)-I$3)/365*$F$20 -> 0 | J20: =(J$16+J$18)/99%*1%*(DATE(YEAR(J$3),12,31)-J$3)/365*$F$20 -> 0 | K20: =(K$16+K$18)/99%*1%*(DATE(YEAR(K$3),12,31)-K$3)/365*$F$20 -> 25.743185 | L20: =(L$16+L$18)/99%*1%*(DATE(YEAR(L$3),12,31)-L$3)/365*$F$20 -> 0 | M20: =(M$16+M$18)/99%*1%*(DATE(YEAR(M$3),12,31)-M$3)/365*$F$20 -> 61.892902 | N20: =(N$16+N$18)/99%*1%*(DATE(YEAR(N$3),12,31)-N$3)/365*$F$20 -> 0 | O20: =(O$16+O$18)/99%*1%*(DATE(YEAR(O$3),12,31)-O$3)/365*$F$20 -> 0 | P20: =(P$16+P$18)/99%*1%*(DATE(YEAR(P$3),12,31)-P$3)/365*$F$20 -> 0 | ... S20: =(S$16+S$18)/99%*1%*(DATE(YEAR(S$3),12,31)-S$3)/365*$F$20 -> 34.86924 | T20: =(T$17+T$19)/99%*1%*(DATE(YEAR(T$3),12,31)-T$3)/365*$F$20 -> 564.45939 | U20: =U$16/99%*1%*(DATE(YEAR(U$3),12,31)-U$3)/365*$F$20 -> 0 | V20: =V$16/99%*1%*(DATE(YEAR(V$3),12,31)-V$3)/365*$F$20 -> 0 | W20: =W$16/99%*1%*(DATE(YEAR(W$3),12,31)-W$3)/365*$F$20 -> 0 | X20: =X$16/99%*1%*(DATE(YEAR(X$3),12,31)-X$3)/365*$F$20 -> 0 | Y20: =Y$16/99%*1%*(DATE(YEAR(Y$3),12,31)-Y$3)/365*$F$20 -> 61.892902 | Z20: =Z$16/99%*1%*(DATE(YEAR(Z$3),12,31)-Z$3)/365*$F$20 -> 0 | AA20: =AA$16/99%*1%*(DATE(YEAR(AA$3),12,31)-AA$3)/365*$F$20 -> 0 | AB20: =AB$16/99%*1%*(DATE(YEAR(AB$3),12,31)-AB$3)/365*$F$20 -> 35.159817 | ... AE20: =AE$16/99%*1%*(DATE(YEAR(AE$3),12,31)-AE$3)/365*$F$20 -> 8.7173101 | AF20: =AF$17/99%*1%*(DATE(YEAR(AF$3),12,31)-AF$3)/365*$F$20 -> 879.24242 | AG20: =AG$16/99%*1%*(DATE(YEAR(AG$3),12,31)-AG$3)/365*$F$20 -> 0 | AH20: =AH$16/99%*1%*(DATE(YEAR(AH$3),12,31)-AH$3)/365*$F$20 -> 0 | AI20: =AI$16/99%*1%*(DATE(YEAR(AI$3),12,31)-AI$3)/365*$F$20 -> 0 | AJ20: =AJ$16/99%*1%*(DATE(YEAR(AJ$3),12,31)-AJ$3)/365*$F$20 -> 0 | AK20: =AK$16/99%*1%*(DATE(YEAR(AP$3),12,31)-AP$3)/365*$F$20 -> 17.43462 | AL20: =AL$16/99%*1%*(DATE(YEAR(AQ$3),12,31)-AQ$3)/365*$F$20 -> 0 | AM20: =AM$16/99%*1%*(DATE(YEAR(AR$3),12,31)-AR$3)/365*$F$20 -> 0 | AN20: =AN$16/99%*1%*(DATE(YEAR(AS$3),12,31)-AS$3)/365*$F$20 -> 0 | AO20: =AO$16/99%*1%*(DATE(YEAR(AT$3),12,31)-AT$3)/365*$F$20 -> 0 | AP20: =AP$16/99%*1%*(DATE(YEAR(AU$3),12,31)-AU$3)/365*$F$20 -> 0 | AQ20: =AQ$16/99%*1%*(DATE(YEAR(AV$3),12,31)-AV$3)/365*$F$20 -> 0 | AR20: =AR$16/99%*1%*(DATE(YEAR(AW$3),12,31)-AW$3)/365*$F$20 -> 0 | ... BO20: =BO$16/99%*1%*(DATE(YEAR(BT$3),12,31)-BT$3)/365*$F$20 -> 0
A21: 8 | C21: 基金激励管理费出资额（含税，万元） | D21: “1”为支付，"0"为不支付 | E21: =汇总!E65 -> 0 | F21: 0.3 | G21: 0 | H21: =(H$17+H$19)/99%*1%*(DATE(YEAR(H$3),12,31)-H$3)/365*$F$21*$E$21 -> 0 | I21: =(I$16+I$18)/99%*1%*(DATE(YEAR(I$3),12,31)-I$3)/365*$F$21*$E$21 -> 0 | J21: =(J$16+J$18)/99%*1%*(DATE(YEAR(J$3),12,31)-J$3)/365*$F$21*$E$21 -> 0 | K21: =(K$16+K$18)/99%*1%*(DATE(YEAR(K$3),12,31)-K$3)/365*$F$21*$E$21 -> 0 | L21: =(L$16+L$18)/99%*1%*(DATE(YEAR(L$3),12,31)-L$3)/365*$F$21*$E$21 -> 0 | M21: =(M$16+M$18)/99%*1%*(DATE(YEAR(M$3),12,31)-M$3)/365*$F$21*$E$21 -> 0 | N21: =(N$16+N$18)/99%*1%*(DATE(YEAR(N$3),12,31)-N$3)/365*$F$21*$E$21 -> 0 | O21: =(O$16+O$18)/99%*1%*(DATE(YEAR(O$3),12,31)-O$3)/365*$F$21*$E$21 -> 0 | P21: =(P$16+P$18)/99%*1%*(DATE(YEAR(P$3),12,31)-P$3)/365*$F$21*$E$21 -> 0 | ... S21: =(S$16+S$18)/99%*1%*(DATE(YEAR(S$3),12,31)-S$3)/365*$F$21*$E$21 -> 0 | T21: =(T$17+T$19)/99%*1%*(DATE(YEAR(T$3),12,31)-T$3)/365*$F$21*$E$21 -> 0 | U21: =(U$16+U$18)/99%*1%*(DATE(YEAR(U$3),12,31)-U$3)/365*$F$21*$E$21 -> 0 | V21: =(V$16+V$18)/99%*1%*(DATE(YEAR(V$3),12,31)-V$3)/365*$F$21*$E$21 -> 0 | W21: =(W$16+W$18)/99%*1%*(DATE(YEAR(W$3),12,31)-W$3)/365*$F$21*$E$21 -> 0 | X21: =(X$16+X$18)/99%*1%*(DATE(YEAR(X$3),12,31)-X$3)/365*$F$21*$E$21 -> 0 | Y21: =(Y$16+Y$18)/99%*1%*(DATE(YEAR(Y$3),12,31)-Y$3)/365*$F$21*$E$21 -> 0 | Z21: =(Z$16+Z$18)/99%*1%*(DATE(YEAR(Z$3),12,31)-Z$3)/365*$F$21*$E$21 -> 0 | AA21: =(AA$16+AA$18)/99%*1%*(DATE(YEAR(AA$3),12,31)-AA$3)/365*$F$21*$E$21 -> 0 | AB21: =(AB$16+AB$18)/99%*1%*(DATE(YEAR(AB$3),12,31)-AB$3)/365*$F$21*$E$21 -> 0 | ... AE21: =(AE$16+AE$18)/99%*1%*(DATE(YEAR(AE$3),12,31)-AE$3)/365*$F$21*$E$21 -> 0 | AF21: =(AF$17+AF$19)/99%*1%*(DATE(YEAR(AF$3),12,31)-AF$3)/365*$F$21*$E21 -> 0 | AG21: =AG$16/99%*1%*(DATE(YEAR(AG$3),12,31)-AG$3)/365*$F$21 -> 0 | AH21: =AH$16/99%*1%*(DATE(YEAR(AH$3),12,31)-AH$3)/365*$F$21 -> 0 | AI21: =AI$16/99%*1%*(DATE(YEAR(AI$3),12,31)-AI$3)/365*$F$21 -> 0 | AJ21: =AJ$16/99%*1%*(DATE(YEAR(AJ$3),12,31)-AJ$3)/365*$F$21 -> 0 | AK21: =(AK$16+AK$18)/99%*1%*(DATE(YEAR(AP$3),12,31)-AP$3)/365*$F$21*$E$21 -> 0 | AL21: =(AL$16+AL$18)/99%*1%*(DATE(YEAR(AQ$3),12,31)-AQ$3)/365*$F$21*$E$21 -> 0 | AM21: =(AM$16+AM$18)/99%*1%*(DATE(YEAR(AR$3),12,31)-AR$3)/365*$F$21*$E$21 -> 0 | AN21: =(AN$16+AN$18)/99%*1%*(DATE(YEAR(AS$3),12,31)-AS$3)/365*$F$21*$E$21 -> 0 | AO21: =(AO$16+AO$18)/99%*1%*(DATE(YEAR(AT$3),12,31)-AT$3)/365*$F$21*$E$21 -> 0 | AP21: =(AP$16+AP$18)/99%*1%*(DATE(YEAR(AU$3),12,31)-AU$3)/365*$F$21*$E$21 -> 0 | AQ21: =(AQ$16+AQ$18)/99%*1%*(DATE(YEAR(AV$3),12,31)-AV$3)/365*$F$21*$E$21 -> 0 | AR21: =(AR$16+AR$18)/99%*1%*(DATE(YEAR(AW$3),12,31)-AW$3)/365*$F$21*$E$21 -> 0 | ... BO21: =(BO$16+BO$18)/99%*1%*(DATE(YEAR(BT$3),12,31)-BT$3)/365*$F$21*$E$21 -> 0
C22: 基金新增总出资额（万元） | G22: =SUM(G16,G20:G21) -> 0 | H22: =SUM(H16,H20:H21) -> 0 | I22: =SUM(I16,I20:I21) -> 0 | J22: =SUM(J16,J20:J21) -> 0 | K22: =SUM(K16,K18,K20:K21) -> 4875.7432 | L22: =SUM(L16,L18,L20:L21) -> 0 | M22: =SUM(M16,M18,M20:M21) -> 15061.893 | N22: =SUM(N16,N18,N20:N21) -> 0 | O22: =SUM(O16,O18,O20:O21) -> 0 | P22: =SUM(P16,P18,P20:P21) -> 0 | Q22: =SUM(Q16,Q18,Q20:Q21) -> 0 | R22: =SUM(R16,R18,R20:R21) -> 0 | ... BO22: =SUM(BO16,BO18,BO20:BO21) -> 0
C23: 基金累计总出资额（万元） | D23: 认缴资本 | E23: 150000 | F23: 1 | G23: =G22 -> 0 | H23: =G23+H22 -> 0 | I23: =H23+I22 -> 0 | J23: =I23+J22 -> 0 | K23: =J23+K22 -> 4875.7432 | L23: =K23+L22 -> 4875.7432 | M23: =L23+M22 -> 19937.636 | N23: =M23+N22 -> 19937.636 | O23: =N23+O22 -> 19937.636 | ... BO23: =BN23+BO22 -> 142339.41
C24: 基金累计总出资% | G24: =G23/$E$23 -> 0 | H24: =H23/$E$23 -> 0 | I24: =I23/$E$23 -> 0 | J24: =J23/$E$23 -> 0 | K24: =K23/$E$23 -> 0.032504955 | L24: =L23/$E$23 -> 0.032504955 | M24: =M23/$E$23 -> 0.13291757 | N24: =N23/$E$23 -> 0.13291757 | ... BO24: =BO23/$E$23 -> 0.94892941
A26: 4 | C26: ACPL新增出资额（万元） | D26: ACPL | E26: 2250 | F26: =E26/150000 -> 0.015 | G26: 0 | H26: 0 | I26: 0 | J26: =基金资金安排!C22 -> 780 | K26: =IF(($F26*K$23-J27)<0,0,($F26*K$23-J27)) -> 0 | L26: =IF(($F26*L$23-K27)<0,0,($F26*L$23-K27)) -> 0 | M26: =IF(($F26*M$23-L27)<0,0,($F26*M$23-L27)) -> 0 | N26: =IF(($F26*N$23-M27)<0,0,($F26*N$23-M27)) -> 0 | O26: =IF(($F26*O$23-N27)<0,0,($F26*O$23-N27)) -> 0 | P26: =IF(($F26*P$23-O27)<0,0,($F26*P$23-O27)) -> 0 | Q26: =IF(($F26*Q$23-P27)<0,0,($F26*Q$23-P27)) -> 0 | R26: =IF(($F26*R$23-Q27)<0,0,($F26*R$23-Q27)) -> 0 | ... BO26: =IF(($F26*BO$23-BN27)<0,0,($F26*BO$23-BN27)) -> 0
A27: 4 | C27: ACPL累计出资额（万元） | G27: =G26 -> 0 | H27: =G27+H26 -> 0 | I27: =H27+I26 -> 0 | J27: =I27+J26 -> 780 | K27: =J27+K26 -> 780 | L27: =K27+L26 -> 780 | M27: =L27+M26 -> 780 | N27: =M27+N26 -> 780 | O27: =N27+O26 -> 780 | ... BO27: =BN27+BO26 -> 2135.0912
C28: ACPLSZ新增出资额（万元） | D28: ACPLSZ | E28: 1250 | F28: =E28/150000 -> 0.0083333333 | G28: 0 | H28: 0 | I28: 0 | J28: =基金资金安排!C13 -> 237.5 | K28: =基金资金安排!H13 -> 127.55102 | L28: =IF(($F28*L$23-K29)<0,0,($F28*L$23-K29)) -> 0 | M28: =IF(($F28*M$23-L29)<0,0,($F28*M$23-L29)) -> 0 | N28: =IF(($F28*N$23-M29)<0,0,($F28*N$23-M29)) -> 0 | O28: =IF(($F28*O$23-N29)<0,0,($F28*O$23-N29)) -> 0 | P28: =IF(($F28*P$23-O29)<0,0,($F28*P$23-O29)) -> 0 | Q28: =IF(($F28*Q$23-P29)<0,0,($F28*Q$23-P29)) -> 0 | R28: =IF(($F28*R$23-Q29)<0,0,($F28*R$23-Q29)) -> 0 | S28: =IF(($F28*S$23-R29)<0,0,($F28*S$23-R29)) -> 301.38652 | ... BO28: =IF(($F28*BO$23-BN29)<0,0,($F28*BO$23-BN29)) -> 0
C29: ACPLSZ累计出资额（万元） | G29: =G28 -> 0 | H29: =G29+H28 -> 0 | I29: =H29+I28 -> 0 | J29: =I29+J28 -> 237.5 | K29: =J29+K28 -> 365.05102 | L29: =K29+L28 -> 365.05102 | M29: =L29+M28 -> 365.05102 | N29: =M29+N28 -> 365.05102 | O29: =N29+O28 -> 365.05102 | ... BO29: =BN29+BO28 -> 1186.1618
C30: ACPSZL新增出资额（万元） | D30: ACPSZL | E30: 675 | F30: =E30/150000 -> 0.0045 | G30: 0 | H30: 0 | I30: 0 | J30: =基金资金安排!C18 -> 202.04082 | K30: =IF(($F30*K$23-J31)<0,0,($F30*K$23-J31)) -> 0 | L30: =IF(($F30*L$23-K31)<0,0,($F30*L$23-K31)) -> 0 | M30: =IF(($F30*M$23-L31)<0,0,($F30*M$23-L31)) -> 0 | N30: =IF(($F30*N$23-M31)<0,0,($F30*N$23-M31)) -> 0 | O30: =IF(($F30*O$23-N31)<0,0,($F30*O$23-N31)) -> 0 | P30: =IF(($F30*P$23-O31)<0,0,($F30*P$23-O31)) -> 0 | Q30: =IF(($F30*Q$23-P31)<0,0,($F30*Q$23-P31)) -> 0 | R30: =IF(($F30*R$23-Q31)<0,0,($F30*R$23-Q31)) -> 0 | ... BO30: =IF(($F30*BO$23-BN31)<0,0,($F30*BO$23-BN31)) -> 0
A31: 11 | C31: ACPSZL累计出资额（万元） | G31: =G30 -> 0 | H31: =G31+H30 -> 0 | I31: =H31+I30 -> 0 | J31: =I31+J30 -> 202.04082 | K31: =J31+K30 -> 202.04082 | L31: =K31+L30 -> 202.04082 | M31: =L31+M30 -> 202.04082 | N31: =M31+N30 -> 202.04082 | O31: =N31+O30 -> 202.04082 | ... BO31: =BN31+BO30 -> 640.52735
A32: 4 | C32: 深圳新融新增出资额（万元） | D32: 深圳新融 | E32: 5000 | F32: =E32/150000 -> 0.033333333 | G32: 0 | H32: 0 | I32: 0 | J32: =基金资金安排!C7 -> 500 | K32: 1000 | L32: =IF(($F32*L$23-K33)<0,0,($F32*L$23-K33)) -> 0 | M32: =IF(($F32*M$23-L33)<0,0,($F32*M$23-L33)) -> 0 | N32: =IF(($F32*N$23-M33)<0,0,($F32*N$23-M33)) -> 0 | O32: =IF(($F32*O$23-N33)<0,0,($F32*O$23-N33)) -> 0 | P32: =IF(($F32*P$23-O33)<0,0,($F32*P$23-O33)) -> 0 | Q32: =IF(($F32*Q$23-P33)<0,0,($F32*Q$23-P33)) -> 0 | R32: =IF(($F32*R$23-Q33)<0,0,($F32*R$23-Q33)) -> 0 | S32: =IF(($F32*S$23-R33)<0,0,($F32*S$23-R33)) -> 1165.7502 | ... BO32: =IF(($F32*BO$23-BN33)<0,0,($F32*BO$23-BN33)) -> 0
A33: 4 | C33: 深圳新融累计出资额（万元） | G33: =G32 -> 0 | H33: =G33+H32 -> 0 | I33: =H33+I32 -> 0 | J33: =I33+J32 -> 500 | K33: =J33+K32 -> 1500 | L33: =K33+L32 -> 1500 | M33: =L33+M32 -> 1500 | N33: =M33+N32 -> 1500 | O33: =N33+O32 -> 1500 | ... BO33: =BN33+BO32 -> 4744.6471
A34: 19
A35: 32 | C35: MAA 基本收入（含税，万元） | F35: =汇总!$D$66 -> 0.1 | G35: =F35*5500 -> 550 | H35: =H$8*$F35*100*H$4/4+H$7*$F35*100*(DATE(YEAR(H$3),INT((MONTH(H$3)-1)/3)*3+4,0)-H$3)/365*H$5 -> 137.5 | I35: =I$8*$F35*100*I$4/4+I$7*$F35*100*(DATE(YEAR(I$3),INT((MONTH(I$3)-1)/3)*3+4,0)-I$3)/365*I$5 -> 0 | J35: =J$8*$F35*100*J$4/4+J$7*$F35*100*(DATE(YEAR(J$3),INT((MONTH(J$3)-1)/3)*3+4,0)-J$3)/365*J$5 -> 0 | K35: =K$8*$F35*100*K$4/4+K$7*$F35*100*(DATE(YEAR(K$3),INT((MONTH(K$3)-1)/3)*3+4,0)-K$3)/365*K$5 -> 137.5 | L35: =L$8*$F35*100*L$4/4+L$7*$F35*100*(DATE(YEAR(L$3),INT((MONTH(L$3)-1)/3)*3+4,0)-L$3)/365*L$5 -> 0 | M35: =M$8*$F35*100*M$4/4+M$7*$F35*100*(DATE(YEAR(M$3),INT((MONTH(M$3)-1)/3)*3+4,0)-M$3)/365*M$5 -> 79.452055 | N35: =N$8*$F35*100*N$4/4+N$7*$F35*100*(DATE(YEAR(N$3),INT((MONTH(N$3)-1)/3)*3+4,0)-N$3)/365*N$5 -> 387.5 | O35: =O$8*$F35*100*O$4/4+O$7*$F35*100*(DATE(YEAR(O$3),INT((MONTH(O$3)-1)/3)*3+4,0)-O$3)/365*O$5 -> 0 | ... AJ35: =AJ$8*$F35*100*AJ$4/4+AJ$7*$F35*100*(DATE(YEAR(AJ$3),INT((MONTH(AJ$3)-1)/3)*3+4,0)-AJ$3)/365*AJ$5 -> 0 | AK35: =AK$8*$F35*100*AK$4/4+AK$7*$F35*100*(DATE(YEAR(AP$3),INT((MONTH(AP$3)-1)/3)*3+4,0)-AP$3)/365*AK$5 -> 164.38356 | AL35: =AL$8*$F35*100*AL$4/4+AL$7*$F35*100*(DATE(YEAR(AQ$3),INT((MONTH(AQ$3)-1)/3)*3+4,0)-AQ$3)/365*AL$5 -> 2387.5 | AM35: =AM$8*$F35*100*AM$4/4+AM$7*$F35*100*(DATE(YEAR(AR$3),INT((MONTH(AR$3)-1)/3)*3+4,0)-AR$3)/365*AM$5 -> 0 | AN35: =AN$8*$F35*100*AN$4/4+AN$7*$F35*100*(DATE(YEAR(AS$3),INT((MONTH(AS$3)-1)/3)*3+4,0)-AS$3)/365*AN$5 -> 0 | AO35: =AO$8*$F35*100*AO$4/4+AO$7*$F35*100*(DATE(YEAR(AT$3),INT((MONTH(AT$3)-1)/3)*3+4,0)-AT$3)/365*AO$5 -> 2387.5 | AP35: =AP$8*$F35*100*AP$4/4+AP$7*$F35*100*(DATE(YEAR(AU$3),INT((MONTH(AU$3)-1)/3)*3+4,0)-AU$3)/365*AP$5 -> 0 | AQ35: =AQ$8*$F35*100*AQ$4/4+AQ$7*$F35*100*(DATE(YEAR(AV$3),INT((MONTH(AV$3)-1)/3)*3+4,0)-AV$3)/365*AQ$5 -> 0 | AR35: =AR$8*$F35*100*AR$4/4+AR$7*$F35*100*(DATE(YEAR(AW$3),INT((MONTH(AW$3)-1)/3)*3+4,0)-AW$3)/365*AR$5 -> 2387.5 | ... BO35: =BO$8*$F35*100*BO$4/4+BO$7*$F35*100*(DATE(YEAR(BT$3),INT((MONTH(BT$3)-1)/3)*3+4,0)-BT$3)/365*BO$5 -> 0
A36: 32 | C36: MAA 激励收入一（含税，万元） | D36: “1”为支付，"0"为不支付 | E36: =汇总!E67 -> 0 | F36: =汇总!$D$67 -> 0.01 | G36: =G$8*$F36*100*(DATE(2025,12,31)-DATE(2024,12,16))/365 -> 0 | T36: {=SUMPRODUCT(H$8:S$8,I$3:T$3-H$3:S$3)/(T$3-H$3)*100*$F36*$E$36} -> 0 | AF36: {=SUMPRODUCT(T$8:AE$8,U$3:AF$3-T$3:AE$3)/(AF$3-T$3)*100*$F36*$E$36} -> 0
C37: MAA 激励收入二（含税，万元） | D37: “1”为支付，"0"为不支付 | E37: =汇总!E68 -> 0 | F37: =汇总!$D$68 -> 0.04 | G37: =G$8*$F37*100*(DATE(2025,12,31)-DATE(2024,12,16))/365 -> 0 | T37: {=SUMPRODUCT(H$8:S$8,I$3:T$3-H$3:S$3)/(T$3-H$3)*100*$F37*$E$37} -> 0 | AF37: {=SUMPRODUCT(T$8:AE$8,U$3:AF$3-T$3:AE$3)/(AF$3-T$3)*100*$F37*$E$37} -> 0
A38: 32 | C38: 总MAA收入（含税，万元） | G38: =SUM(G35:G37) -> 550 | H38: =SUM(H35:H37) -> 137.5 | I38: =SUM(I35:I37) -> 0 | J38: =SUM(J35:J37) -> 0 | K38: =SUM(K35:K37) -> 137.5 | L38: =SUM(L35:L37) -> 0 | M38: =SUM(M35:M37) -> 79.452055 | N38: =SUM(N35:N37) -> 387.5 | ... BO38: =SUM(BO35:BO37) -> 0
A40: 32 | C40: MAA 基本收入（不含税，万元） | D40: VAT | E40: 0.06 | F40: 0.12 | G40: =G35/(1+$E40) -> 518.86792 | H40: =H35/(1+$E40) -> 129.71698 | I40: =I35/(1+$E40) -> 0 | J40: =J35/(1+$E40) -> 0 | K40: =K35/(1+$E40) -> 129.71698 | L40: =L35/(1+$E40) -> 0 | M40: =M35/(1+$E40) -> 74.954769 | N40: =N35/(1+$E40) -> 365.56604 | ... BO40: =BO35/(1+$E40) -> 0
A41: 32 | C41: MAA 激励收入一（不含税，万元） | D41: VAT | E41: 0.06 | F41: 0.01 | G41: =G36/(1+$E41) -> 0 | H41: =H36/(1+$E41) -> 0 | I41: =I36/(1+$E41) -> 0 | J41: =J36/(1+$E41) -> 0 | K41: =K36/(1+$E41) -> 0 | L41: =L36/(1+$E41) -> 0 | M41: =M36/(1+$E41) -> 0 | N41: =N36/(1+$E41) -> 0 | ... BO41: =BO36/(1+$E41) -> 0
C42: MAA 激励收入二（不含税，万元） | D42: VAT | E42: 0.06 | F42: 0.02 | G42: =G37/(1+$E42) -> 0 | H42: =H37/(1+$E42) -> 0 | I42: =I37/(1+$E42) -> 0 | J42: =J37/(1+$E42) -> 0 | K42: =K37/(1+$E42) -> 0 | L42: =L37/(1+$E42) -> 0 | M42: =M37/(1+$E42) -> 0 | N42: =N37/(1+$E42) -> 0 | ... BO42: =BO37/(1+$E42) -> 0
A43: 32 | C43: 总MAA收入（不含税，万元） | D43: VAT | E43: 0.06 | G43: =SUM(G40:G42) -> 518.86792 | H43: =SUM(H40:H42) -> 129.71698 | I43: =SUM(I40:I42) -> 0 | J43: =SUM(J40:J42) -> 0 | K43: =SUM(K40:K42) -> 129.71698 | L43: =SUM(L40:L42) -> 0 | M43: =SUM(M40:M42) -> 74.954769 | N43: =SUM(N40:N42) -> 365.56604 | ... BO43: =SUM(BO40:BO42) -> 0
A45: 32 | C45: 运维费用（含税，万元） | D45: 单瓦成本 | E45: 0.06 | F45: =汇总!$D$69 -> 0.035 | G45: =280*(DATE(2025,12,31)-DATE(2024,12,16))/365 -> 291.50685 | H45: =177.33/4*H$4+H$7*$F45*100*(DATE(YEAR(H$3),INT((MONTH(H$3)-1)/3)*3+4,0)-H$3)/365 -> 91.270856 | I45: =177.33/4*I$4+I$7*$F45*100*(DATE(YEAR(I$3),INT((MONTH(I$3)-1)/3)*3+4,0)-I$3)/365 -> 0 | J45: =177.33/4*J$4+J$7*$F45*100*(DATE(YEAR(J$3),INT((MONTH(J$3)-1)/3)*3+4,0)-J$3)/365 -> 0 | K45: =177.33/4*K$4+(K$8-$G$8)*$F45*100/4*K$4+K$7*$F45*100*(DATE(YEAR(K$3),INT((MONTH(K$3)-1)/3)*3+4,0)-K$3)/365 -> 92.4575 | L45: =177.33/4*L$4+(L$8-$G$8)*$F45*100/4*L$4+L$7*$F45*100*(DATE(YEAR(L$3),INT((MONTH(L$3)-1)/3)*3+4,0)-L$3)/365 -> 0 | M45: =177.33/4*M$4+(M$8-$G$8)*$F45*100/4*M$4+M$7*$F45*100*(DATE(YEAR(M$3),INT((MONTH(M$3)-1)/3)*3+4,0)-M$3)/365 -> 27.808219 | N45: =177.33/4*N$4+(N$8-$G$8)*$F45*100/4*N$4+N$7*$F45*100*(DATE(YEAR(N$3),INT((MONTH(N$3)-1)/3)*3+4,0)-N$3)/365 -> 179.9575 | O45: =177.33/4*O$4+(O$8-$G$8)*$F45*100/4*O$4+O$7*$F45*100*(DATE(YEAR(O$3),INT((MONTH(O$3)-1)/3)*3+4,0)-O$3)/365 -> 0 | P45: =177.33/4*P$4+(P$8-$G$8)*$F45*100/4*P$4+P$7*$F45*100*(DATE(YEAR(P$3),INT((MONTH(P$3)-1)/3)*3+4,0)-P$3)/365 -> 0 | Q45: =177.33/4*Q$4+(Q$8-$G$8)*$F45*100/4*Q$4+Q$7*$F45*100*(DATE(YEAR(Q$3),INT((MONTH(Q$3)-1)/3)*3+4,0)-Q$3)/365 -> 179.9575 | R45: =177.33/4*R$4+(R$8-$G$8)*$F45*100/4*R$4+R$7*$F45*100*(DATE(YEAR(R$3),INT((MONTH(R$3)-1)/3)*3+4,0)-R$3)/365 -> 0 | ... AJ45: =177.33/4*AJ$4+(AJ$8-$G$8)*$F45*100/4*AJ$4+AJ$7*$F45*100*(DATE(YEAR(AJ$3),INT((MONTH(AJ$3)-1)/3)*3+4,0)-AJ$3)/365 -> 0 | AK45: =177.33/4*AK$4+(AK$8-$G$8)*$F45*100/4*AK$4+AK$7*$F45*100*(DATE(YEAR(AP$3),INT((MONTH(AP$3)-1)/3)*3+4,0)-AP$3)/365 -> 57.534247 | AL45: =177.33/4*AL$4+(AL$8-$G$8)*$F45*100/4*AL$4+AL$7*$F45*100*(DATE(YEAR(AQ$3),INT((MONTH(AQ$3)-1)/3)*3+4,0)-AQ$3)/365 -> 879.9575 | AM45: =177.33/4*AM$4+(AM$8-$G$8)*$F45*100/4*AM$4+AM$7*$F45*100*(DATE(YEAR(AR$3),INT((MONTH(AR$3)-1)/3)*3+4,0)-AR$3)/365 -> 0 | AN45: =177.33/4*AN$4+(AN$8-$G$8)*$F45*100/4*AN$4+AN$7*$F45*100*(DATE(YEAR(AS$3),INT((MONTH(AS$3)-1)/3)*3+4,0)-AS$3)/365 -> 0 | AO45: =177.33/4*AO$4+(AO$8-$G$8)*$F45*100/4*AO$4+AO$7*$F45*100*(DATE(YEAR(AT$3),INT((MONTH(AT$3)-1)/3)*3+4,0)-AT$3)/365 -> 879.9575 | AP45: =177.33/4*AP$4+(AP$8-$G$8)*$F45*100/4*AP$4+AP$7*$F45*100*(DATE(YEAR(AU$3),INT((MONTH(AU$3)-1)/3)*3+4,0)-AU$3)/365 -> 0 | AQ45: =177.33/4*AQ$4+(AQ$8-$G$8)*$F45*100/4*AQ$4+AQ$7*$F45*100*(DATE(YEAR(AV$3),INT((MONTH(AV$3)-1)/3)*3+4,0)-AV$3)/365 -> 0 | AR45: =177.33/4*AR$4+(AR$8-$G$8)*$F45*100/4*AR$4+AR$7*$F45*100*(DATE(YEAR(AW$3),INT((MONTH(AW$3)-1)/3)*3+4,0)-AW$3)/365 -> 879.9575 | ... BO45: =177.33/4*BO$4+(BO$8-$G$8)*$F45*100/4*BO$4+BO$7*$F45*100*(DATE(YEAR(BT$3),INT((MONTH(BT$3)-1)/3)*3+4,0)-BT$3)/365 -> 0
A46: 32 | C46: 第三方咨询顾问
A47: 32 | C47: 电力交易（含税，万/项目） | D47: VAT | E47: 0.06 | F47: 10 | G47: 10 | H47: =$F47*G$10/4*H$4+$F47*(H$10-G$10)*(DATE(YEAR(H$3),INT((MONTH(H$3)-1)/3)*3+4,0)-H$3)/365*H$5 -> 0 | I47: =$F47*H$10/4*I$4+$F47*(I$10-H$10)*(DATE(YEAR(I$3),INT((MONTH(I$3)-1)/3)*3+4,0)-I$3)/365*I$5 -> 0 | J47: =$F47*I$10/4*J$4+$F47*(J$10-I$10)*(DATE(YEAR(J$3),INT((MONTH(J$3)-1)/3)*3+4,0)-J$3)/365*J$5 -> 0 | K47: =$F47*J$10/4*K$4+$F47*(K$10-J$10)*(DATE(YEAR(K$3),INT((MONTH(K$3)-1)/3)*3+4,0)-K$3)/365*K$5 -> 2.5 | L47: =$F47*K$10/4*L$4+$F47*(L$10-K$10)*(DATE(YEAR(L$3),INT((MONTH(L$3)-1)/3)*3+4,0)-L$3)/365*L$5 -> 0 | M47: =$F47*L$10/4*M$4+$F47*(M$10-L$10)*(DATE(YEAR(M$3),INT((MONTH(M$3)-1)/3)*3+4,0)-M$3)/365*M$5 -> 0.79452055 | N47: =$F47*M$10/4*N$4+$F47*(N$10-M$10)*(DATE(YEAR(N$3),INT((MONTH(N$3)-1)/3)*3+4,0)-N$3)/365*N$5 -> 5 | O47: =$F47*N$10/4*O$4+$F47*(O$10-N$10)*(DATE(YEAR(O$3),INT((MONTH(O$3)-1)/3)*3+4,0)-O$3)/365*O$5 -> 0 | ... AJ47: =$F47*AI$10/4*AJ$4+$F47*(AJ$10-AI$10)*(DATE(YEAR(AJ$3),INT((MONTH(AJ$3)-1)/3)*3+4,0)-AJ$3)/365*AJ$5 -> 0 | AK47: =$F47*AJ$10/4*AK$4+$F47*(AK$10-AJ$10)*(DATE(YEAR(AP$3),INT((MONTH(AP$3)-1)/3)*3+4,0)-AP$3)/365*AK$5 -> 1.6438356 | AL47: =$F47*AK$10/4*AL$4+$F47*(AL$10-AK$10)*(DATE(YEAR(AQ$3),INT((MONTH(AQ$3)-1)/3)*3+4,0)-AQ$3)/365*AL$5 -> 24.285714 | AM47: =$F47*AL$10/4*AM$4+$F47*(AM$10-AL$10)*(DATE(YEAR(AR$3),INT((MONTH(AR$3)-1)/3)*3+4,0)-AR$3)/365*AM$5 -> 0 | AN47: =$F47*AM$10/4*AN$4+$F47*(AN$10-AM$10)*(DATE(YEAR(AS$3),INT((MONTH(AS$3)-1)/3)*3+4,0)-AS$3)/365*AN$5 -> 0 | AO47: =$F47*AN$10/4*AO$4+$F47*(AO$10-AN$10)*(DATE(YEAR(AT$3),INT((MONTH(AT$3)-1)/3)*3+4,0)-AT$3)/365*AO$5 -> 24.285714 | AP47: =$F47*AO$10/4*AP$4+$F47*(AP$10-AO$10)*(DATE(YEAR(AU$3),INT((MONTH(AU$3)-1)/3)*3+4,0)-AU$3)/365*AP$5 -> 0 | AQ47: =$F47*AP$10/4*AQ$4+$F47*(AQ$10-AP$10)*(DATE(YEAR(AV$3),INT((MONTH(AV$3)-1)/3)*3+4,0)-AV$3)/365*AQ$5 -> 0 | AR47: =$F47*AQ$10/4*AR$4+$F47*(AR$10-AQ$10)*(DATE(YEAR(AW$3),INT((MONTH(AW$3)-1)/3)*3+4,0)-AW$3)/365*AR$5 -> 24.285714 | ... BO47: =$F47*BN$10/4*BO$4+$F47*(BO$10-BN$10)*(DATE(YEAR(BT$3),INT((MONTH(BT$3)-1)/3)*3+4,0)-BT$3)/365*BO$5 -> 0
C48: 电力研究数据库（含税，万/年） | D48: VAT | E48: 0.06 | F48: 25 | G48: 0 | H48: =$F$48/4*H$4 -> 6.25 | I48: =$F$48/4*I$4 -> 0 | J48: =$F$48/4*J$4 -> 0 | K48: =$F$48/4*K$4 -> 6.25 | L48: =$F$48/4*L$4 -> 0 | M48: =$F$48/4*M$4 -> 0 | N48: =$F$48/4*N$4 -> 6.25 | O48: =$F$48/4*O$4 -> 0 | ... BO48: =$F$48/4*BO$4 -> 0
C49: 监控系统服务软件开发（含税，万/项目） | D49: VAT | E49: 0.06 | F49: 10 | G49: 0 | H49: =$F49*H$10/4*H$4 -> 2.5 | I49: =$F49*I$10/4*I$4 -> 0 | J49: =$F49*J$10/4*J$4 -> 0 | K49: =$F49*K$10/4*K$4 -> 2.5 | L49: =$F49*L$10/4*L$4 -> 0 | M49: =$F49*M$10/4*M$4 -> 0 | N49: =$F49*N$10/4*N$4 -> 5 | O49: =$F49*O$10/4*O$4 -> 0 | ... BO49: =$F49*BO$10/4*BO$4 -> 0
C50: 发电能力（EBA）归因分析（含税，万/项目） | D50: VAT | E50: 0.06 | F50: 0 | G50: 0 | H50: =$F50*H$10/4*H$4 -> 0 | I50: =$F50*I$10/4*I$4 -> 0 | J50: =$F50*J$10/4*J$4 -> 0 | K50: =$F50*K$10/4*K$4 -> 0 | L50: =$F50*L$10/4*L$4 -> 0 | M50: =$F50*M$10/4*M$4 -> 0 | N50: =$F50*N$10/4*N$4 -> 0 | O50: =$F50*O$10/4*O$4 -> 0 | ... BO50: =$F50*BO$10/4*BO$4 -> 0
A51: 32 | C51: 项目公司财务经办人员工资及五险一金（含税，万/年） | D51: VAT | E51: 0 | F51: 20 | G51: =F51 -> 20 | H51: =$F$51/12*H$11 -> 1.6666667 | I51: =$F$51/12*I$11 -> 1.6666667 | J51: =$F$51/12*J$11 -> 1.6666667 | K51: =$F$51/12*K$11 -> 1.6666667 | L51: =$F$51/12*L$11 -> 1.6666667 | M51: =$F$51/12*M$11 -> 3.3333333 | N51: =$F$51/12*N$11 -> 3.3333333 | O51: =$F$51/12*O$11 -> 3.3333333 | ... BO51: =$F$51/12*BO$11 -> 6.6666667
C52: 会计服务费（含税，万/年/项目） | D52: VAT | E52: 0.01 | F52: =4000*12/10000 -> 4.8 | G52: =F52 -> 4.8 | H52: =$F$52/12*H10 -> 0.4 | I52: =$F$52/12*I10 -> 0.4 | J52: =$F$52/12*J10 -> 0.4 | K52: =$F$52/12*K10 -> 0.4 | L52: =$F$52/12*L10 -> 0.4 | M52: =$F$52/12*M10 -> 0.8 | N52: =$F$52/12*N10 -> 0.8 | O52: =$F$52/12*O10 -> 0.8 | ... BO52: =$F$52/12*BO10 -> 3.8857143
C53: 人力资源服务费（含税，万/年/项目） | D53: VAT | E53: 0.01 | F53: =500*12/10000 -> 0.6 | G53: =F53 -> 0.6 | H53: =$F$53/12*H10 -> 0.05 | I53: =$F$53/12*I10 -> 0.05 | J53: =$F$53/12*J10 -> 0.05 | K53: =$F$53/12*K10 -> 0.05 | L53: =$F$53/12*L10 -> 0.05 | M53: =$F$53/12*M10 -> 0.1 | N53: =$F$53/12*N10 -> 0.1 | O53: =$F$53/12*O10 -> 0.1 | ... BO53: =$F$53/12*BO10 -> 0.48571429
C54: 办公用品，差旅，其他（含税，万/年/项目） | D54: VAT | E54: 0 | F54: 1 | G54: =F54 -> 1 | H54: =$F$54/12*H10 -> 0.083333333 | I54: =$F$54/12*I10 -> 0.083333333 | J54: =$F$54/12*J10 -> 0.083333333 | K54: =$F$54/12*K10 -> 0.083333333 | L54: =$F$54/12*L10 -> 0.083333333 | M54: =$F$54/12*M10 -> 0.16666667 | N54: =$F$54/12*N10 -> 0.16666667 | O54: =$F$54/12*O10 -> 0.16666667 | ... BO54: =$F$54/12*BO10 -> 0.80952381
C55: 其他费用合计（含税，万元） | G55: =SUM(G46:G54) -> 36.4 | H55: =SUM(H46:H54) -> 10.95 | I55: =SUM(I46:I54) -> 2.2 | J55: =SUM(J46:J54) -> 2.2 | K55: =SUM(K46:K54) -> 13.45 | L55: =SUM(L46:L54) -> 2.2 | M55: =SUM(M46:M54) -> 5.1945205 | N55: =SUM(N46:N54) -> 20.65 | ... BO55: =SUM(BO46:BO54) -> 11.847619
C56: 总费用（含税，万元) | G56: =SUM(G45,G55) -> 327.90685 | H56: =SUM(H45,H55) -> 102.22086 | I56: =SUM(I45,I55) -> 2.2 | J56: =SUM(J45,J55) -> 2.2 | K56: =SUM(K45,K55) -> 105.9075 | L56: =SUM(L45,L55) -> 2.2 | M56: =SUM(M45,M55) -> 33.00274 | N56: =SUM(N45,N55) -> 200.6075 | ... BO56: =SUM(BO45,BO55) -> 11.847619
A58: 32 | C58: 运维费用（不含税，万元） | D58: 单瓦成本 | E58: 0.06 | F58: 0.04 | G58: =G45/(1+$E58) -> 275.00646 | H58: =H45/(1+$E58) -> 86.104581 | I58: =I45/(1+$E58) -> 0 | J58: =J45/(1+$E58) -> 0 | K58: =K45/(1+$E58) -> 87.224057 | L58: =L45/(1+$E58) -> 0 | M58: =M45/(1+$E58) -> 26.234169 | N58: =N45/(1+$E58) -> 169.77123 | ... BO58: =BO45/(1+$E58) -> 0
A59: 32 | C59: 第三方咨询顾问
A60: 32 | C60: 电力交易（不含税，万/项目） | D60: VAT | E60: 0.06 | F60: 10 | G60: =G47/(1+$E60) -> 9.4339623 | H60: =H47/(1+$E60) -> 0 | I60: =I47/(1+$E60) -> 0 | J60: =J47/(1+$E60) -> 0 | K60: =K47/(1+$E60) -> 2.3584906 | L60: =L47/(1+$E60) -> 0 | M60: =M47/(1+$E60) -> 0.74954769 | N60: =N47/(1+$E60) -> 4.7169811 | ... BO60: =BO47/(1+$E60) -> 0
C61: 电力研究数据库（不含税，万/年） | D61: VAT | E61: 0.06 | F61: 25 | G61: =G48/(1+$E61) -> 0 | H61: =H48/(1+$E61) -> 5.8962264 | I61: =I48/(1+$E61) -> 0 | J61: =J48/(1+$E61) -> 0 | K61: =K48/(1+$E61) -> 5.8962264 | L61: =L48/(1+$E61) -> 0 | M61: =M48/(1+$E61) -> 0 | N61: =N48/(1+$E61) -> 5.8962264 | ... BO61: =BO48/(1+$E61) -> 0
C62: 监控系统服务软件开发（不含税，万/项目） | D62: VAT | E62: 0.06 | F62: 10 | G62: =G49/(1+$E62) -> 0 | H62: =H49/(1+$E62) -> 2.3584906 | I62: =I49/(1+$E62) -> 0 | J62: =J49/(1+$E62) -> 0 | K62: =K49/(1+$E62) -> 2.3584906 | L62: =L49/(1+$E62) -> 0 | M62: =M49/(1+$E62) -> 0 | N62: =N49/(1+$E62) -> 4.7169811 | ... BO62: =BO49/(1+$E62) -> 0
C63: 发电能力（EBA）归因分析（不含税，万/项目） | D63: VAT | E63: 0.06 | F63: 15 | G63: =G50/(1+$E63) -> 0 | H63: =H50/(1+$E63) -> 0 | I63: =I50/(1+$E63) -> 0 | J63: =J50/(1+$E63) -> 0 | K63: =K50/(1+$E63) -> 0 | L63: =L50/(1+$E63) -> 0 | M63: =M50/(1+$E63) -> 0 | N63: =N50/(1+$E63) -> 0 | ... BO63: =BO50/(1+$E63) -> 0
A64: 32 | C64: 项目公司财务经办人员工资及五险一金（不含税，万/年） | D64: VAT | E64: 0 | F64: 20 | G64: =G51/(1+$E64) -> 20 | H64: =H51/(1+$E64) -> 1.6666667 | I64: =I51/(1+$E64) -> 1.6666667 | J64: =J51/(1+$E64) -> 1.6666667 | K64: =K51/(1+$E64) -> 1.6666667 | L64: =L51/(1+$E64) -> 1.6666667 | M64: =M51/(1+$E64) -> 3.3333333 | N64: =N51/(1+$E64) -> 3.3333333 | ... BO64: =BO51/(1+$E64) -> 6.6666667
C65: 会计服务费（不含税，万/年/项目） | D65: VAT | E65: 0.01 | F65: =4000*12/10000 -> 4.8 | G65: =G52/(1+$E65) -> 4.7524752 | H65: =H52/(1+$E65) -> 0.3960396 | I65: =I52/(1+$E65) -> 0.3960396 | J65: =J52/(1+$E65) -> 0.3960396 | K65: =K52/(1+$E65) -> 0.3960396 | L65: =L52/(1+$E65) -> 0.3960396 | M65: =M52/(1+$E65) -> 0.79207921 | N65: =N52/(1+$E65) -> 0.79207921 | ... BO65: =BO52/(1+$E65) -> 3.8472419
C66: 人力资源服务费（不含税，万/年/项目） | D66: VAT | E66: 0.01 | F66: =500*12/10000 -> 0.6 | G66: =G53/(1+$E66) -> 0.59405941 | H66: =H53/(1+$E66) -> 0.04950495 | I66: =I53/(1+$E66) -> 0.04950495 | J66: =J53/(1+$E66) -> 0.04950495 | K66: =K53/(1+$E66) -> 0.04950495 | L66: =L53/(1+$E66) -> 0.04950495 | M66: =M53/(1+$E66) -> 0.099009901 | N66: =N53/(1+$E66) -> 0.099009901 | ... BO66: =BO53/(1+$E66) -> 0.48090523
C67: 办公用品，差旅，其他（不含税，万/年/项目） | D67: VAT | E67: 0 | F67: 1 | G67: =G54/(1+$E67) -> 1 | H67: =H54/(1+$E67) -> 0.083333333 | I67: =I54/(1+$E67) -> 0.083333333 | J67: =J54/(1+$E67) -> 0.083333333 | K67: =K54/(1+$E67) -> 0.083333333 | L67: =L54/(1+$E67) -> 0.083333333 | M67: =M54/(1+$E67) -> 0.16666667 | N67: =N54/(1+$E67) -> 0.16666667 | ... BO67: =BO54/(1+$E67) -> 0.80952381
C68: 其他费用合计（不含税，万元） | G68: =SUM(G59:G67) -> 35.780497 | H68: =SUM(H59:H67) -> 10.450262 | I68: =SUM(I59:I67) -> 2.1955446 | J68: =SUM(J59:J67) -> 2.1955446 | K68: =SUM(K59:K67) -> 12.808752 | L68: =SUM(L59:L67) -> 2.1955446 | M68: =SUM(M59:M67) -> 5.1406368 | N68: =SUM(N59:N67) -> 19.721278 | ... BO68: =SUM(BO59:BO67) -> 11.804338
C69: 总费用（不含税，万元) | G69: =SUM(G58,G68) -> 310.78696 | H69: =SUM(H58,H68) -> 96.554843 | I69: =SUM(I58,I68) -> 2.1955446 | J69: =SUM(J58,J68) -> 2.1955446 | K69: =SUM(K58,K68) -> 100.03281 | L69: =SUM(L58,L68) -> 2.1955446 | M69: =SUM(M58,M68) -> 31.374806 | N69: =SUM(N58,N68) -> 189.4925 | ... BO69: =SUM(BO58,BO68) -> 11.804338
A71: 32 | C71: 基金基础管理费收入（不含VAT，万元） | D71: 扣除IDG 25% CIT | E71: 0.25 | F71: 0.06 | G71: =G20/(1+$F$71)*(1-$E$71) -> 0 | H71: =H20/(1+$F$71)*(1-$E$71) -> 0 | I71: =I20/(1+$F$71)*(1-$E$71) -> 0 | J71: =J20/(1+$F$71)*(1-$E$71) -> 0 | K71: =K20/(1+$F$71)*(1-$E$71) -> 18.214518 | L71: =L20/(1+$F$71)*(1-$E$71) -> 0 | M71: =M20/(1+$F$71)*(1-$E$71) -> 43.792147 | N71: =N20/(1+$F$71)*(1-$E$71) -> 0 | ... BO71: =BO20/(1+$F$71)*(1-$E$71) -> 0
A72: 32 | C72: 基金激励管理费收入（不含VAT，万元） | D72: 扣除IDG 25% CIT | E72: 0.25 | F72: 0.06 | G72: =G21/(1+$F$71)*(1-$E$71) -> 0 | H72: =H21/(1+$F$71)*(1-$E$71) -> 0 | I72: =I21/(1+$F$71)*(1-$E$71) -> 0 | J72: =J21/(1+$F$71)*(1-$E$71) -> 0 | K72: =K21/(1+$F$71)*(1-$E$71) -> 0 | L72: =L21/(1+$F$71)*(1-$E$71) -> 0 | M72: =M21/(1+$F$71)*(1-$E$71) -> 0 | N72: =N21/(1+$F$71)*(1-$E$71) -> 0 | ... BO72: =BO21/(1+$F$71)*(1-$E$71) -> 0
A73: 32 | B73: ACPLSZ | C73: 总基金管理费收入（不含VAT，万元） | K73: =SUM(G71:K72) -> 18.214518 | L73: =SUM(L71:L72) -> 0 | M73: =SUM(M71:M72) -> 43.792147 | N73: =SUM(N71:N72) -> 0 | O73: =SUM(O71:O72) -> 0 | P73: =SUM(P71:P72) -> 0 | Q73: =SUM(Q71:Q72) -> 0 | R73: =SUM(R71:R72) -> 0 | S73: =SUM(S71:S72) -> 24.671632 | ... BO73: =SUM(BO71:BO72) -> 0
A75: 32 | B75: Total | C75: 净MAA收入（不含税，万元） | G75: 0 | H75: 0 | I75: 0 | J75: 0 | L75: =SUM(G43:M43)-SUM(G69:M69) -> 307.92061 | M75: 0 | N75: =SUM(N43:P43)-SUM(N69:P69) -> 167.29136 | O75: 0 | P75: 0 | Q75: =SUM(Q43:S43)-SUM(Q69:S69) -> 362.62083 | R75: 0 | S75: 0 | T75: =SUM(T43:V43)-SUM(T69:V69) -> 752.79976 | U75: 0 | V75: 0 | W75: =SUM(W43:Y43)-SUM(W69:Y69) -> 798.57527 | X75: 0 | Y75: 0 | Z75: =SUM(Z43:AB43)-SUM(Z69:AB69) -> 942.24021 | AA75: 0 | AB75: 0 | AC75: =SUM(AC43:AE43)-SUM(AC69:AE69) -> 1090.8927 | AD75: 0 | AE75: 0 | AF75: =SUM(AF43:AH43)-SUM(AF69:AH69) -> 1188.7946 | AG75: 0 | AH75: 0 | AI75: =SUM(AI43:AK43)-SUM(AI69:AK69) -> 1287.5162 | AJ75: 0 | AK75: 0 | AL75: =SUM(AL43:AN43)-SUM(AL69:AN69) -> 1335.7928 | AM75: 0 | AN75: 0 | AO75: =SUM(AO43:AQ43)-SUM(AO69:AQ69) -> 1335.5548 | AP75: 0 | AQ75: 0 | AR75: =SUM(AR43:AT43)-SUM(AR69:AT69) -> 1335.0786 | AS75: 0 | AT75: 0 | AU75: =SUM(AU43:AW43)-SUM(AU69:AW69) -> 1335.0786 | AV75: 0 | AW75: 0 | AX75: =SUM(AX43:AZ43)-SUM(AX69:AZ69) -> 1335.0786 | AY75: 0 | AZ75: 0 | BA75: =SUM(BA43:BC43)-SUM(BA69:BC69) -> 1335.0786 | BB75: 0 | BC75: 0 | BD75: =SUM(BD43:BF43)-SUM(BD69:BF69) -> 1335.0786 | BE75: 0 | BF75: 0 | BG75: =SUM(BG43:BI43)-SUM(BG69:BI69) -> 1335.0786 | BH75: 0 | BI75: 0 | BJ75: =SUM(BJ43:BL43)-SUM(BJ69:BL69) -> 1335.0786 | BK75: 0 | BL75: 0 | BM75: =SUM(BM43:BO43)-SUM(BM69:BO69) -> 1335.0786 | BN75: 0 | BO75: 0
A76: 32 | B76: ACPLSZ | C76: 净MAA收入（不含税，万元） | F76: 0.75 | G76: 0 | H76: 0 | I76: 0 | J76: 0 | K76: =K75*100% -> 0 | L76: =(G43-G69)+(L75-(G43-G69))*$F$76 -> 282.9607 | M76: =M75*$F$76 -> 0 | N76: =N75*$F$76 -> 125.46852 | O76: =O75*$F$76 -> 0 | P76: =P75*$F$76 -> 0 | Q76: =Q75*$F$76 -> 271.96562 | R76: =R75*$F$76 -> 0 | S76: =S75*$F$76 -> 0 | T76: =T75*$F$76 -> 564.59982 | ... BO76: =BO75*$F$76 -> 0
A77: 32 | B77: ACPLHK | C77: 净MAA收入（不含税，万元） | F77: 0.25 | G77: 0 | H77: 0 | I77: 0 | J77: 0 | K77: 0 | L77: =L75-L76 -> 24.95991 | M77: =M75*$F$77 -> 0 | N77: =N75*$F$77 -> 41.822839 | O77: =O75*$F$77 -> 0 | P77: =P75*$F$77 -> 0 | Q77: =Q75*$F$77 -> 90.655207 | R77: =R75*$F$77 -> 0 | S77: =S75*$F$77 -> 0 | T77: =T75*$F$77 -> 188.19994 | ... BO77: =BO75*$F$77 -> 0
A78: 32 | B78: ACPLHK | C78: 净MAA收入（不含税，万元，扣除5% WHT） | F78: 0.05 | G78: 0 | H78: 0 | I78: 0 | J78: 0 | K78: =K77*(1-$F$78) -> 0 | L78: =L77*(1-$F$78) -> 23.711914 | M78: =M77*(1-$F$78) -> 0 | N78: =N77*(1-$F$78) -> 39.731697 | O78: =O77*(1-$F$78) -> 0 | P78: =P77*(1-$F$78) -> 0 | Q78: =Q77*(1-$F$78) -> 86.122446 | R78: =R77*(1-$F$78) -> 0 | ... BO78: =BO77*(1-$F$78) -> 0
AE81: =3500+1600 -> 5100
AE82: 3100
AE83: 2000

Sheet 情形2
C2: 1 | D2: 2 | F2: 3 | G2: 18 | H2: 19 | I2: 20 | J2: 21 | K2: 22 | L2: 23 | M2: 24 | N2: 25 | O2: 26 | P2: 27 | Q2: 28 | R2: 29 | S2: 30 | T2: 31 | U2: 32 | V2: 33 | W2: 34 | X2: 35 | Y2: 36 | Z2: 37 | AA2: 38 | AB2: 39 | AC2: 40 | AD2: 41 | AE2: 42 | AF2: 43 | AG2: 44 | AH2: 45 | AI2: 46 | AJ2: 47 | AK2: 48
A3: 1 | G3: 45992 | H3: 46023 | I3: 46054 | J3: 46082 | K3: 46113 | L3: 46143 | M3: 46174 | N3: 46204 | O3: 46235 | P3: 46266 | Q3: 46296 | R3: 46327 | S3: 46357 | T3: 46388 | U3: 46419 | V3: 46447 | W3: 46478 | X3: 46508 | Y3: 46539 | Z3: 46569 | AA3: 46600 | AB3: 46631 | AC3: 46661 | AD3: 46692 | AE3: 46722 | AF3: 46753 | AG3: 46784 | AH3: 46813 | AI3: 46844 | AJ3: 46874 | AK3: 46905 | AL3: 46935 | AM3: 46966 | AN3: 46997 | AO3: 47027 | AP3: 47058 | AQ3: 47088 | AR3: 47119 | AS3: 47150 | AT3: 47178 | AU3: 47209 | AV3: 47239 | AW3: 47270 | AX3: 47300 | AY3: 47331 | AZ3: 47362 | BA3: 47392 | BB3: 47423 | BC3: 47453 | BD3: 47484 | BE3: 47515 | BF3: 47543 | BG3: 47574 | BH3: 47604 | BI3: 47635 | BJ3: 47665 | BK3: 47696 | BL3: 47727 | BM3: 47757 | BN3: 47788 | BO3: 47818
C4: MAA季度管理费支付期间 | H4: 1 | I4: 0 | J4: 0 | K4: 1 | L4: 0 | M4: 0 | N4: 1 | O4: 0 | P4: 0 | Q4: 1 | R4: 0 | S4: 0 | T4: 1 | U4: 0 | V4: 0 | W4: 1 | X4: 0 | Y4: 0 | Z4: 1 | AA4: 0 | AB4: 0 | AC4: 1 | AD4: 0 | AE4: 0 | AF4: 1 | AG4: 0 | AH4: 0 | AI4: 1 | AJ4: 0 | AK4: 0 | AL4: 1 | AM4: 0 | AN4: 0 | AO4: 1 | AP4: 0 | AQ4: 0 | AR4: 1 | AS4: 0 | AT4: 0 | AU4: 1 | AV4: 0 | AW4: 0 | AX4: 1 | AY4: 0 | AZ4: 0 | BA4: 1 | BB4: 0 | BC4: 0 | BD4: 1 | BE4: 0 | BF4: 0 | BG4: 1 | BH4: 0 | BI4: 0 | BJ4: 1 | BK4: 0 | BL4: 0 | BM4: 1 | BN4: 0 | BO4: 0 | BP4: 1 | BQ4: 0 | BR4: 0 | BS4: 1 | BT4: 0 | BU4: 0
A5: 2 | C5: MAA新增资本管理费支付期间 | H5: 0 | I5: 1 | J5: 1 | K5: 0 | L5: 1 | M5: 1 | N5: 0 | O5: 1 | P5: 1 | Q5: 0 | R5: 1 | S5: 1 | T5: 0 | U5: 1 | V5: 1 | W5: 0 | X5: 1 | Y5: 1 | Z5: 0 | AA5: 1 | AB5: 1 | AC5: 0 | AD5: 1 | AE5: 1 | AF5: 0 | AG5: 1 | AH5: 1 | AI5: 0 | AJ5: 1 | AK5: 1 | AL5: 0 | AM5: 1 | AN5: 1 | AO5: 0 | AP5: 1 | AQ5: 1 | AR5: 0 | AS5: 1 | AT5: 1 | AU5: 0 | AV5: 1 | AW5: 1 | AX5: 0 | AY5: 1 | AZ5: 1 | BA5: 0 | BB5: 1 | BC5: 1 | BD5: 0 | BE5: 1 | BF5: 1 | BG5: 0 | BH5: 1 | BI5: 1 | BJ5: 0 | BK5: 1 | BL5: 1 | BM5: 0 | BN5: 1 | BO5: 1 | BP5: 0 | BQ5: 1 | BR5: 1 | BS5: 0 | BT5: 1 | BU5: 1
C6: 天数 | H6: =DAY(EOMONTH(H3,0)) -> 31 | I6: =DAY(EOMONTH(I3,0)) -> 28 | J6: =DAY(EOMONTH(J3,0)) -> 31 | K6: =DAY(EOMONTH(K3,0)) -> 30 | L6: =DAY(EOMONTH(L3,0)) -> 31 | M6: =DAY(EOMONTH(M3,0)) -> 30 | N6: =DAY(EOMONTH(N3,0)) -> 31 | O6: =DAY(EOMONTH(O3,0)) -> 31 | ... BU6: =DAY(EOMONTH(BU3,0)) -> 31
C7: 新增装机（MW） | H7: 55 | I7: 0 | J7: =汇总!M39 -> 0 | K7: 0 | L7: 0 | M7: =汇总!M40 -> 0 | P7: =汇总!M41 -> 150 | S7: =汇总!M42 -> 150 | V7: =汇总!M47 -> 50 | Y7: =汇总!M48 -> 100 | AB7: =汇总!M49 -> 50 | AE7: =汇总!M50 -> 100 | AH7: =汇总!M55 -> 0 | AK7: =汇总!M56 -> 150 | AN7: =汇总!M57 -> 0 | AQ7: =汇总!M58 -> 150 | AZ7: =汇总!AF49 -> 0 | BC7: =汇总!AF50 -> 0 | BL7: =汇总!AR49 -> 0 | BO7: =汇总!AR50 -> 0
C8: 累计装机（MW） | G8: =G7 -> 0 | H8: =G8+H7 -> 55 | I8: =H8+I7 -> 55 | J8: =I8+J7 -> 55 | K8: =J8+K7 -> 55 | L8: =K8+L7 -> 55 | M8: =L8+M7 -> 55 | N8: =M8+N7 -> 55 | O8: =N8+O7 -> 55 | ... BU8: =BT8+BU7 -> 955
C9: 累计装机（MW）- annual cumulative average | S9: =SUMPRODUCT($H$8:S8,$H$6:S6)/365 -> 117.87671 | AE9: =SUMPRODUCT($T$8:AE8,$T$6:AE6)/365 -> 480.75342 | AQ9: =SUMPRODUCT($AF$8:AQ8,$AF$6:AQ6)/365 -> 757.47945 | BC9: =SUMPRODUCT($H$8:BC8,$H$6:BC6)/365 -> 2311.1096 | BO9: =SUMPRODUCT($H$8:BO8,$H$6:BO6)/365 -> 3266.1096
C10: 项目数量 | H10: {=G10+_xlfn.IFS(H7=0,0,H7<=100,1,H7<=200,2)} -> 1 | I10: {=H10+_xlfn.IFS(I7=0,0,I7<=100,1,I7<=200,2)} -> 1 | J10: {=I10+_xlfn.IFS(J7=0,0,J7<=100,1,J7<=200,2)} -> 1 | K10: {=J10+_xlfn.IFS(K7=0,0,K7<=100,1,K7<=200,2)} -> 1 | L10: {=K10+_xlfn.IFS(L7=0,0,L7<=100,1,L7<=200,2)} -> 1 | M10: {=L10+_xlfn.IFS(M7=0,0,M7<=100,1,M7<=200,2)} -> 1 | N10: {=M10+_xlfn.IFS(N7=0,0,N7<=100,1,N7<=200,2)} -> 1 | O10: {=N10+_xlfn.IFS(O7=0,0,O7<=100,1,O7<=200,2)} -> 1 | ... BU10: {=BT10+_xlfn.IFS(BU7=0,0,BU7<=100,1,BU7<=200,2)} -> 13
C11: 区域数量 | G11: =G10 -> 0 | H11: =H10 -> 1 | I11: =I10 -> 1 | J11: =J10 -> 1 | K11: =K10 -> 1 | L11: =L10 -> 1 | M11: =M10 -> 1 | N11: =M11 -> 1 | O11: =N11 -> 1 | P11: =O11 -> 1 | Q11: =Q10 -> 3 | R11: =Q11 -> 3 | S11: =R11 -> 3 | T11: =S11 -> 3 | U11: =T11 -> 3 | V11: =U11 -> 3 | W11: =V11 -> 3 | X11: =W11 -> 3 | Y11: =X11+1 -> 4 | Z11: =Y11 -> 4 | AA11: =Z11 -> 4 | AB11: =AA11 -> 4 | AC11: =AB11 -> 4 | AD11: =AC11 -> 4 | AE11: =AD11 -> 4 | AF11: =AE11 -> 4 | AG11: =AF11 -> 4 | ... BU11: =BT11 -> 4
C12: 平均单瓦股权价格（元/W) | F12: =汇总!$M$64 -> 2 | H12: =$F$12 -> 2 | I12: =$F$12 -> 2 | J12: =$F$12 -> 2 | K12: =$F$12 -> 2 | L12: =$F$12 -> 2 | M12: =$F$12 -> 2 | N12: =$F$12 -> 2 | O12: =$F$12 -> 2 | ... BU12: =$F$12 -> 2
C13: JV股权新增出资额（万元） | G13: 0 | H13: 0 | I13: =+I7*I12*100 -> 0 | J13: =+J7*J12*100 -> 0 | K13: =+K7*K12*100 -> 0 | L13: =+L7*L12*100 -> 0 | M13: =+M7*M12*100 -> 0 | N13: =+N7*N12*100 -> 0 | O13: =+O7*O12*100 -> 0 | P13: =+P7*P12*100 -> 30000 | ... BU13: =+BU7*BU12*100 -> 0
C14: JV股权累计出资额（万元） | G14: =8700 -> 8700 | H14: =G14+H13 -> 8700 | I14: =H14+I13 -> 8700 | J14: =I14+J13 -> 8700 | K14: =J14+K13 -> 8700 | L14: =K14+L13 -> 8700 | M14: =L14+M13 -> 8700 | N14: =M14+N13 -> 8700 | O14: =N14+O13 -> 8700 | ... BU14: =BT14+BU13 -> 188700
C16: 基金股权新增出资额（万元） | F16: 0.75 | G16: =G13*$F$16 -> 0 | H16: =H13*$F$16 -> 0 | I16: =I13*$F$16 -> 0 | J16: =J13*$F$16 -> 0 | K16: =K14*50% -> 4350 | L16: =L13*$F$16 -> 0 | M16: =M13*$F$16 -> 0 | N16: =N13*$F$16 -> 0 | O16: =O13*$F$16 -> 0 | P16: =P13*$F$16 -> 22500 | Q16: =Q13*$F$16 -> 0 | R16: =R13*$F$16 -> 0 | S16: =S13*$F$16 -> 22500 | ... BU16: =BU13*$F$16 -> 0
C17: 基金股权累计出资额（万元） | F17: 0.75 | G17: =G16 -> 0 | H17: =G17+H16 -> 0 | I17: =H17+I16 -> 0 | J17: =I17+J16 -> 0 | K17: =J17+K16 -> 4350 | L17: =K17+L16 -> 4350 | M17: =L17+M16 -> 4350 | N17: =M17+N16 -> 4350 | O17: =N17+O16 -> 4350 | ... BU17: =BT17+BU16 -> 139350
A18: 8 | C18: 基金费用新增出资额（万元） | G18: 0 | H18: 0 | I18: 0 | J18: 0 | K18: 500 | L18: 0 | M18: 0 | N18: 0 | O18: 0 | P18: 0 | Q18: 0 | R18: 0 | S18: 0 | T18: 200 | U18: 0 | V18: 0 | W18: 0 | X18: 0 | Y18: 0 | Z18: 0 | AA18: 0 | AB18: 0 | AC18: 0 | AD18: 0 | AE18: 0 | AF18: 200 | AG18: 0 | AH18: 0 | AI18: 0 | AJ18: 0 | AK18: 0 | AL18: 0 | AM18: 0 | AN18: 0 | AO18: 0 | AP18: 0 | AQ18: 0 | AR18: 200 | AS18: 0 | AT18: 0 | AU18: 0 | AV18: 0 | AW18: 0 | AX18: 0 | AY18: 0 | AZ18: 0 | BA18: 0 | BB18: 0 | BC18: 0 | BD18: 200 | BE18: 0 | BF18: 0 | BG18: 0 | BH18: 0 | BI18: 0 | BJ18: 0 | BK18: 0 | BL18: 0 | BM18: 0 | BN18: 0 | BO18: 0 | BP18: 200 | BQ18: 0 | BR18: 0 | BS18: 0 | BT18: 0 | BU18: 0
A19: 8 | C19: 基金费用累计出资额（万元） | G19: =G18 -> 0 | H19: =G19+H18 -> 0 | I19: =H19+I18 -> 0 | J19: =I19+J18 -> 0 | K19: =J19+K18 -> 500 | L19: =K19+L18 -> 500 | M19: =L19+M18 -> 500 | N19: =M19+N18 -> 500 | O19: =N19+O18 -> 500 | ... BU19: =BT19+BU18 -> 1500
A20: 8 | C20: 基金基础管理费出资额（含税，万元） | F20: 0.7 | G20: =(G$17+G$19)/99%*1%*(DATE(YEAR(G$3),12,31)-G$3)/365 -> 0 | H20: =(H$17+H$19)/99%*1%*(DATE(YEAR(H$3),12,31)-H$3)/365*$F$20 -> 0 | I20: =(I$16+I$18)/99%*1%*(DATE(YEAR(I$3),12,31)-I$3)/365*$F$20 -> 0 | J20: =(J$16+J$18)/99%*1%*(DATE(YEAR(J$3),12,31)-J$3)/365*$F$20 -> 0 | K20: =(K$16+K$18)/99%*1%*(DATE(YEAR(K$3),12,31)-K$3)/365*$F$20 -> 25.743185 | L20: =(L$16+L$18)/99%*1%*(DATE(YEAR(L$3),12,31)-L$3)/365*$F$20 -> 0 | M20: =(M$16+M$18)/99%*1%*(DATE(YEAR(M$3),12,31)-M$3)/365*$F$20 -> 0 | N20: =(N$16+N$18)/99%*1%*(DATE(YEAR(N$3),12,31)-N$3)/365*$F$20 -> 0 | O20: =(O$16+O$18)/99%*1%*(DATE(YEAR(O$3),12,31)-O$3)/365*$F$20 -> 0 | P20: =(P$16+P$18)/99%*1%*(DATE(YEAR(P$3),12,31)-P$3)/365*$F$20 -> 52.739726 | ... S20: =(S$16+S$18)/99%*1%*(DATE(YEAR(S$3),12,31)-S$3)/365*$F$20 -> 13.075965 | T20: =(T$17+T$19)/99%*1%*(DATE(YEAR(T$3),12,31)-T$3)/365*$F$20 -> 352.91933 | U20: =U$16/99%*1%*(DATE(YEAR(U$3),12,31)-U$3)/365*$F$20 -> 0 | V20: =V$16/99%*1%*(DATE(YEAR(V$3),12,31)-V$3)/365*$F$20 -> 44.312993 | W20: =W$16/99%*1%*(DATE(YEAR(W$3),12,31)-W$3)/365*$F$20 -> 0 | X20: =X$16/99%*1%*(DATE(YEAR(X$3),12,31)-X$3)/365*$F$20 -> 0 | Y20: =Y$16/99%*1%*(DATE(YEAR(Y$3),12,31)-Y$3)/365*$F$20 -> 61.892902 | Z20: =Z$16/99%*1%*(DATE(YEAR(Z$3),12,31)-Z$3)/365*$F$20 -> 0 | AA20: =AA$16/99%*1%*(DATE(YEAR(AA$3),12,31)-AA$3)/365*$F$20 -> 0 | AB20: =AB$16/99%*1%*(DATE(YEAR(AB$3),12,31)-AB$3)/365*$F$20 -> 17.579909 | ... AE20: =AE$16/99%*1%*(DATE(YEAR(AE$3),12,31)-AE$3)/365*$F$20 -> 8.7173101 | AF20: =AF$17/99%*1%*(DATE(YEAR(AF$3),12,31)-AF$3)/365*$F$20 -> 667.12121 | AG20: =AG$16/99%*1%*(DATE(YEAR(AG$3),12,31)-AG$3)/365*$F$20 -> 0 | AH20: =AH$16/99%*1%*(DATE(YEAR(AH$3),12,31)-AH$3)/365*$F$20 -> 0 | AI20: =AI$16/99%*1%*(DATE(YEAR(AI$3),12,31)-AI$3)/365*$F$20 -> 0 | AJ20: =AJ$16/99%*1%*(DATE(YEAR(AJ$3),12,31)-AJ$3)/365*$F$20 -> 0 | AK20: =AK$16/99%*1%*(DATE(YEAR(AK$3),12,31)-AK$3)/365*$F$20 -> 92.839352 | AL20: =AL$16/99%*1%*(DATE(YEAR(AL$3),12,31)-AL$3)/365*$F$20 -> 0 | AM20: =AM$16/99%*1%*(DATE(YEAR(AM$3),12,31)-AM$3)/365*$F$20 -> 0 | AN20: =AN$16/99%*1%*(DATE(YEAR(AN$3),12,31)-AN$3)/365*$F$20 -> 0 | ... AQ20: =AQ$16/99%*1%*(DATE(YEAR(AQ$3),12,31)-AQ$3)/365*$F$20 -> 13.075965 | AR20: =AR$17/99%*1%*(DATE(YEAR(AR$3),12,31)-AR$3)/365*$F$20 -> 982.60357 | AS20: =AS$16/99%*1%*(DATE(YEAR(AS$3),12,31)-AS$3)/365*$F$20 -> 0 | AT20: =AT$16/99%*1%*(DATE(YEAR(AT$3),12,31)-AT$3)/365*$F$20 -> 0 | AU20: =AU$16/99%*1%*(DATE(YEAR(AU$3),12,31)-AU$3)/365*$F$20 -> 0 | AV20: =AV$16/99%*1%*(DATE(YEAR(AV$3),12,31)-AV$3)/365*$F$20 -> 0 | AW20: =AW$16/99%*1%*(DATE(YEAR(AW$3),12,31)-AW$3)/365*$F$20 -> 0 | AX20: =AX$16/99%*1%*(DATE(YEAR(AX$3),12,31)-AX$3)/365*$F$20 -> 0 | AY20: =AY$16/99%*1%*(DATE(YEAR(AY$3),12,31)-AY$3)/365*$F$20 -> 0 | AZ20: =AZ$16/99%*1%*(DATE(YEAR(AZ$3),12,31)-AZ$3)/365*$F$20 -> 0 | ... BC20: =BC$16/99%*1%*(DATE(YEAR(BC$3),12,31)-BC$3)/365*$F$20 -> 0 | BD20: =BD$17/99%*1%*(DATE(YEAR(BD$3),12,31)-BD$3)/365*$F$20 -> 982.60357 | BE20: =BE$16/99%*1%*(DATE(YEAR(BE$3),12,31)-BE$3)/365*$F$20 -> 0 | BF20: =BF$16/99%*1%*(DATE(YEAR(BF$3),12,31)-BF$3)/365*$F$20 -> 0 | BG20: =BG$16/99%*1%*(DATE(YEAR(BG$3),12,31)-BG$3)/365*$F$20 -> 0 | BH20: =BH$16/99%*1%*(DATE(YEAR(BH$3),12,31)-BH$3)/365*$F$20 -> 0 | BI20: =BI$16/99%*1%*(DATE(YEAR(BI$3),12,31)-BI$3)/365*$F$20 -> 0 | BJ20: =BJ$16/99%*1%*(DATE(YEAR(BJ$3),12,31)-BJ$3)/365*$F$20 -> 0 | BK20: =BK$16/99%*1%*(DATE(YEAR(BK$3),12,31)-BK$3)/365*$F$20 -> 0 | BL20: =BL$16/99%*1%*(DATE(YEAR(BL$3),12,31)-BL$3)/365*$F$20 -> 0 | ... BO20: =BO$16/99%*1%*(DATE(YEAR(BO$3),12,31)-BO$3)/365*$F$20 -> 0 | BP20: =BP$17/99%*1%*(DATE(YEAR(BP$3),12,31)-BP$3)/365*$F$20 -> 988.00249 | BQ20: =BQ$16/99%*1%*(DATE(YEAR(BQ$3),12,31)-BQ$3)/365*$F$20 -> 0 | BR20: =BR$16/99%*1%*(DATE(YEAR(BR$3),12,31)-BR$3)/365*$F$20 -> 0 | BS20: =BS$16/99%*1%*(DATE(YEAR(BS$3),12,31)-BS$3)/365*$F$20 -> 0 | BT20: =BT$16/99%*1%*(DATE(YEAR(BT$3),12,31)-BT$3)/365*$F$20 -> 0 | BU20: =BU$16/99%*1%*(DATE(YEAR(BU$3),12,31)-BU$3)/365*$F$20 -> 0
A21: 8 | C21: 基金激励管理费出资额（含税，万元） | D21: “1”为支付，"0"为不支付 | E21: =汇总!N65 -> 0 | F21: 0.3 | G21: 0 | H21: =(H$17+H$19)/99%*1%*(DATE(YEAR(H$3),12,31)-H$3)/365*$F$21*$E$21 -> 0 | I21: =(I$16+I$18)/99%*1%*(DATE(YEAR(I$3),12,31)-I$3)/365*$F$21*$E$21 -> 0 | J21: =(J$16+J$18)/99%*1%*(DATE(YEAR(J$3),12,31)-J$3)/365*$F$21*$E$21 -> 0 | K21: =(K$16+K$18)/99%*1%*(DATE(YEAR(K$3),12,31)-K$3)/365*$F$21*$E$21 -> 0 | L21: =(L$16+L$18)/99%*1%*(DATE(YEAR(L$3),12,31)-L$3)/365*$F$21*$E$21 -> 0 | M21: =(M$16+M$18)/99%*1%*(DATE(YEAR(M$3),12,31)-M$3)/365*$F$21*$E$21 -> 0 | N21: =(N$16+N$18)/99%*1%*(DATE(YEAR(N$3),12,31)-N$3)/365*$F$21*$E$21 -> 0 | O21: =(O$16+O$18)/99%*1%*(DATE(YEAR(O$3),12,31)-O$3)/365*$F$21*$E$21 -> 0 | P21: =(P$16+P$18)/99%*1%*(DATE(YEAR(P$3),12,31)-P$3)/365*$F$21*$E$21 -> 0 | ... S21: =(S$16+S$18)/99%*1%*(DATE(YEAR(S$3),12,31)-S$3)/365*$F$21*$E$21 -> 0 | T21: =(T$17+T$19)/99%*1%*(DATE(YEAR(T$3),12,31)-T$3)/365*$F$21*$E$21 -> 0 | U21: =(U$16+U$18)/99%*1%*(DATE(YEAR(U$3),12,31)-U$3)/365*$F$21*$E$21 -> 0 | V21: =(V$16+V$18)/99%*1%*(DATE(YEAR(V$3),12,31)-V$3)/365*$F$21*$E$21 -> 0 | W21: =(W$16+W$18)/99%*1%*(DATE(YEAR(W$3),12,31)-W$3)/365*$F$21*$E$21 -> 0 | X21: =(X$16+X$18)/99%*1%*(DATE(YEAR(X$3),12,31)-X$3)/365*$F$21*$E$21 -> 0 | Y21: =(Y$16+Y$18)/99%*1%*(DATE(YEAR(Y$3),12,31)-Y$3)/365*$F$21*$E$21 -> 0 | Z21: =(Z$16+Z$18)/99%*1%*(DATE(YEAR(Z$3),12,31)-Z$3)/365*$F$21*$E$21 -> 0 | AA21: =(AA$16+AA$18)/99%*1%*(DATE(YEAR(AA$3),12,31)-AA$3)/365*$F$21*$E$21 -> 0 | AB21: =(AB$16+AB$18)/99%*1%*(DATE(YEAR(AB$3),12,31)-AB$3)/365*$F$21*$E$21 -> 0 | ... AE21: =(AE$16+AE$18)/99%*1%*(DATE(YEAR(AE$3),12,31)-AE$3)/365*$F$21*$E$21 -> 0 | AF21: =(AF$17+AF$19)/99%*1%*(DATE(YEAR(AF$3),12,31)-AF$3)/365*$F$21*$E21 -> 0 | AG21: =AG$16/99%*1%*(DATE(YEAR(AG$3),12,31)-AG$3)/365*$F$21 -> 0 | AH21: =AH$16/99%*1%*(DATE(YEAR(AH$3),12,31)-AH$3)/365*$F$21 -> 0 | AI21: =AI$16/99%*1%*(DATE(YEAR(AI$3),12,31)-AI$3)/365*$F$21 -> 0 | AJ21: =AJ$16/99%*1%*(DATE(YEAR(AJ$3),12,31)-AJ$3)/365*$F$21 -> 0 | AK21: =(AK$16+AK$18)/99%*1%*(DATE(YEAR(AK$3),12,31)-AK$3)/365*$F$21*$E$21 -> 0 | AL21: =(AL$16+AL$18)/99%*1%*(DATE(YEAR(AL$3),12,31)-AL$3)/365*$F$21*$E$21 -> 0 | AM21: =(AM$16+AM$18)/99%*1%*(DATE(YEAR(AM$3),12,31)-AM$3)/365*$F$21*$E$21 -> 0 | AN21: =(AN$16+AN$18)/99%*1%*(DATE(YEAR(AN$3),12,31)-AN$3)/365*$F$21*$E$21 -> 0 | AO21: =(AO$16+AO$18)/99%*1%*(DATE(YEAR(AO$3),12,31)-AO$3)/365*$F$21*$E$21 -> 0 | AP21: =(AP$16+AP$18)/99%*1%*(DATE(YEAR(AP$3),12,31)-AP$3)/365*$F$21*$E$21 -> 0 | AQ21: =(AQ$16+AQ$18)/99%*1%*(DATE(YEAR(AQ$3),12,31)-AQ$3)/365*$F$21*$E$21 -> 0 | AR21: =(AR$17+AR$19)/99%*1%*(DATE(YEAR(AR$3),12,31)-AR$3)/365*$F$21*$E21 -> 0 | AS21: =AS$16/99%*1%*(DATE(YEAR(AS$3),12,31)-AS$3)/365*$F$21 -> 0 | AT21: =AT$16/99%*1%*(DATE(YEAR(AT$3),12,31)-AT$3)/365*$F$21 -> 0 | AU21: =AU$16/99%*1%*(DATE(YEAR(AU$3),12,31)-AU$3)/365*$F$21 -> 0 | AV21: =AV$16/99%*1%*(DATE(YEAR(AV$3),12,31)-AV$3)/365*$F$21 -> 0 | AW21: =(AW$16+AW$18)/99%*1%*(DATE(YEAR(AW$3),12,31)-AW$3)/365*$F$21*$E$21 -> 0 | AX21: =(AX$16+AX$18)/99%*1%*(DATE(YEAR(AX$3),12,31)-AX$3)/365*$F$21*$E$21 -> 0 | AY21: =(AY$16+AY$18)/99%*1%*(DATE(YEAR(AY$3),12,31)-AY$3)/365*$F$21*$E$21 -> 0 | AZ21: =(AZ$16+AZ$18)/99%*1%*(DATE(YEAR(AZ$3),12,31)-AZ$3)/365*$F$21*$E$21 -> 0 | BA21: =(BA$16+BA$18)/99%*1%*(DATE(YEAR(BA$3),12,31)-BA$3)/365*$F$21*$E$21 -> 0 | BB21: =(BB$16+BB$18)/99%*1%*(DATE(YEAR(BB$3),12,31)-BB$3)/365*$F$21*$E$21 -> 0 | BC21: =(BC$16+BC$18)/99%*1%*(DATE(YEAR(BC$3),12,31)-BC$3)/365*$F$21*$E$21 -> 0 | BD21: =(BD$17+BD$19)/99%*1%*(DATE(YEAR(BD$3),12,31)-BD$3)/365*$F$21*$E21 -> 0 | BE21: =BE$16/99%*1%*(DATE(YEAR(BE$3),12,31)-BE$3)/365*$F$21 -> 0 | BF21: =BF$16/99%*1%*(DATE(YEAR(BF$3),12,31)-BF$3)/365*$F$21 -> 0 | BG21: =BG$16/99%*1%*(DATE(YEAR(BG$3),12,31)-BG$3)/365*$F$21 -> 0 | BH21: =BH$16/99%*1%*(DATE(YEAR(BH$3),12,31)-BH$3)/365*$F$21 -> 0 | BI21: =(BI$16+BI$18)/99%*1%*(DATE(YEAR(BI$3),12,31)-BI$3)/365*$F$21*$E$21 -> 0 | BJ21: =(BJ$16+BJ$18)/99%*1%*(DATE(YEAR(BJ$3),12,31)-BJ$3)/365*$F$21*$E$21 -> 0 | BK21: =(BK$16+BK$18)/99%*1%*(DATE(YEAR(BK$3),12,31)-BK$3)/365*$F$21*$E$21 -> 0 | BL21: =(BL$16+BL$18)/99%*1%*(DATE(YEAR(BL$3),12,31)-BL$3)/365*$F$21*$E$21 -> 0 | BM21: =(BM$16+BM$18)/99%*1%*(DATE(YEAR(BM$3),12,31)-BM$3)/365*$F$21*$E$21 -> 0 | BN21: =(BN$16+BN$18)/99%*1%*(DATE(YEAR(BN$3),12,31)-BN$3)/365*$F$21*$E$21 -> 0 | BO21: =(BO$16+BO$18)/99%*1%*(DATE(YEAR(BO$3),12,31)-BO$3)/365*$F$21*$E$21 -> 0 | BP21: =(BP$17+BP$19)/99%*1%*(DATE(YEAR(BP$3),12,31)-BP$3)/365*$F$21*$E21 -> 0 | BQ21: =BQ$16/99%*1%*(DATE(YEAR(BQ$3),12,31)-BQ$3)/365*$F$21 -> 0 | BR21: =BR$16/99%*1%*(DATE(YEAR(BR$3),12,31)-BR$3)/365*$F$21 -> 0 | BS21: =BS$16/99%*1%*(DATE(YEAR(BS$3),12,31)-BS$3)/365*$F$21 -> 0 | BT21: =BT$16/99%*1%*(DATE(YEAR(BT$3),12,31)-BT$3)/365*$F$21 -> 0 | BU21: =(BU$16+BU$18)/99%*1%*(DATE(YEAR(BU$3),12,31)-BU$3)/365*$F$21*$E$21 -> 0
C22: 基金新增总出资额（万元） | G22: =SUM(G16,G20:G21) -> 0 | H22: =SUM(H16,H20:H21) -> 0 | I22: =SUM(I16,I20:I21) -> 0 | J22: =SUM(J16,J20:J21) -> 0 | K22: =SUM(K16,K18,K20:K21) -> 4875.7432 | L22: =SUM(L16,L18,L20:L21) -> 0 | M22: =SUM(M16,M18,M20:M21) -> 0 | N22: =SUM(N16,N18,N20:N21) -> 0 | O22: =SUM(O16,O18,O20:O21) -> 0 | P22: =SUM(P16,P18,P20:P21) -> 22552.74 | Q22: =SUM(Q16,Q18,Q20:Q21) -> 0 | R22: =SUM(R16,R18,R20:R21) -> 0 | ... BU22: =SUM(BU16,BU18,BU20:BU21) -> 0
C23: 基金累计总出资额（万元） | D23: 认缴资本 | E23: 150000 | F23: 1 | G23: =G22 -> 0 | H23: =G23+H22 -> 0 | I23: =H23+I22 -> 0 | J23: =I23+J22 -> 0 | K23: =J23+K22 -> 4875.7432 | L23: =K23+L22 -> 4875.7432 | M23: =L23+M22 -> 4875.7432 | N23: =M23+N22 -> 4875.7432 | O23: =N23+O22 -> 4875.7432 | ... BU23: =BT23+BU22 -> 145153.23
C24: 基金累计总出资% | G24: =G23/$E$23 -> 0 | H24: =H23/$E$23 -> 0 | I24: =I23/$E$23 -> 0 | J24: =J23/$E$23 -> 0 | K24: =K23/$E$23 -> 0.032504955 | L24: =L23/$E$23 -> 0.032504955 | M24: =M23/$E$23 -> 0.032504955 | N24: =N23/$E$23 -> 0.032504955 | ... BU24: =BU23/$E$23 -> 0.96768818
A26: 4 | C26: ACPL新增出资额（万元） | D26: ACPL | E26: 2250 | F26: =E26/150000 -> 0.015 | G26: 0 | H26: 0 | I26: 0 | J26: =基金资金安排!C22 -> 780 | K26: =IF(($F26*K$23-J27)<0,0,($F26*K$23-J27)) -> 0 | L26: =IF(($F26*L$23-K27)<0,0,($F26*L$23-K27)) -> 0 | M26: =IF(($F26*M$23-L27)<0,0,($F26*M$23-L27)) -> 0 | N26: =IF(($F26*N$23-M27)<0,0,($F26*N$23-M27)) -> 0 | O26: =IF(($F26*O$23-N27)<0,0,($F26*O$23-N27)) -> 0 | P26: =IF(($F26*P$23-O27)<0,0,($F26*P$23-O27)) -> 0 | Q26: =IF(($F26*Q$23-P27)<0,0,($F26*Q$23-P27)) -> 0 | R26: =IF(($F26*R$23-Q27)<0,0,($F26*R$23-Q27)) -> 0 | ... BU26: =IF(($F26*BU$23-BT27)<0,0,($F26*BU$23-BT27)) -> 0
A27: 4 | C27: ACPL累计出资额（万元） | G27: =G26 -> 0 | H27: =G27+H26 -> 0 | I27: =H27+I26 -> 0 | J27: =I27+J26 -> 780 | K27: =J27+K26 -> 780 | L27: =K27+L26 -> 780 | M27: =L27+M26 -> 780 | N27: =M27+N26 -> 780 | O27: =N27+O26 -> 780 | ... BU27: =BT27+BU26 -> 2177.2984
C28: ACPLSZ新增出资额（万元） | D28: ACPLSZ | E28: 1250 | F28: =E28/150000 -> 0.0083333333 | G28: 0 | H28: 0 | I28: 0 | J28: =基金资金安排!C13 -> 237.5 | K28: =基金资金安排!H13 -> 127.55102 | L28: =IF(($F28*L$23-K29)<0,0,($F28*L$23-K29)) -> 0 | M28: =IF(($F28*M$23-L29)<0,0,($F28*M$23-L29)) -> 0 | N28: =IF(($F28*N$23-M29)<0,0,($F28*N$23-M29)) -> 0 | O28: =IF(($F28*O$23-N29)<0,0,($F28*O$23-N29)) -> 0 | P28: =IF(($F28*P$23-O29)<0,0,($F28*P$23-O29)) -> 0 | Q28: =IF(($F28*Q$23-P29)<0,0,($F28*Q$23-P29)) -> 0 | R28: =IF(($F28*R$23-Q29)<0,0,($F28*R$23-Q29)) -> 0 | S28: =IF(($F28*S$23-R29)<0,0,($F28*S$23-R29)) -> 51.128637 | ... BU28: =IF(($F28*BU$23-BT29)<0,0,($F28*BU$23-BT29)) -> 0
C29: ACPLSZ累计出资额（万元） | G29: =G28 -> 0 | H29: =G29+H28 -> 0 | I29: =H29+I28 -> 0 | J29: =I29+J28 -> 237.5 | K29: =J29+K28 -> 365.05102 | L29: =K29+L28 -> 365.05102 | M29: =L29+M28 -> 365.05102 | N29: =M29+N28 -> 365.05102 | O29: =N29+O28 -> 365.05102 | ... BU29: =BT29+BU28 -> 1209.6102
C30: ACPSZL新增出资额（万元） | D30: ACPSZL | E30: 675 | F30: =E30/150000 -> 0.0045 | G30: 0 | H30: 0 | I30: 0 | J30: =基金资金安排!C18 -> 202.04082 | K30: =IF(($F30*K$23-J31)<0,0,($F30*K$23-J31)) -> 0 | L30: =IF(($F30*L$23-K31)<0,0,($F30*L$23-K31)) -> 0 | M30: =IF(($F30*M$23-L31)<0,0,($F30*M$23-L31)) -> 0 | N30: =IF(($F30*N$23-M31)<0,0,($F30*N$23-M31)) -> 0 | O30: =IF(($F30*O$23-N31)<0,0,($F30*O$23-N31)) -> 0 | P30: =IF(($F30*P$23-O31)<0,0,($F30*P$23-O31)) -> 0 | Q30: =IF(($F30*Q$23-P31)<0,0,($F30*Q$23-P31)) -> 0 | R30: =IF(($F30*R$23-Q31)<0,0,($F30*R$23-Q31)) -> 0 | ... BU30: =IF(($F30*BU$23-BT31)<0,0,($F30*BU$23-BT31)) -> 0
A31: 11 | C31: ACPSZL累计出资额（万元） | G31: =G30 -> 0 | H31: =G31+H30 -> 0 | I31: =H31+I30 -> 0 | J31: =I31+J30 -> 202.04082 | K31: =J31+K30 -> 202.04082 | L31: =K31+L30 -> 202.04082 | M31: =L31+M30 -> 202.04082 | N31: =M31+N30 -> 202.04082 | O31: =N31+O30 -> 202.04082 | ... BU31: =BT31+BU30 -> 653.18952
A32: 4 | C32: 深圳新融新增出资额（万元） | D32: 深圳新融 | E32: 5000 | F32: =E32/150000 -> 0.033333333 | G32: 0 | H32: 0 | I32: 0 | J32: =基金资金安排!C7 -> 500 | K32: 1000 | L32: =IF(($F32*L$23-K33)<0,0,($F32*L$23-K33)) -> 0 | M32: =IF(($F32*M$23-L33)<0,0,($F32*M$23-L33)) -> 0 | N32: =IF(($F32*N$23-M33)<0,0,($F32*N$23-M33)) -> 0 | O32: =IF(($F32*O$23-N33)<0,0,($F32*O$23-N33)) -> 0 | P32: =IF(($F32*P$23-O33)<0,0,($F32*P$23-O33)) -> 0 | Q32: =IF(($F32*Q$23-P33)<0,0,($F32*Q$23-P33)) -> 0 | R32: =IF(($F32*R$23-Q33)<0,0,($F32*R$23-Q33)) -> 0 | S32: =IF(($F32*S$23-R33)<0,0,($F32*S$23-R33)) -> 164.71863 | ... BU32: =IF(($F32*BU$23-BT33)<0,0,($F32*BU$23-BT33)) -> 0
A33: 4 | C33: 深圳新融累计出资额（万元） | G33: =G32 -> 0 | H33: =G33+H32 -> 0 | I33: =H33+I32 -> 0 | J33: =I33+J32 -> 500 | K33: =J33+K32 -> 1500 | L33: =K33+L32 -> 1500 | M33: =L33+M32 -> 1500 | N33: =M33+N32 -> 1500 | O33: =N33+O32 -> 1500 | ... BU33: =BT33+BU32 -> 4838.4409
A34: 19
A35: 32 | C35: MAA 基本收入（含税，万元） | F35: =汇总!$D$66 -> 0.1 | G35: =F35*5500 -> 550 | H35: =H$8*$F35*100*H$4/4+H$7*$F35*100*(DATE(YEAR(H$3),INT((MONTH(H$3)-1)/3)*3+4,0)-H$3)/365*H$5 -> 137.5 | I35: =I$8*$F35*100*I$4/4+I$7*$F35*100*(DATE(YEAR(I$3),INT((MONTH(I$3)-1)/3)*3+4,0)-I$3)/365*I$5 -> 0 | J35: =J$8*$F35*100*J$4/4+J$7*$F35*100*(DATE(YEAR(J$3),INT((MONTH(J$3)-1)/3)*3+4,0)-J$3)/365*J$5 -> 0 | K35: =K$8*$F35*100*K$4/4+K$7*$F35*100*(DATE(YEAR(K$3),INT((MONTH(K$3)-1)/3)*3+4,0)-K$3)/365*K$5 -> 137.5 | L35: =L$8*$F35*100*L$4/4+L$7*$F35*100*(DATE(YEAR(L$3),INT((MONTH(L$3)-1)/3)*3+4,0)-L$3)/365*L$5 -> 0 | M35: =M$8*$F35*100*M$4/4+M$7*$F35*100*(DATE(YEAR(M$3),INT((MONTH(M$3)-1)/3)*3+4,0)-M$3)/365*M$5 -> 0 | N35: =N$8*$F35*100*N$4/4+N$7*$F35*100*(DATE(YEAR(N$3),INT((MONTH(N$3)-1)/3)*3+4,0)-N$3)/365*N$5 -> 137.5 | O35: =O$8*$F35*100*O$4/4+O$7*$F35*100*(DATE(YEAR(O$3),INT((MONTH(O$3)-1)/3)*3+4,0)-O$3)/365*O$5 -> 0 | ... BU35: =BU$8*$F35*100*BU$4/4+BU$7*$F35*100*(DATE(YEAR(BU$3),INT((MONTH(BU$3)-1)/3)*3+4,0)-BU$3)/365*BU$5 -> 0
A36: 32 | C36: MAA 激励收入一（含税，万元） | D36: “1”为支付，"0"为不支付 | E36: =汇总!N67 -> 0 | F36: =汇总!$D$67 -> 0.01 | G36: =G$8*$F36*100*(DATE(2025,12,31)-DATE(2024,12,16))/365 -> 0 | T36: {=SUMPRODUCT(H$8:S$8,I$3:T$3-H$3:S$3)/(T$3-H$3)*100*$F36*$E$36} -> 0 | AF36: {=SUMPRODUCT(T$8:AE$8,U$3:AF$3-T$3:AE$3)/(AF$3-T$3)*100*$F36*$E$36} -> 0 | AR36: {=SUMPRODUCT(AF$8:AQ$8,AG$3:AR$3-AF$3:AQ$3)/(AR$3-AF$3)*100*$F36*$E$36} -> 0 | BD36: {=SUMPRODUCT(AR$8:BC$8,AS$3:BD$3-AR$3:BC$3)/(BD$3-AR$3)*100*$F36*$E$36} -> 0 | BP36: {=SUMPRODUCT(BD$8:BO$8,BE$3:BP$3-BD$3:BO$3)/(BP$3-BD$3)*100*$F36*$E$36} -> 0
C37: MAA 激励收入二（含税，万元） | D37: “1”为支付，"0"为不支付 | E37: =汇总!N68 -> 0 | F37: =汇总!$D$68 -> 0.04 | G37: =G$8*$F37*100*(DATE(2025,12,31)-DATE(2024,12,16))/365 -> 0 | T37: {=SUMPRODUCT(H$8:S$8,I$3:T$3-H$3:S$3)/(T$3-H$3)*100*$F37*$E$37} -> 0 | AF37: {=SUMPRODUCT(T$8:AE$8,U$3:AF$3-T$3:AE$3)/(AF$3-T$3)*100*$F37*$E$37} -> 0 | AR37: {=SUMPRODUCT(AF$8:AQ$8,AG$3:AR$3-AF$3:AQ$3)/(AR$3-AF$3)*100*$F37*$E$37} -> 0 | BD37: {=SUMPRODUCT(AR$8:BC$8,AS$3:BD$3-AR$3:BC$3)/(BD$3-AR$3)*100*$F37*$E$37} -> 0 | BP37: {=SUMPRODUCT(BD$8:BO$8,BE$3:BP$3-BD$3:BO$3)/(BP$3-BD$3)*100*$F37*$E$37} -> 0
A38: 32 | C38: 总MAA收入（含税，万元） | G38: =SUM(G35:G37) -> 550 | H38: =SUM(H35:H37) -> 137.5 | I38: =SUM(I35:I37) -> 0 | J38: =SUM(J35:J37) -> 0 | K38: =SUM(K35:K37) -> 137.5 | L38: =SUM(L35:L37) -> 0 | M38: =SUM(M35:M37) -> 0 | N38: =SUM(N35:N37) -> 137.5 | ... BU38: =SUM(BU35:BU37) -> 0
A40: 32 | C40: MAA 基本收入（不含税，万元） | D40: VAT | E40: 0.06 | F40: 0.12 | G40: =G35/(1+$E40) -> 518.86792 | H40: =H35/(1+$E40) -> 129.71698 | I40: =I35/(1+$E40) -> 0 | J40: =J35/(1+$E40) -> 0 | K40: =K35/(1+$E40) -> 129.71698 | L40: =L35/(1+$E40) -> 0 | M40: =M35/(1+$E40) -> 0 | N40: =N35/(1+$E40) -> 129.71698 | ... BU40: =BU35/(1+$E40) -> 0
A41: 32 | C41: MAA 激励收入一（不含税，万元） | D41: VAT | E41: 0.06 | F41: 0.01 | G41: =G36/(1+$E41) -> 0 | H41: =H36/(1+$E41) -> 0 | I41: =I36/(1+$E41) -> 0 | J41: =J36/(1+$E41) -> 0 | K41: =K36/(1+$E41) -> 0 | L41: =L36/(1+$E41) -> 0 | M41: =M36/(1+$E41) -> 0 | N41: =N36/(1+$E41) -> 0 | ... BU41: =BU36/(1+$E41) -> 0
C42: MAA 激励收入二（不含税，万元） | D42: VAT | E42: 0.06 | F42: 0.02 | G42: =G37/(1+$E42) -> 0 | H42: =H37/(1+$E42) -> 0 | I42: =I37/(1+$E42) -> 0 | J42: =J37/(1+$E42) -> 0 | K42: =K37/(1+$E42) -> 0 | L42: =L37/(1+$E42) -> 0 | M42: =M37/(1+$E42) -> 0 | N42: =N37/(1+$E42) -> 0 | ... BU42: =BU37/(1+$E42) -> 0
A43: 32 | C43: 总MAA收入（不含税，万元） | D43: VAT | E43: 0.06 | G43: =SUM(G40:G42) -> 518.86792 | H43: =SUM(H40:H42) -> 129.71698 | I43: =SUM(I40:I42) -> 0 | J43: =SUM(J40:J42) -> 0 | K43: =SUM(K40:K42) -> 129.71698 | L43: =SUM(L40:L42) -> 0 | M43: =SUM(M40:M42) -> 0 | N43: =SUM(N40:N42) -> 129.71698 | ... BU43: =SUM(BU40:BU42) -> 0
A45: 32 | C45: 运维费用（含税，万元） | D45: 单瓦成本 | E45: 0.06 | F45: =汇总!$M$69 -> 0.035 | G45: =280*(DATE(2025,12,31)-DATE(2024,12,16))/365 -> 291.50685 | H45: =177.33/4*H$4+H$7*$F45*100*(DATE(YEAR(H$3),INT((MONTH(H$3)-1)/3)*3+4,0)-H$3)/365 -> 91.270856 | I45: =177.33/4*I$4+I$7*$F45*100*(DATE(YEAR(I$3),INT((MONTH(I$3)-1)/3)*3+4,0)-I$3)/365 -> 0 | J45: =177.33/4*J$4+J$7*$F45*100*(DATE(YEAR(J$3),INT((MONTH(J$3)-1)/3)*3+4,0)-J$3)/365 -> 0 | K45: =177.33/4*K$4+(K$8-$G$8)*$F45*100/4*K$4+K$7*$F45*100*(DATE(YEAR(K$3),INT((MONTH(K$3)-1)/3)*3+4,0)-K$3)/365 -> 92.4575 | L45: =177.33/4*L$4+(L$8-$G$8)*$F45*100/4*L$4+L$7*$F45*100*(DATE(YEAR(L$3),INT((MONTH(L$3)-1)/3)*3+4,0)-L$3)/365 -> 0 | M45: =177.33/4*M$4+(M$8-$G$8)*$F45*100/4*M$4+M$7*$F45*100*(DATE(YEAR(M$3),INT((MONTH(M$3)-1)/3)*3+4,0)-M$3)/365 -> 0 | N45: =177.33/4*N$4+(N$8-$G$8)*$F45*100/4*N$4+N$7*$F45*100*(DATE(YEAR(N$3),INT((MONTH(N$3)-1)/3)*3+4,0)-N$3)/365 -> 92.4575 | O45: =177.33/4*O$4+(O$8-$G$8)*$F45*100/4*O$4+O$7*$F45*100*(DATE(YEAR(O$3),INT((MONTH(O$3)-1)/3)*3+4,0)-O$3)/365 -> 0 | P45: =177.33/4*P$4+(P$8-$G$8)*$F45*100/4*P$4+P$7*$F45*100*(DATE(YEAR(P$3),INT((MONTH(P$3)-1)/3)*3+4,0)-P$3)/365 -> 41.712329 | Q45: =177.33/4*Q$4+(Q$8-$G$8)*$F45*100/4*Q$4+Q$7*$F45*100*(DATE(YEAR(Q$3),INT((MONTH(Q$3)-1)/3)*3+4,0)-Q$3)/365 -> 223.7075 | R45: =177.33/4*R$4+(R$8-$G$8)*$F45*100/4*R$4+R$7*$F45*100*(DATE(YEAR(R$3),INT((MONTH(R$3)-1)/3)*3+4,0)-R$3)/365 -> 0 | ... BU45: =177.33/4*BU$4+(BU$8-$G$8)*$F45*100/4*BU$4+BU$7*$F45*100*(DATE(YEAR(BU$3),INT((MONTH(BU$3)-1)/3)*3+4,0)-BU$3)/365 -> 0
A46: 32 | C46: 第三方咨询顾问
A47: 32 | C47: 电力交易（含税，万/项目） | D47: VAT | E47: 0.06 | F47: 20 | G47: 10 | H47: =$F47*G$10/4*H$4+$F47*(H$10-G$10)*(DATE(YEAR(H$3),INT((MONTH(H$3)-1)/3)*3+4,0)-H$3)/365*H$5 -> 0 | I47: =$F47*H$10/4*I$4+$F47*(I$10-H$10)*(DATE(YEAR(I$3),INT((MONTH(I$3)-1)/3)*3+4,0)-I$3)/365*I$5 -> 0 | J47: =$F47*I$10/4*J$4+$F47*(J$10-I$10)*(DATE(YEAR(J$3),INT((MONTH(J$3)-1)/3)*3+4,0)-J$3)/365*J$5 -> 0 | K47: =$F47*J$10/4*K$4+$F47*(K$10-J$10)*(DATE(YEAR(K$3),INT((MONTH(K$3)-1)/3)*3+4,0)-K$3)/365*K$5 -> 5 | L47: =$F47*K$10/4*L$4+$F47*(L$10-K$10)*(DATE(YEAR(L$3),INT((MONTH(L$3)-1)/3)*3+4,0)-L$3)/365*L$5 -> 0 | M47: =$F47*L$10/4*M$4+$F47*(M$10-L$10)*(DATE(YEAR(M$3),INT((MONTH(M$3)-1)/3)*3+4,0)-M$3)/365*M$5 -> 0 | N47: =$F47*M$10/4*N$4+$F47*(N$10-M$10)*(DATE(YEAR(N$3),INT((MONTH(N$3)-1)/3)*3+4,0)-N$3)/365*N$5 -> 5 | O47: =$F47*N$10/4*O$4+$F47*(O$10-N$10)*(DATE(YEAR(O$3),INT((MONTH(O$3)-1)/3)*3+4,0)-O$3)/365*O$5 -> 0 | ... BU47: =$F47*BT$10/4*BU$4+$F47*(BU$10-BT$10)*(DATE(YEAR(BU$3),INT((MONTH(BU$3)-1)/3)*3+4,0)-BU$3)/365*BU$5 -> 0
C48: 电力研究数据库（含税，万/年） | D48: VAT | E48: 0.06 | F48: 25 | G48: 0 | H48: =$F$48/4*H$4 -> 6.25 | I48: =$F$48/4*I$4 -> 0 | J48: =$F$48/4*J$4 -> 0 | K48: =$F$48/4*K$4 -> 6.25 | L48: =$F$48/4*L$4 -> 0 | M48: =$F$48/4*M$4 -> 0 | N48: =$F$48/4*N$4 -> 6.25 | O48: =$F$48/4*O$4 -> 0 | ... BU48: =$F$48/4*BU$4 -> 0
C49: 监控系统服务软件开发（含税，万/项目） | D49: VAT | E49: 0.06 | F49: 10 | G49: 0 | H49: =$F49*H$10/4*H$4 -> 2.5 | I49: =$F49*I$10/4*I$4 -> 0 | J49: =$F49*J$10/4*J$4 -> 0 | K49: =$F49*K$10/4*K$4 -> 2.5 | L49: =$F49*L$10/4*L$4 -> 0 | M49: =$F49*M$10/4*M$4 -> 0 | N49: =$F49*N$10/4*N$4 -> 2.5 | O49: =$F49*O$10/4*O$4 -> 0 | ... BU49: =$F49*BU$10/4*BU$4 -> 0
C50: 发电能力（EBA）归因分析（含税，万/项目） | D50: VAT | E50: 0.06 | F50: 0 | G50: 0 | H50: =$F50*H$10/4*H$4 -> 0 | I50: =$F50*I$10/4*I$4 -> 0 | J50: =$F50*J$10/4*J$4 -> 0 | K50: =$F50*K$10/4*K$4 -> 0 | L50: =$F50*L$10/4*L$4 -> 0 | M50: =$F50*M$10/4*M$4 -> 0 | N50: =$F50*N$10/4*N$4 -> 0 | O50: =$F50*O$10/4*O$4 -> 0 | ... BU50: =$F50*BU$10/4*BU$4 -> 0
A51: 32 | C51: 项目公司财务经办人员工资及五险一金（含税，万/年） | D51: VAT | E51: 0 | F51: =0.75*12 -> 9 | G51: =F51 -> 9 | H51: =$F$51/12*H$11 -> 0.75 | I51: =$F$51/12*I$11 -> 0.75 | J51: =$F$51/12*J$11 -> 0.75 | K51: =$F$51/12*K$11 -> 0.75 | L51: =$F$51/12*L$11 -> 0.75 | M51: =$F$51/12*M$11 -> 0.75 | N51: =$F$51/12*N$11 -> 0.75 | O51: =$F$51/12*O$11 -> 0.75 | ... BU51: =$F$51/12*BU$11 -> 3
C52: 会计服务费（含税，万/年/项目） | D52: VAT | E52: 0.01 | F52: =4000*12/10000 -> 4.8 | G52: =F52 -> 4.8 | H52: =$F$52/12*H10 -> 0.4 | I52: =$F$52/12*I10 -> 0.4 | J52: =$F$52/12*J10 -> 0.4 | K52: =$F$52/12*K10 -> 0.4 | L52: =$F$52/12*L10 -> 0.4 | M52: =$F$52/12*M10 -> 0.4 | N52: =$F$52/12*N10 -> 0.4 | O52: =$F$52/12*O10 -> 0.4 | ... BU52: =$F$52/12*BU10 -> 5.2
C53: 人力资源服务费（含税，万/年/项目） | D53: VAT | E53: 0.01 | F53: =500*12/10000 -> 0.6 | G53: =F53 -> 0.6 | H53: =$F$53/12*H10 -> 0.05 | I53: =$F$53/12*I10 -> 0.05 | J53: =$F$53/12*J10 -> 0.05 | K53: =$F$53/12*K10 -> 0.05 | L53: =$F$53/12*L10 -> 0.05 | M53: =$F$53/12*M10 -> 0.05 | N53: =$F$53/12*N10 -> 0.05 | O53: =$F$53/12*O10 -> 0.05 | ... BU53: =$F$53/12*BU10 -> 0.65
C54: 办公用品，差旅，其他（含税，万/年/项目） | D54: VAT | E54: 0 | F54: 1 | G54: =F54 -> 1 | H54: =$F$54/12*H10 -> 0.083333333 | I54: =$F$54/12*I10 -> 0.083333333 | J54: =$F$54/12*J10 -> 0.083333333 | K54: =$F$54/12*K10 -> 0.083333333 | L54: =$F$54/12*L10 -> 0.083333333 | M54: =$F$54/12*M10 -> 0.083333333 | N54: =$F$54/12*N10 -> 0.083333333 | O54: =$F$54/12*O10 -> 0.083333333 | ... BU54: =$F$54/12*BU10 -> 1.0833333
C55: 其他费用合计（含税，万元） | G55: =SUM(G46:G54) -> 25.4 | H55: =SUM(H46:H54) -> 10.033333 | I55: =SUM(I46:I54) -> 1.2833333 | J55: =SUM(J46:J54) -> 1.2833333 | K55: =SUM(K46:K54) -> 15.033333 | L55: =SUM(L46:L54) -> 1.2833333 | M55: =SUM(M46:M54) -> 1.2833333 | N55: =SUM(N46:N54) -> 15.033333 | ... BU55: =SUM(BU46:BU54) -> 9.9333333
C56: 总费用（含税，万元) | G56: =SUM(G45,G55) -> 316.90685 | H56: =SUM(H45,H55) -> 101.30419 | I56: =SUM(I45,I55) -> 1.2833333 | J56: =SUM(J45,J55) -> 1.2833333 | K56: =SUM(K45,K55) -> 107.49083 | L56: =SUM(L45,L55) -> 1.2833333 | M56: =SUM(M45,M55) -> 1.2833333 | N56: =SUM(N45,N55) -> 107.49083 | ... BU56: =SUM(BU45,BU55) -> 9.9333333
A58: 32 | C58: 运维费用（不含税，万元） | D58: 单瓦成本 | E58: 0.06 | F58: 0.04 | G58: =G45/(1+$E58) -> 275.00646 | H58: =H45/(1+$E58) -> 86.104581 | I58: =I45/(1+$E58) -> 0 | J58: =J45/(1+$E58) -> 0 | K58: =K45/(1+$E58) -> 87.224057 | L58: =L45/(1+$E58) -> 0 | M58: =M45/(1+$E58) -> 0 | N58: =N45/(1+$E58) -> 87.224057 | ... BU58: =BU45/(1+$E58) -> 0
A59: 32 | C59: 第三方咨询顾问
A60: 32 | C60: 电力交易（不含税，万/项目） | D60: VAT | E60: 0.06 | F60: 10 | G60: =G47/(1+$E60) -> 9.4339623 | H60: =H47/(1+$E60) -> 0 | I60: =I47/(1+$E60) -> 0 | J60: =J47/(1+$E60) -> 0 | K60: =K47/(1+$E60) -> 4.7169811 | L60: =L47/(1+$E60) -> 0 | M60: =M47/(1+$E60) -> 0 | N60: =N47/(1+$E60) -> 4.7169811 | ... BU60: =BU47/(1+$E60) -> 0
C61: 电力研究数据库（不含税，万/年） | D61: VAT | E61: 0.06 | F61: 25 | G61: =G48/(1+$E61) -> 0 | H61: =H48/(1+$E61) -> 5.8962264 | I61: =I48/(1+$E61) -> 0 | J61: =J48/(1+$E61) -> 0 | K61: =K48/(1+$E61) -> 5.8962264 | L61: =L48/(1+$E61) -> 0 | M61: =M48/(1+$E61) -> 0 | N61: =N48/(1+$E61) -> 5.8962264 | ... BU61: =BU48/(1+$E61) -> 0
C62: 监控系统服务软件开发（不含税，万/项目） | D62: VAT | E62: 0.06 | F62: 10 | G62: =G49/(1+$E62) -> 0 | H62: =H49/(1+$E62) -> 2.3584906 | I62: =I49/(1+$E62) -> 0 | J62: =J49/(1+$E62) -> 0 | K62: =K49/(1+$E62) -> 2.3584906 | L62: =L49/(1+$E62) -> 0 | M62: =M49/(1+$E62) -> 0 | N62: =N49/(1+$E62) -> 2.3584906 | ... BU62: =BU49/(1+$E62) -> 0
C63: 发电能力（EBA）归因分析（不含税，万/项目） | D63: VAT | E63: 0.06 | F63: 15 | G63: =G50/(1+$E63) -> 0 | H63: =H50/(1+$E63) -> 0 | I63: =I50/(1+$E63) -> 0 | J63: =J50/(1+$E63) -> 0 | K63: =K50/(1+$E63) -> 0 | L63: =L50/(1+$E63) -> 0 | M63: =M50/(1+$E63) -> 0 | N63: =N50/(1+$E63) -> 0 | ... BU63: =BU50/(1+$E63) -> 0
A64: 32 | C64: 项目公司财务经办人员工资及五险一金（不含税，万/年） | D64: VAT | E64: 0 | F64: =0.75*12 -> 9 | G64: =G51/(1+$E64) -> 9 | H64: =H51/(1+$E64) -> 0.75 | I64: =I51/(1+$E64) -> 0.75 | J64: =J51/(1+$E64) -> 0.75 | K64: =K51/(1+$E64) -> 0.75 | L64: =L51/(1+$E64) -> 0.75 | M64: =M51/(1+$E64) -> 0.75 | N64: =N51/(1+$E64) -> 0.75 | ... BU64: =BU51/(1+$E64) -> 3
C65: 会计服务费（不含税，万/年/项目） | D65: VAT | E65: 0.01 | F65: =4000*12/10000 -> 4.8 | G65: =G52/(1+$E65) -> 4.7524752 | H65: =H52/(1+$E65) -> 0.3960396 | I65: =I52/(1+$E65) -> 0.3960396 | J65: =J52/(1+$E65) -> 0.3960396 | K65: =K52/(1+$E65) -> 0.3960396 | L65: =L52/(1+$E65) -> 0.3960396 | M65: =M52/(1+$E65) -> 0.3960396 | N65: =N52/(1+$E65) -> 0.3960396 | ... BU65: =BU52/(1+$E65) -> 5.1485149
C66: 人力资源服务费（不含税，万/年/项目） | D66: VAT | E66: 0.01 | F66: =500*12/10000 -> 0.6 | G66: =G53/(1+$E66) -> 0.59405941 | H66: =H53/(1+$E66) -> 0.04950495 | I66: =I53/(1+$E66) -> 0.04950495 | J66: =J53/(1+$E66) -> 0.04950495 | K66: =K53/(1+$E66) -> 0.04950495 | L66: =L53/(1+$E66) -> 0.04950495 | M66: =M53/(1+$E66) -> 0.04950495 | N66: =N53/(1+$E66) -> 0.04950495 | ... BU66: =BU53/(1+$E66) -> 0.64356436
C67: 办公用品，差旅，其他（不含税，万/年/项目） | D67: VAT | E67: 0 | F67: 1 | G67: =G54/(1+$E67) -> 1 | H67: =H54/(1+$E67) -> 0.083333333 | I67: =I54/(1+$E67) -> 0.083333333 | J67: =J54/(1+$E67) -> 0.083333333 | K67: =K54/(1+$E67) -> 0.083333333 | L67: =L54/(1+$E67) -> 0.083333333 | M67: =M54/(1+$E67) -> 0.083333333 | N67: =N54/(1+$E67) -> 0.083333333 | ... BU67: =BU54/(1+$E67) -> 1.0833333
C68: 其他费用合计（不含税，万元） | G68: =SUM(G59:G67) -> 24.780497 | H68: =SUM(H59:H67) -> 9.5335949 | I68: =SUM(I59:I67) -> 1.2788779 | J68: =SUM(J59:J67) -> 1.2788779 | K68: =SUM(K59:K67) -> 14.250576 | L68: =SUM(L59:L67) -> 1.2788779 | M68: =SUM(M59:M67) -> 1.2788779 | N68: =SUM(N59:N67) -> 14.250576 | ... BU68: =SUM(BU59:BU67) -> 9.8754125
C69: 总费用（不含税，万元) | G69: =SUM(G58,G68) -> 299.78696 | H69: =SUM(H58,H68) -> 95.638176 | I69: =SUM(I58,I68) -> 1.2788779 | J69: =SUM(J58,J68) -> 1.2788779 | K69: =SUM(K58,K68) -> 101.47463 | L69: =SUM(L58,L68) -> 1.2788779 | M69: =SUM(M58,M68) -> 1.2788779 | N69: =SUM(N58,N68) -> 101.47463 | ... BU69: =SUM(BU58,BU68) -> 9.8754125
A71: 32 | C71: 基金基础管理费收入（不含VAT，万元） | D71: 扣除IDG 25% CIT | E71: 0.25 | F71: 0.06 | G71: =G20/(1+$F$71)*(1-$E$71) -> 0 | H71: =H20/(1+$F$71)*(1-$E$71) -> 0 | I71: =I20/(1+$F$71)*(1-$E$71) -> 0 | J71: =J20/(1+$F$71)*(1-$E$71) -> 0 | K71: =K20/(1+$F$71)*(1-$E$71) -> 18.214518 | L71: =L20/(1+$F$71)*(1-$E$71) -> 0 | M71: =M20/(1+$F$71)*(1-$E$71) -> 0 | N71: =N20/(1+$F$71)*(1-$E$71) -> 0 | ... BU71: =BU20/(1+$F$71)*(1-$E$71) -> 0
A72: 32 | C72: 基金激励管理费收入（不含VAT，万元） | D72: 扣除IDG 25% CIT | E72: 0.25 | F72: 0.06 | G72: =G21/(1+$F$71)*(1-$E$71) -> 0 | H72: =H21/(1+$F$71)*(1-$E$71) -> 0 | I72: =I21/(1+$F$71)*(1-$E$71) -> 0 | J72: =J21/(1+$F$71)*(1-$E$71) -> 0 | K72: =K21/(1+$F$71)*(1-$E$71) -> 0 | L72: =L21/(1+$F$71)*(1-$E$71) -> 0 | M72: =M21/(1+$F$71)*(1-$E$71) -> 0 | N72: =N21/(1+$F$71)*(1-$E$71) -> 0 | ... BU72: =BU21/(1+$F$71)*(1-$E$71) -> 0
A73: 32 | B73: ACPLSZ | C73: 总基金管理费收入（不含VAT，万元） | K73: =SUM(G71:K72) -> 18.214518 | L73: =SUM(L71:L72) -> 0 | M73: =SUM(M71:M72) -> 0 | N73: =SUM(N71:N72) -> 0 | O73: =SUM(O71:O72) -> 0 | P73: =SUM(P71:P72) -> 37.315844 | Q73: =SUM(Q71:Q72) -> 0 | R73: =SUM(R71:R72) -> 0 | S73: =SUM(S71:S72) -> 9.2518621 | ... BU73: =SUM(BU71:BU72) -> 0
A75: 32 | B75: Total | C75: 净MAA收入（不含税，万元） | G75: 0 | H75: 0 | I75: 0 | J75: 0 | L75: =SUM(G43:M43)-SUM(G69:M69) -> 276.28661 | M75: 0 | N75: =SUM(N43:P43)-SUM(N69:P69) -> 94.709546 | O75: 0 | P75: 0 | Q75: =SUM(Q43:S43)-SUM(Q69:S69) -> 305.25481 | R75: 0 | S75: 0 | T75: =SUM(T43:V43)-SUM(T69:V69) -> 469.56248 | U75: 0 | V75: 0 | W75: =SUM(W43:Y43)-SUM(W69:Y69) -> 560.3733 | X75: 0 | Y75: 0 | Z75: =SUM(Z43:AB43)-SUM(Z69:AB69) -> 679.15278 | AA75: 0 | AB75: 0 | AC75: =SUM(AC43:AE43)-SUM(AC69:AE69) -> 773.13024 | AD75: 0 | AE75: 0 | AF75: =SUM(AF43:AH43)-SUM(AF69:AH69) -> 869.44907 | AG75: 0 | AH75: 0 | AI75: =SUM(AI43:AK43)-SUM(AI69:AK69) -> 938.47402 | AJ75: 0 | AK75: 0 | AL75: =SUM(AL43:AN43)-SUM(AL69:AN69) -> 1082.0777 | AM75: 0 | AN75: 0 | AO75: =SUM(AO43:AQ43)-SUM(AO69:AQ69) -> 1153.5193 | AP75: 0 | AQ75: 0 | AR75: =SUM(AR43:AT43)-SUM(AR69:AT69) -> 1294.7063 | AS75: 0 | AT75: 0 | AU75: =SUM(AU43:AW43)-SUM(AU69:AW69) -> 1294.7063 | AV75: 0 | AW75: 0 | AX75: =SUM(AX43:AZ43)-SUM(AX69:AZ69) -> 1294.7063 | AY75: 0 | AZ75: 0 | BA75: =SUM(BA43:BC43)-SUM(BA69:BC69) -> 1294.7063 | BB75: 0 | BC75: 0 | BD75: =SUM(BD43:BF43)-SUM(BD69:BF69) -> 1294.7063 | BE75: 0 | BF75: 0 | BG75: =SUM(BG43:BI43)-SUM(BG69:BI69) -> 1294.7063 | BH75: 0 | BI75: 0 | BJ75: =SUM(BJ43:BL43)-SUM(BJ69:BL69) -> 1294.7063 | BK75: 0 | BL75: 0 | BM75: =SUM(BM43:BO43)-SUM(BM69:BO69) -> 1294.7063 | BN75: 0 | BO75: 0 | BP75: =SUM(BP43:BR43)-SUM(BP69:BR69) -> 1294.7063 | BQ75: 0 | BR75: 0 | BS75: =SUM(BS43:BU43)-SUM(BS69:BU69) -> 1294.7063 | BT75: 0 | BU75: 0
A76: 32 | B76: ACPLSZ | C76: 净MAA收入（不含税，万元） | F76: 0.75 | G76: 0 | H76: 0 | I76: 0 | J76: 0 | K76: =K75*100% -> 0 | L76: =(G43-G69)+(L75-(G43-G69))*$F$76 -> 261.9852 | M76: =M75*$F$76 -> 0 | N76: =N75*$F$76 -> 71.032159 | O76: =O75*$F$76 -> 0 | P76: =P75*$F$76 -> 0 | Q76: =Q75*$F$76 -> 228.94111 | R76: =R75*$F$76 -> 0 | S76: =S75*$F$76 -> 0 | T76: =T75*$F$76 -> 352.17186 | ... BU76: =BU75*$F$76 -> 0
A77: 32 | B77: ACPLHK | C77: 净MAA收入（不含税，万元） | F77: 0.25 | G77: 0 | H77: 0 | I77: 0 | J77: 0 | K77: 0 | L77: =L75-L76 -> 14.30141 | M77: =M75*$F$77 -> 0 | N77: =N75*$F$77 -> 23.677386 | O77: =O75*$F$77 -> 0 | P77: =P75*$F$77 -> 0 | Q77: =Q75*$F$77 -> 76.313703 | R77: =R75*$F$77 -> 0 | S77: =S75*$F$77 -> 0 | T77: =T75*$F$77 -> 117.39062 | ... BU77: =BU75*$F$77 -> 0
A78: 32 | B78: ACPLHK | C78: 净MAA收入（不含税，万元，扣除5% WHT） | F78: 0.05 | G78: 0 | H78: 0 | I78: 0 | J78: 0 | K78: =K77*(1-$F$78) -> 0 | L78: =L77*(1-$F$78) -> 13.58634 | M78: =M77*(1-$F$78) -> 0 | N78: =N77*(1-$F$78) -> 22.493517 | O78: =O77*(1-$F$78) -> 0 | P78: =P77*(1-$F$78) -> 0 | Q78: =Q77*(1-$F$78) -> 72.498017 | R78: =R77*(1-$F$78) -> 0 | ... BU78: =BU77*(1-$F$78) -> 0
AF80: =3102 -> 3102 | AG80: =AF80-1200 -> 1902 | AH80: =AG80*25% -> 475.5 | AI80: =AF80-AH80+AF81 -> 3586.836 | AJ80: =AI80-1200 -> 2386.836 | AK80: 3500
AF81: =SUM(AF78:AO78) -> 960.33602

Sheet Pipeline
B2: 按项目
C4: 业主 | D4: 所在省份 | E4: 项目规模（MW） | F4: 项目类型 | G4: 交易确定性 | H4: 交易概率预测 | I4: 预估资本金出资（亿元） | J4: 预估动钱时间 | K4: 单价
B5: JV类 (active deals only) | C5: 三一重能 | D5: 湖南 | E5: 200 | F5: 风电 | G5: 高 | H5: 0.7 | I5: =0.3*K5*E5/10^2 -> 3.48 | J5: 26 Q3 | K5: 5.8
C6: 特变 | D6: 河南/湖南等 | E6: 100 | F6: 风电 | G6: 高 | H6: 0.7 | I6: =0.3*K6*E6/10^2 -> 1.95 | J6: 26 Q3 | K6: 6.5
C7: 阳光 | D7: 安徽、山东 | E7: =225+200 -> 425 | F7: 光伏、风电 | G7: 中 | H7: 0.5 | I7: =0.3*K7*E7/10^2 -> 6.6525 | J7: 26 Q4 | K7: =(4*200+6.3*225)/(200+225) -> 5.2176471
C8: 特变 | D8: 安徽 | E8: 100 | F8: 风电 | G8: 中 | H8: 0.5 | I8: =0.3*K8*E8/10^2 -> 2.4 | J8: 26 Q4 | K8: 8
C9: 格物 - 增量 | D9: 河北冀南 | E9: 300 | F9: 风电 | G9: 中 | H9: 0.5 | I9: =0.3*K9*E9/10^2 -> 6.3 | J9: 26 Q4 | K9: 7
C10: 首欣 | D10: 山东 | E10: 100 | F10: 风电 | G10: 中 | H10: 0.4 | I10: =0.3*K10*E10/10^2 -> 2.1 | J10: 26 Q3 | K10: 7
C11: 三一重能&河南电建 | D11: 河南 | E11: 100 | F11: 风电 | G11: 低 | H11: 0.3 | I11: =0.3*K11*E11/10^2 -> 1.89 | J11: 26 Q4 | K11: 6.3
C12: 格物 - 存量 | D12: 河北冀南 | E12: 200 | F12: 风电 | G12: 低 | H12: 0.3 | I12: =0.3*K12*E12/10^2 -> 4.44 | J12: 26 Q4 | K12: 7.4
C13: 民海集团 | D13: 广西 | E13: 200 | F13: 风电 | G13: 低 | H13: 0.3 | I13: =0.3*K13*E13/10^2 -> 3.9 | J13: 26 Q4 | K13: 6.5
C14: 清电能源 | D14: 河南 | E14: 100 | F14: 风电 | G14: 低 | H14: 0.2 | I14: =0.3*K14*E14/10^2 -> 1.5 | J14: 26 Q3 | K14: 5
B15: 开发类 | C15: 富士康 | D15: 江西赣州 | E15: 250 | F15: 风电 | G15: 高 | H15: 0.6 | I15: =0.3*K15*E15/10^2 -> 3.975 | J15: 27 H2 | K15: 5.3
C16: 富士康 | D16: 河南港区 | E16: 100 | F16: 风电 | G16: 中 | H16: 0.5 | I16: =0.3*K16*E16/10^2 -> 1.65 | J16: 27 H2 | K16: 5.5
C17: 富士康 | D17: 河南鹤壁 | E17: 15 | F17: 风电 | G17: 低 | H17: 0.3 | I17: =0.3*K17*E17/10^2 -> 0.2385 | J17: 27 H2 | K17: 5.3
B21: 按出资时间（仅考虑中&高确定性）
C22: 预计资本金出资（亿元）
B23: 26 Q1 | C23: =SUMIFS($I$5:$I$17,$J$5:$J$17,$B23,$G$5:$G$17,"高")+SUMIFS($I$5:$I$17,$J$5:$J$17,$B23,$G$5:$G$17,"中") -> 0
B24: 26 Q2 | C24: =SUMIFS($I$5:$I$17,$J$5:$J$17,$B24,$G$5:$G$17,"高")+SUMIFS($I$5:$I$17,$J$5:$J$17,$B24,$G$5:$G$17,"中") -> 0
B25: 26 Q3 | C25: =SUMIFS($I$5:$I$17,$J$5:$J$17,$B25,$G$5:$G$17,"高")+SUMIFS($I$5:$I$17,$J$5:$J$17,$B25,$G$5:$G$17,"中") -> 7.53
B26: 26 Q4 | C26: =SUMIFS($I$5:$I$17,$J$5:$J$17,$B26,$G$5:$G$17,"高")+SUMIFS($I$5:$I$17,$J$5:$J$17,$B26,$G$5:$G$17,"中") -> 15.3525
B27: 27 H2 | C27: =SUMIFS($I$5:$I$17,$J$5:$J$17,$B27,$G$5:$G$17,"高")+SUMIFS($I$5:$I$17,$J$5:$J$17,$B27,$G$5:$G$17,"中") -> 5.625
B28: 总计 | C28: =SUM(C23:C27) -> 28.5075
B30: 按出资时间（全pipeline）
C31: 预计资本金出资（亿元）
B32: 26 Q1 | C32: =SUMIF($J$5:$J$17,"26 Q1",$I$5:$I$17) -> 0
B33: 26 Q2 | C33: =SUMIF($J$5:$J$17,"26 Q2",$I$5:$I$17) -> 0
B34: 26 Q3 | C34: =SUMIF($J$5:$J$17,"26 Q3",$I$5:$I$17) -> 9.03
B35: 26 Q4 | C35: =SUMIF($J$5:$J$17,"26 Q4",$I$5:$I$17) -> 25.5825
B36: 27 H2 | C36: =SUMIF($J$5:$J$17,"27 H2",$I$5:$I$17) -> 5.8635
B37: 总计 | C37: =SUM(C32:C36) -> 40.476

Sheet 基金资金安排
A1: 单位：人民币万元 | K1: 基金规模： | L1: 105000
C3: 基金备案实缴 | D3: 认缴注册资本 | E3: 认缴比例 | F3: 终关实缴比例
A4: 成都光宜基金 | C4: 2000 | D4: =SUM(D5:D7) -> 20000 | E4: =D4/$D$11 -> 4
B5: 太保 | C5: =C4*E5 -> 1000 | D5: 10000 | E5: =D5/$D$4 -> 0.5 | F5: =C5/150000 -> 0.0066666667
B6: 国能 | C6: =(C4-C5)/2 -> 500 | D6: 5000 | E6: =D6/$D$4 -> 0.25 | F6: =C6/D6 -> 0.1
B7: GP | C7: =C6 -> 500 | D7: 5000 | E7: =D7/$D$4 -> 0.25 | F7: =C7/D7 -> 0.1
Q9: 基金首期实缴 | R9: 2000
C10: 基金备案实缴 | D10: 认缴注册资本 | E10: 认缴比例 | F10: 实际对基金认缴 | H10: 第二次实缴 | J10: 对应基金比例 | K10: 基金累计实缴门槛需要再次call款 | N10: GP | O10: 5000 | Q10: GP首期实缴 | R10: =R9/L1*O10 -> 95.238095
A11: 深圳新融（GP） | C11: 1031 | D11: 5000 | E11: =D11/$D$11 -> 1 | H11: =1531-C11 -> 500 | J11: =D11/$L$1 -> 0.047619048 | K11: =C11/J11 -> 21651 | L11: =K11/$L$1 -> 0.2062 | N11: LP | O11: 10000
B12: 珠海新融 | C12: 100 | D12: 100 | E12: =D12/$D$11 -> 0.02 | H12: 0 | J12: =D12/$L$1 -> 0.00095238095 | K12: =C12/J12 -> 105000 | L12: =K12/$L$1 -> 1 | M12: =C12/D12 -> 1
B13: 旭智咨询 | C13: =($C$11-$C$12)*D13/SUM($D$13:$D$14) -> 237.5 | D13: 1250 | E13: =D13/$D$11 -> 0.25 | H13: =($H$11)*D13/SUM($D$13:$D$14) -> 127.55102 | J13: =D13/$L$1 -> 0.011904762 | K13: =C13/J13 -> 19950 | L13: =K13/$L$1 -> 0.19 | M13: =C13/D13 -> 0.19
B14: 深圳曦风 | C14: =($C$11-$C$12)*D14/SUM($D$13:$D$14) -> 693.5 | D14: =D11-D12-D13 -> 3650 | E14: =D14/$D$11 -> 0.73 | H14: =($H$11)*D14/SUM($D$13:$D$14) -> 372.44898 | J14: =D14/$L$1 -> 0.034761905 | K14: =C14/J14 -> 19950 | L14: =K14/$L$1 -> 0.19 | M14: =C14/D14 -> 0.19
C15: =SUM(C12:C14)-C11 -> 0
A16: 深圳曦风 | C16: 1100 | D16: =SUM(D17:D18) -> 4900 | E16: =D16/$D$16 -> 1 | F16: =D14 -> 3650 | H16: 0 | J16: =3650/$L$1 -> 0.034761905 | K16: =C16/J16 -> 31643.836 | L16: =K16/$L$1 -> 0.30136986
B17: 旭智新能源 | C17: =$C$16*E17 -> 897.95918 | D17: 4000 | E17: =D17/$D$16 -> 0.81632653 | F17: =ROUNDUP(E17*F16,4) -> 2979.5919 | H17: 0 | J17: =(3650*E17)/$L$1 -> 0.028377065
B18: 旭智私募 | C18: =$C$16*E18 -> 202.04082 | D18: 900 | E18: =D18/$D$16 -> 0.18367347 | F18: =F16-F17 -> 670.4081 | H18: 0 | J18: =(3650*E18)/$L$1 -> 0.0063848397
B19: 剩余资金 | C19: =C16-C14 -> 406.5
L20: 目前认购股份 | N20: 调整 | P20: 调整后认购股份 | R20: 目前已发股份 | T20: 调整 | V20: 调整后已发股份 | X20: 1st Capital call | Z20: 实际缴款total | AA20: 2nd Capital call
A21: 旭智新能源 | C21: =MAX(1040,C17+5) -> 1040 | D21: =SUM(D22:D27) -> 3000 | E21: =SUM(E22:E27) -> 1 | F21: =ROUNDUP(F17,-3) -> 3000 | H21: =D21/$L$1 -> 0.028571429 | I21: =C21/H21 -> 36400 | J21: =I21/$L$1 -> 0.34666667 | L21: Class A | M21: Class B | N21: Class A | O21: Class B | P21: Class A | Q21: Class B | R21: Class A | S21: Class B | T21: Class A | U21: Class B | V21: Class A | W21: Class B | X21: Class A | Y21: Class B | AA21: Class A | AB21: Class B
B22: ACPL | C22: =ROUND($C$21*E22,4) -> 780 | D22: =F22 -> 2250 | E22: =D22/$D$21 -> 0.75 | F22: =F21-SUM(F23:F27) -> 2250 | H22: =D22/$L$1 -> 0.021428571 | K22: =B22 -> ACPL | L22: 20000000 | M22: 0 | N22: =P22-L22 -> -5000000 | O22: =Q22-M22 -> 7500000 | P22: 15000000 | Q22: =F22*10000-P22 -> 7500000 | R22: 5200000 | T22: =V22-R22 -> 0 | U22: =W22-S22 -> 2600000 | V22: =R22 -> 5200000 | W22: =C22*10000-V22 -> 2600000 | X22: =V22 -> 5200000 | Z22: =X22 -> 5200000 | AA22: 0 | AB22: =U22 -> 2600000 | AD22: =AB22+X22-10000 -> 7790000
B23: Reil | C23: =ROUND($C$21*E23,4) -> 173.3333 | D23: 500 | E23: =D23/$D$21 -> 0.16666667 | F23: =D23 -> 500 | H23: =D23/$L$1 -> 0.0047619048 | K23: =B23 -> Reil | L23: 0 | M23: 15000000 | N23: =P23-L23 -> 0 | O23: =Q23-M23 -> -10000000 | Q23: =F23*10000 -> 5000000 | S23: 3900000 | T23: =V23-R23 -> 0 | U23: =W23-S23 -> -2166667 | W23: =C23*10000 -> 1733333 | X23: =V23 -> 0 | Y23: =S23 -> 3900000 | Z23: =W23 -> 1733333 | AA23: =X23 -> 0 | AB23: 0 | AD23: =Z23-Y23 -> -2166667
B24: 黄耀宗 | C24: =ROUND($C$21*E24,4) -> 34.6667 | D24: 100 | E24: =D24/$D$21 -> 0.033333333 | F24: =D24 -> 100 | H24: =D24/$L$1 -> 0.00095238095 | K24: =B24 -> 黄耀宗 | L24: 0 | M24: 1000000 | N24: =P24-L24 -> 0 | O24: =Q24-M24 -> 0 | Q24: =F24*10000 -> 1000000 | S24: 260000 | T24: =V24-R24 -> 0 | U24: =W24-S24 -> 86667 | W24: =C24*10000 -> 346667 | X24: =V24 -> 0 | Y24: =S24 -> 260000 | Z24: =S24 -> 260000 | AA24: =X24 -> 0 | AB24: =U24 -> 86667
